Workbook
Name bimbing1: [1]Daftar!$Q$337:$Q$419
Name bimbing1: Daftar!$Q$315:$Q$397
Name bimbing2: [1]Daftar!$R$337:$R$419
Name bimbing2: Daftar!$R$315:$R$397
Name data: [2]Daftar!$A$5:$U$516
Name data: Daftar!$A$4:$AG$1724
Name dosen: 'Dosen JTE'!$A$5:$E$59
Name dosen: 'Dosen JTE (2)'!$A$5:$E$59
Name dosen: '[2]Dosen JTE'!$A$5:$E$53
Name dosen: rekap!$A$6:$F$45
Name dosen: 'Dosen JTE'!$A$5:$E$60
Name MHS: [3]MHS!$B$3:$C$774
Name penguji: [1]Daftar!$S$4:$U$246
Name penguji: Daftar!$S$4:$U$229

Sheet 000000000

Sheet Daftar
A1: DAFTAR SEMINAR PROPOSAL TUGAS AKHIR PERIODE TAHUN 2010 JURUSAN TEKNIK ELEKTRO FT UNRAM
A3: NO. | B3: TGL SURAT | C3: NAMA | D3: NIM | E3: JUDUL PROPOSAL TUGAS AKHIR | F3: PEMBIMBING 1 | G3: PEMBIMBING 2 | H3: PENGUJI 1 | I3: PENGUJI 2 | J3: PENGUJI 3 | K3: HARI | L3: TANGGAL | M3: WAKTU | N3: TEMPAT | P3: No. Srt Undangan | Q3: 1 | R3: 2 | S3: 3 | T3: 4 | U3: 5 | W3: TGL VALUE | X3: KBK | Y3: DOSEN PA | Z3: MULAI TA | AA3: AKHIR TA | AB3: PERPANJANGAN | AC3: KET | AM3: Hasil | AN3: Ujian | AS3: NAMA | AT3: NIM | AU3: NO.
A4: 1 | C4: =VLOOKUP(D4,'[4]mhs elektro-kecil'!$B$5:$C$1847,2,0) -> Muh. Azhari Zulfani | D4: F1B005048 | E4: Teknik Kompresi Menggunakan Algoritma LZ77 dengan Metode Pencarian Kamus Berbasis Queue untuk Kompresi Teks | F4: Dr. Rismon H. Sianipar, S.T., M.Eng. | G4: Budi Irmawati, S. Kom., M.T. | H4: I B K Widiartha, S.T., M.T. | I4: Heri Wijayanto, S.T., M.T. | J4: Muhamad Irwan, S.T., M.T. | K4: Kamis | L4: 40227 | M4: 10.00-12.00 | O4: Lulus | Q4: 33 | R4: 20 | S4: 27 | T4: 32 | U4: 39 | W4: =TEXT(L4,"dd mmmm yyyy") -> 18 Februari 2010 | X4: =IFERROR(VLOOKUP(D4,'[5]mhs elektro-kecil'!$B$5:$E$2500,3,0),"CEK") -> CEK | Y4: =IFERROR(VLOOKUP(D4,'[5]mhs elektro-kecil'!$B$5:$E$2500,4,0),"CEK") -> CEK | Z4: =L4 -> 40227 | AA4: =Z4+180 -> 40407 | AC4: Lulus | AI4: =MID(D4,5,2) -> 05 | AL4: =IF(MID(D4,5,2)="06",2006,IF(MID(D4,5,2)="07",2007,IF(MID(D4,5,2)="08",2008,IF(MID(D4,5,2)="09",2009,IF(MID(D4,5,2)="10",2010,IF(MID(D4,5,2)="11",2011,IF(MID(D4,5,2)="12",2012,IF(MID(D4,5,2)="05",2005,IF(MID(D4,5,2)="04",2004,IF(MID(D4,5,2)="03",2003,IF(MID(D4,5,2)="13",2013,IF(MID(D4,5,2)="14",2014,IF(MID(D4,5,2)="15",2015,IF(MID(D4,5,2)="16",2016,IF(MID(D4,5,2)="17",2017,IF(MID(D4,5,2)="18",2018,2019)))))))))))))))) -> 2005 | AM4: =COUNTIF([6]Daftar!$D$5:$D$851,D4) -> #VALUE! | AN4: =COUNTIF([7]daftar!$D$4:$D$885,D4) -> #VALUE! | AS4: =C4 -> Muh. Azhari Zulfani | AT4: =D4 -> F1B005048 | AU4: =A4 -> 1
A5: =A4+1 -> 2 | C5: =VLOOKUP(D5,'[4]mhs elektro-kecil'!$B$5:$C$1847,2,0) -> Dea Nur Asri | D5: F1B005010 | E5: Analisa Keandalan Sistem Pembangkit Interkoneksi (Studi Kasus PLTD Ampenan dan PLTD Paok Motong) | F5: Agung Budi Muljono, S.T., M.T. | G5: Supriyatna, S.T., M.T. | H5: Sabar Nababan, S.T., M.T. | I5: Muhammad Firad, S.T. | J5: Ni Made Seniari, S.T., M.T. | K5: Kamis | L5: 40227 | M5: 08.00-10.00 | O5: Lulus | Q5: 13 | R5: 2 | S5: 31 | T5: 11 | U5: 1 | W5: =TEXT(L5,"dd mmmm yyyy") -> 18 Februari 2010 | X5: =IFERROR(VLOOKUP(D5,'[5]mhs elektro-kecil'!$B$5:$E$2500,3,0),"CEK") -> CEK | Y5: =IFERROR(VLOOKUP(D5,'[5]mhs elektro-kecil'!$B$5:$E$2500,4,0),"CEK") -> CEK | Z5: =L5 -> 40227 | AA5: =Z5+180 -> 40407 | AC5: Lulus | AI5: =MID(D5,5,2) -> 05 | AL5: =IF(MID(D5,5,2)="06",2006,IF(MID(D5,5,2)="07",2007,IF(MID(D5,5,2)="08",2008,IF(MID(D5,5,2)="09",2009,IF(MID(D5,5,2)="10",2010,IF(MID(D5,5,2)="11",2011,IF(MID(D5,5,2)="12",2012,IF(MID(D5,5,2)="05",2005,IF(MID(D5,5,2)="04",2004,IF(MID(D5,5,2)="03",2003,IF(MID(D5,5,2)="13",2013,IF(MID(D5,5,2)="14",2014,IF(MID(D5,5,2)="15",2015,IF(MID(D5,5,2)="16",2016,IF(MID(D5,5,2)="17",2017,IF(MID(D5,5,2)="18",2018,2019)))))))))))))))) -> 2005 | AM5: =COUNTIF([6]Daftar!$D$5:$D$851,D5) -> #VALUE! | AN5: =COUNTIF([7]daftar!$D$4:$D$885,D5) -> #VALUE! | AS5: =C5 -> Dea Nur Asri | AT5: =D5 -> F1B005010 | AU5: =A5 -> 2
A6: =A5+1 -> 3 | C6: =VLOOKUP(D6,'[4]mhs elektro-kecil'!$B$5:$C$1847,2,0) -> Fitria Husniayati | D6: F1B005018 | E6: Analisis dan Simulasi Perbaikan Kualitas Daya pada Inverter Merk Usat dengan Pemasangan Filter Pasif | F6: I Made Ari Nrartha, S.T., M.T. | G6: Dr. Warindi, S.T., M.Eng. | H6: Rosmaliati, S.T., M.T. | I6: I Ketut Perdana Putra, S.T., M.T. | J6: Abdullah Zainuddin, S.T., M.T. | K6: Kamis | L6: 40227 | M6: 10.00-12.00 | O6: Lulus | Q6: 25 | R6: 37 | S6: 16 | T6: 23 | U6: 15 | W6: =TEXT(L6,"dd mmmm yyyy") -> 18 Februari 2010 | X6: =IFERROR(VLOOKUP(D6,'[5]mhs elektro-kecil'!$B$5:$E$2500,3,0),"CEK") -> CEK | Y6: =IFERROR(VLOOKUP(D6,'[5]mhs elektro-kecil'!$B$5:$E$2500,4,0),"CEK") -> CEK | Z6: =L6 -> 40227 | AA6: =Z6+180 -> 40407 | AC6: Lulus | AI6: =MID(D6,5,2) -> 05 | AL6: =IF(MID(D6,5,2)="06",2006,IF(MID(D6,5,2)="07",2007,IF(MID(D6,5,2)="08",2008,IF(MID(D6,5,2)="09",2009,IF(MID(D6,5,2)="10",2010,IF(MID(D6,5,2)="11",2011,IF(MID(D6,5,2)="12",2012,IF(MID(D6,5,2)="05",2005,IF(MID(D6,5,2)="04",2004,IF(MID(D6,5,2)="03",2003,IF(MID(D6,5,2)="13",2013,IF(MID(D6,5,2)="14",2014,IF(MID(D6,5,2)="15",2015,IF(MID(D6,5,2)="16",2016,IF(MID(D6,5,2)="17",2017,IF(MID(D6,5,2)="18",2018,2019)))))))))))))))) -> 2005 | AM6: =COUNTIF([6]Daftar!$D$5:$D$851,D6) -> #VALUE! | AN6: =COUNTIF([7]daftar!$D$4:$D$885,D6) -> #VALUE! | AS6: =C6 -> Fitria Husniayati | AT6: =D6 -> F1B005018 | AU6: =A6 -> 3
A7: =A6+1 -> 4 | C7: 7442 | D7: F1B005001 | E7: Pengaturan Kecepatan Motor DC Shunt dengan Buck Converter Menggunakan Metode Pulse Width Modulation Berbasis Mikrokontroler ATMEGA 8535 | F7: I Made Budi Suksmadana, S.T., M.T. | G7: I Made Ari Nrartha, S.T., M.T. | H7: Ida Bagus Fery Citarsa, S.T., M.T. | I7: Abdul Natsir, S.T., M.T. | J7: Bulkis Kanata, S.T., M.T. | K7: Jum'at | L7: 40228 | M7: 08.00-10.00 | O7: Lulus | Q7: 24 | R7: 25 | S7: 12 | T7: 14 | U7: 21 | W7: =TEXT(L7,"dd mmmm yyyy") -> 19 Februari 2010 | X7: =IFERROR(VLOOKUP(D7,'[5]mhs elektro-kecil'!$B$5:$E$2500,3,0),"CEK") -> CEK | Y7: =IFERROR(VLOOKUP(D7,'[5]mhs elektro-kecil'!$B$5:$E$2500,4,0),"CEK") -> CEK | Z7: =L7 -> 40228 | AA7: =Z7+180 -> 40408 | AC7: Lulus | AI7: =MID(D7,5,2) -> 05 | AL7: =IF(MID(D7,5,2)="06",2006,IF(MID(D7,5,2)="07",2007,IF(MID(D7,5,2)="08",2008,IF(MID(D7,5,2)="09",2009,IF(MID(D7,5,2)="10",2010,IF(MID(D7,5,2)="11",2011,IF(MID(D7,5,2)="12",2012,IF(MID(D7,5,2)="05",2005,IF(MID(D7,5,2)="04",2004,IF(MID(D7,5,2)="03",2003,IF(MID(D7,5,2)="13",2013,IF(MID(D7,5,2)="14",2014,IF(MID(D7,5,2)="15",2015,IF(MID(D7,5,2)="16",2016,IF(MID(D7,5,2)="17",2017,IF(MID(D7,5,2)="18",2018,2019)))))))))))))))) -> 2005 | AM7: =COUNTIF([6]Daftar!$D$5:$D$851,D7) -> #VALUE! | AN7: =COUNTIF([7]daftar!$D$4:$D$885,D7) -> #VALUE! | AS7: =C7 -> 7442 | AT7: =D7 -> F1B005001 | AU7: =A7 -> 4
A8: =A7+1 -> 5 | C8: =VLOOKUP(D8,'[4]mhs elektro-kecil'!$B$5:$C$1847,2,0) -> Fahri Alamsyah | D8: F1B003020 | E8: Rancang Bangun Pengatur Intesitas Cahaya Lampu Menggunakan Remote Control Infra Merah | F8: Paniran, S.T., M.T. | G8: Dr. Warindi, S.T., M.Eng. | H8: Sultan, S.T., M.T. | I8: I Ketut Wiryajati, S.T., M.T. | J8: Muhamad Syamsu Iqbal, S.T., M.T., Ph.D. | K8: Sabtu | L8: 40229 | M8: 10.00-12.00 | O8: Lulus | Q8: 28 | R8: 37 | S8: 5 | T8: 3 | U8: 18 | W8: =TEXT(L8,"dd mmmm yyyy") -> 20 Februari 2010 | X8: =IFERROR(VLOOKUP(D8,'[5]mhs elektro-kecil'!$B$5:$E$2500,3,0),"CEK") -> CEK | Y8: =IFERROR(VLOOKUP(D8,'[5]mhs elektro-kecil'!$B$5:$E$2500,4,0),"CEK") -> CEK | Z8: =L8 -> 40229 | AA8: =Z8+180 -> 40409 | AC8: Lulus | AI8: =MID(D8,5,2) -> 03 | AL8: =IF(MID(D8,5,2)="06",2006,IF(MID(D8,5,2)="07",2007,IF(MID(D8,5,2)="08",2008,IF(MID(D8,5,2)="09",2009,IF(MID(D8,5,2)="10",2010,IF(MID(D8,5,2)="11",2011,IF(MID(D8,5,2)="12",2012,IF(MID(D8,5,2)="05",2005,IF(MID(D8,5,2)="04",2004,IF(MID(D8,5,2)="03",2003,IF(MID(D8,5,2)="13",2013,IF(MID(D8,5,2)="14",2014,IF(MID(D8,5,2)="15",2015,IF(MID(D8,5,2)="16",2016,IF(MID(D8,5,2)="17",2017,IF(MID(D8,5,2)="18",2018,2019)))))))))))))))) -> 2003 | AM8: =COUNTIF([6]Daftar!$D$5:$D$851,D8) -> #VALUE! | AN8: =COUNTIF([7]daftar!$D$4:$D$885,D8) -> #VALUE! | AS8: =C8 -> Fahri Alamsyah | AT8: =D8 -> F1B003020 | AU8: =A8 -> 5
A9: =A8+1 -> 6 | C9: =VLOOKUP(D9,'[4]mhs elektro-kecil'!$B$5:$C$1847,2,0) -> Sri Kurniawati | D9: F1B005070 | E9: Merancang dan membuat Aplikasi Game Edukasi untuk Siswa Sekolah Dasar, Studi Kasus pada Mata Pelajaran Bahasa Indonesia | F9: Heri Wijayanto, S.T., M.T. | G9: Ir. Sri Endang Anjarwani, M.Kom. | H9: Dr. Misbahuddin, S.T., M.T. | I9: Sudi M. Al Sasongko, S.T., M.T. | J9: Dr. Ida Ayu Sri Adnyani, S.T., M.Erg. | K9: Sabtu | L9: 40229 | M9: 08.00-10.00 | O9: Lulus | Q9: 32 | R9: 38 | S9: 7 | T9: 6 | U9: 10 | W9: =TEXT(L9,"dd mmmm yyyy") -> 20 Februari 2010 | X9: =IFERROR(VLOOKUP(D9,'[5]mhs elektro-kecil'!$B$5:$E$2500,3,0),"CEK") -> CEK | Y9: =IFERROR(VLOOKUP(D9,'[5]mhs elektro-kecil'!$B$5:$E$2500,4,0),"CEK") -> CEK | Z9: =L9 -> 40229 | AA9: =Z9+180 -> 40409 | AC9: Lulus | AI9: =MID(D9,5,2) -> 05 | AL9: =IF(MID(D9,5,2)="06",2006,IF(MID(D9,5,2)="07",2007,IF(MID(D9,5,2)="08",2008,IF(MID(D9,5,2)="09",2009,IF(MID(D9,5,2)="10",2010,IF(MID(D9,5,2)="11",2011,IF(MID(D9,5,2)="12",2012,IF(MID(D9,5,2)="05",2005,IF(MID(D9,5,2)="04",2004,IF(MID(D9,5,2)="03",2003,IF(MID(D9,5,2)="13",2013,IF(MID(D9,5,2)="14",2014,IF(MID(D9,5,2)="15",2015,IF(MID(D9,5,2)="16",2016,IF(MID(D9,5,2)="17",2017,IF(MID(D9,5,2)="18",2018,2019)))))))))))))))) -> 2005 | AM9: =COUNTIF([6]Daftar!$D$5:$D$851,D9) -> #VALUE! | AN9: =COUNTIF([7]daftar!$D$4:$D$885,D9) -> #VALUE! | AS9: =C9 -> Sri Kurniawati | AT9: =D9 -> F1B005070 | AU9: =A9 -> 6
A10: =A9+1 -> 7 | C10: =VLOOKUP(D10,'[4]mhs elektro-kecil'!$B$5:$C$1847,2,0) -> Faisaludin | D10: F1B005016 | E10: Rancang Bangun Voltage Source Inverter (VSI) untuk Aplikasi Pembangkit Listrik Tenaga Surya (PLTS) | F10: Dr. Warindi, S.T., M.Eng. | G10: I Made Ari Nrartha, S.T., M.T. | H10: Syafarudin Ch, S.T., M.T. | I10: Supriono, S.T., M.T. | J10: I Made Budi Suksmadana, S.T., M.T. | K10: Sabtu | L10: 40229 | M10: 08.00-10.00 | O10: Lulus | Q10: 37 | R10: 25 | S10: 4 | T10: 29 | U10: 24 | W10: =TEXT(L10,"dd mmmm yyyy") -> 20 Februari 2010 | X10: =IFERROR(VLOOKUP(D10,'[5]mhs elektro-kecil'!$B$5:$E$2500,3,0),"CEK") -> CEK | Y10: =IFERROR(VLOOKUP(D10,'[5]mhs elektro-kecil'!$B$5:$E$2500,4,0),"CEK") -> CEK | Z10: =L10 -> 40229 | AA10: =Z10+180 -> 40409 | AB10: =AA10+180 -> 40589 | AD10: 40589 | AI10: =MID(D10,5,2) -> 05 | AL10: =IF(MID(D10,5,2)="06",2006,IF(MID(D10,5,2)="07",2007,IF(MID(D10,5,2)="08",2008,IF(MID(D10,5,2)="09",2009,IF(MID(D10,5,2)="10",2010,IF(MID(D10,5,2)="11",2011,IF(MID(D10,5,2)="12",2012,IF(MID(D10,5,2)="05",2005,IF(MID(D10,5,2)="04",2004,IF(MID(D10,5,2)="03",2003,IF(MID(D10,5,2)="13",2013,IF(MID(D10,5,2)="14",2014,IF(MID(D10,5,2)="15",2015,IF(MID(D10,5,2)="16",2016,IF(MID(D10,5,2)="17",2017,IF(MID(D10,5,2)="18",2018,2019)))))))))))))))) -> 2005 | AM10: =COUNTIF([6]Daftar!$D$5:$D$851,D10) -> #VALUE! | AN10: =COUNTIF([7]daftar!$D$4:$D$885,D10) -> #VALUE! | AS10: =C10 -> Faisaludin | AT10: =D10 -> F1B005016 | AU10: =A10 -> 7
A11: =A10+1 -> 8 | C11: =VLOOKUP(D11,'[4]mhs elektro-kecil'!$B$5:$C$1847,2,0) -> Agra Ananggadipa | D11: F1B005003 | E11: Penggunaan Algoritma Partikel Swarm Optimization Untuk Optimasi Luas Penampang Konduktor pada Jaringan Distribusi Radial Penyulang Airlangga | F11: Rosmaliati, S.T., M.T. | G11: Dr. Misbahuddin, S.T., M.T. | H11: Agung Budi Muljono, S.T., M.T. | I11: Abdul Natsir, S.T., M.T. | J11: Supriyatna, S.T., M.T. | K11: Rabu | L11: 40233 | M11: 08.00-10.00 | O11: Lulus | Q11: 16 | R11: 7 | S11: 13 | T11: 14 | U11: 2 | W11: =TEXT(L11,"dd mmmm yyyy") -> 24 Februari 2010 | X11: =IFERROR(VLOOKUP(D11,'[5]mhs elektro-kecil'!$B$5:$E$2500,3,0),"CEK") -> CEK | Y11: =IFERROR(VLOOKUP(D11,'[5]mhs elektro-kecil'!$B$5:$E$2500,4,0),"CEK") -> CEK | Z11: =L11 -> 40233 | AA11: =Z11+180 -> 40413 | AC11: Lulus | AI11: =MID(D11,5,2) -> 05 | AL11: =IF(MID(D11,5,2)="06",2006,IF(MID(D11,5,2)="07",2007,IF(MID(D11,5,2)="08",2008,IF(MID(D11,5,2)="09",2009,IF(MID(D11,5,2)="10",2010,IF(MID(D11,5,2)="11",2011,IF(MID(D11,5,2)="12",2012,IF(MID(D11,5,2)="05",2005,IF(MID(D11,5,2)="04",2004,IF(MID(D11,5,2)="03",2003,IF(MID(D11,5,2)="13",2013,IF(MID(D11,5,2)="14",2014,IF(MID(D11,5,2)="15",2015,IF(MID(D11,5,2)="16",2016,IF(MID(D11,5,2)="17",2017,IF(MID(D11,5,2)="18",2018,2019)))))))))))))))) -> 2005 | AM11: =COUNTIF([6]Daftar!$D$5:$D$851,D11) -> #VALUE! | AN11: =COUNTIF([7]daftar!$D$4:$D$885,D11) -> #VALUE! | AS11: =C11 -> Agra Ananggadipa | AT11: =D11 -> F1B005003 | AU11: =A11 -> 8
A12: =A11+1 -> 9 | C12: =VLOOKUP(D12,'[4]mhs elektro-kecil'!$B$5:$C$1847,2,0) -> Qitmir Hayatullah | D12: F1B003052 | E12: Perhitungan Posisi Matahari sebagai Alternatif Pembuatan Alat Pengendali Solar Tracker | F12: Syafarudin Ch, S.T., M.T. | G12: Dr. Warindi, S.T., M.Eng. | H12: Muhammad Firad, S.T. | I12: Sultan, S.T., M.T. | J12: Sabar Nababan, S.T., M.T. | K12: Sabtu | L12: 40233 | M12: 08.00-10.00 | O12: Lulus | Q12: 4 | R12: 37 | S12: 11 | T12: 5 | U12: 31 | W12: =TEXT(L12,"dd mmmm yyyy") -> 24 Februari 2010 | X12: =IFERROR(VLOOKUP(D12,'[5]mhs elektro-kecil'!$B$5:$E$2500,3,0),"CEK") -> CEK | Y12: =IFERROR(VLOOKUP(D12,'[5]mhs elektro-kecil'!$B$5:$E$2500,4,0),"CEK") -> CEK | Z12: =L12 -> 40233 | AA12: =Z12+180 -> 40413 | AC12: Lulus | AI12: =MID(D12,5,2) -> 03 | AL12: =IF(MID(D12,5,2)="06",2006,IF(MID(D12,5,2)="07",2007,IF(MID(D12,5,2)="08",2008,IF(MID(D12,5,2)="09",2009,IF(MID(D12,5,2)="10",2010,IF(MID(D12,5,2)="11",2011,IF(MID(D12,5,2)="12",2012,IF(MID(D12,5,2)="05",2005,IF(MID(D12,5,2)="04",2004,IF(MID(D12,5,2)="03",2003,IF(MID(D12,5,2)="13",2013,IF(MID(D12,5,2)="14",2014,IF(MID(D12,5,2)="15",2015,IF(MID(D12,5,2)="16",2016,IF(MID(D12,5,2)="17",2017,IF(MID(D12,5,2)="18",2018,2019)))))))))))))))) -> 2003 | AM12: =COUNTIF([6]Daftar!$D$5:$D$851,D12) -> #VALUE! | AN12: =COUNTIF([7]daftar!$D$4:$D$885,D12) -> #VALUE! | AS12: =C12 -> Qitmir Hayatullah | AT12: =D12 -> F1B003052 | AU12: =A12 -> 9
A13: =A12+1 -> 10 | C13: =VLOOKUP(D13,'[4]mhs elektro-kecil'!$B$5:$C$1847,2,0) -> I Dewa Made Ady Indrawan | D13: F1B005024 | E13: Sistem Informasi Pemesanan Tiket Online Berbasis Java Server Pages (JSP) | F13: Heri Wijayanto, S.T., M.T. | G13: Ir. Sri Endang Anjarwani, M.Kom. | H13: Budi Irmawati, S. Kom., M.T. | I13: I B K Widiartha, S.T., M.T. | J13: Muhamad Irwan, S.T., M.T. | K13: Sabtu | L13: 40243 | M13: 08.00-10.00 | O13: Lulus | Q13: 32 | R13: 38 | S13: 20 | T13: 27 | U13: 39 | W13: =TEXT(L13,"dd mmmm yyyy") -> 06 Maret 2010 | X13: =IFERROR(VLOOKUP(D13,'[5]mhs elektro-kecil'!$B$5:$E$2500,3,0),"CEK") -> CEK | Y13: =IFERROR(VLOOKUP(D13,'[5]mhs elektro-kecil'!$B$5:$E$2500,4,0),"CEK") -> CEK | Z13: =L13 -> 40243 | AA13: =Z13+180 -> 40423 | AC13: Lulus | AI13: =MID(D13,5,2) -> 05 | AL13: =IF(MID(D13,5,2)="06",2006,IF(MID(D13,5,2)="07",2007,IF(MID(D13,5,2)="08",2008,IF(MID(D13,5,2)="09",2009,IF(MID(D13,5,2)="10",2010,IF(MID(D13,5,2)="11",2011,IF(MID(D13,5,2)="12",2012,IF(MID(D13,5,2)="05",2005,IF(MID(D13,5,2)="04",2004,IF(MID(D13,5,2)="03",2003,IF(MID(D13,5,2)="13",2013,IF(MID(D13,5,2)="14",2014,IF(MID(D13,5,2)="15",2015,IF(MID(D13,5,2)="16",2016,IF(MID(D13,5,2)="17",2017,IF(MID(D13,5,2)="18",2018,2019)))))))))))))))) -> 2005 | AM13: =COUNTIF([6]Daftar!$D$5:$D$851,D13) -> #VALUE! | AN13: =COUNTIF([7]daftar!$D$4:$D$885,D13) -> #VALUE! | AS13: =C13 -> I Dewa Made Ady Indrawan | AT13: =D13 -> F1B005024 | AU13: =A13 -> 10
A14: =A13+1 -> 11 | C14: =VLOOKUP(D14,'[4]mhs elektro-kecil'!$B$5:$C$1847,2,0) -> Siti Septi | D14: F1B005068 | E14: Pengaruh Faktor Meteorologi Terhadap Lokasi Penempatan Pembangkit Listrik Tenaga Surya (PLTS) di Pulau Lombok | F14: Rosmaliati, S.T., M.T. | G14: Ida Bagus Fery Citarsa, S.T., M.T. | H14: Ni Made Seniari, S.T., M.T. | I14: Supriono, S.T., M.T. | J14: I Ketut Wiryajati, S.T., M.T. | K14: Sabtu | L14: 40243 | M14: 08.00-10.00 | O14: Lulus | Q14: 16 | R14: 12 | S14: 1 | T14: 29 | U14: 3 | W14: =TEXT(L14,"dd mmmm yyyy") -> 06 Maret 2010 | X14: =IFERROR(VLOOKUP(D14,'[5]mhs elektro-kecil'!$B$5:$E$2500,3,0),"CEK") -> CEK | Y14: =IFERROR(VLOOKUP(D14,'[5]mhs elektro-kecil'!$B$5:$E$2500,4,0),"CEK") -> CEK | Z14: =L14 -> 40243 | AA14: =Z14+180 -> 40423 | AB14: =AA14+180 -> 40603 | AC14: Lulus | AD14: 40603 | AI14: =MID(D14,5,2) -> 05 | AL14: =IF(MID(D14,5,2)="06",2006,IF(MID(D14,5,2)="07",2007,IF(MID(D14,5,2)="08",2008,IF(MID(D14,5,2)="09",2009,IF(MID(D14,5,2)="10",2010,IF(MID(D14,5,2)="11",2011,IF(MID(D14,5,2)="12",2012,IF(MID(D14,5,2)="05",2005,IF(MID(D14,5,2)="04",2004,IF(MID(D14,5,2)="03",2003,IF(MID(D14,5,2)="13",2013,IF(MID(D14,5,2)="14",2014,IF(MID(D14,5,2)="15",2015,IF(MID(D14,5,2)="16",2016,IF(MID(D14,5,2)="17",2017,IF(MID(D14,5,2)="18",2018,2019)))))))))))))))) -> 2005 | AM14: =COUNTIF([6]Daftar!$D$5:$D$851,D14) -> #VALUE! | AN14: =COUNTIF([7]daftar!$D$4:$D$885,D14) -> #VALUE! | AS14: =C14 -> Siti Septi | AT14: =D14 -> F1B005068 | AU14: =A14 -> 11
A15: =A14+1 -> 12 | C15: =VLOOKUP(D15,'[4]mhs elektro-kecil'!$B$5:$C$1847,2,0) -> Fithra Mubarak | D15: F1B005017 | E15: Optimasi Kinerja Navigasi Robot Berbasis Mikrokontroller Seri AVR Atmega 8535 Menggunakan Metode Logika Fuzzy | F15: I Made Budi Suksmadana, S.T., M.T. | G15: Paniran, S.T., M.T. | H15: Syafarudin Ch, S.T., M.T. | I15: Bulkis Kanata, S.T., M.T. | J15: Ir. Sri Endang Anjarwani, M.Kom. | K15: Sabtu | L15: 40257 | M15: 08.00-10.00 | O15: Lulus | Q15: 24 | R15: 28 | S15: 4 | T15: 21 | U15: 38 | W15: =TEXT(L15,"dd mmmm yyyy") -> 20 Maret 2010 | X15: =IFERROR(VLOOKUP(D15,'[5]mhs elektro-kecil'!$B$5:$E$2151,3,0),"CEK") -> CEK | Y15: =IFERROR(VLOOKUP(D15,'[5]mhs elektro-kecil'!$B$5:$E$2151,4,0),"CEK") -> CEK | Z15: =L15 -> 40257 | AA15: =Z15+180 -> 40437 | AC15: Lulus | AI15: =MID(D15,5,2) -> 05 | AL15: =IF(MID(D15,5,2)="06",2006,IF(MID(D15,5,2)="07",2007,IF(MID(D15,5,2)="08",2008,IF(MID(D15,5,2)="09",2009,IF(MID(D15,5,2)="10",2010,IF(MID(D15,5,2)="11",2011,IF(MID(D15,5,2)="12",2012,IF(MID(D15,5,2)="05",2005,IF(MID(D15,5,2)="04",2004,IF(MID(D15,5,2)="03",2003,IF(MID(D15,5,2)="13",2013,IF(MID(D15,5,2)="14",2014,IF(MID(D15,5,2)="15",2015,IF(MID(D15,5,2)="16",2016,IF(MID(D15,5,2)="17",2017,IF(MID(D15,5,2)="18",2018,2019)))))))))))))))) -> 2005 | AM15: =COUNTIF([6]Daftar!$D$5:$D$851,D15) -> #VALUE! | AN15: =COUNTIF([7]daftar!$D$4:$D$885,D15) -> #VALUE! | AS15: =C15 -> Fithra Mubarak | AT15: =D15 -> F1B005017 | AU15: =A15 -> 12
A16: =A15+1 -> 13 | C16: =VLOOKUP(D16,'[4]mhs elektro-kecil'!$B$5:$C$1847,2,0) -> Rematomatra Rahmansyah | D16: F1B005062 | E16: Implementasi Algoritma LZW Menggunakan Metode Pencarian Kamus Berbasis Hash Table untuk Kompresi File Teks | F16: Dr. Rismon H. Sianipar, S.T., M.Eng. | G16: Ir. Sri Endang Anjarwani, M.Kom. | H16: Heri Wijayanto, S.T., M.T. | I16: Paniran, S.T., M.T. | J16: Budi Irmawati, S. Kom., M.T. | K16: Sabtu | L16: 40264 | M16: 10.00-12.00 | O16: Lulus | Q16: 33 | R16: 38 | S16: 32 | T16: 28 | U16: 20 | W16: =TEXT(L16,"dd mmmm yyyy") -> 27 Maret 2010 | X16: =IFERROR(VLOOKUP(D16,'[5]mhs elektro-kecil'!$B$5:$E$2151,3,0),"CEK") -> CEK | Y16: =IFERROR(VLOOKUP(D16,'[5]mhs elektro-kecil'!$B$5:$E$2151,4,0),"CEK") -> CEK | Z16: =L16 -> 40264 | AA16: =Z16+180 -> 40444 | AC16: Lulus | AI16: =MID(D16,5,2) -> 05 | AL16: =IF(MID(D16,5,2)="06",2006,IF(MID(D16,5,2)="07",2007,IF(MID(D16,5,2)="08",2008,IF(MID(D16,5,2)="09",2009,IF(MID(D16,5,2)="10",2010,IF(MID(D16,5,2)="11",2011,IF(MID(D16,5,2)="12",2012,IF(MID(D16,5,2)="05",2005,IF(MID(D16,5,2)="04",2004,IF(MID(D16,5,2)="03",2003,IF(MID(D16,5,2)="13",2013,IF(MID(D16,5,2)="14",2014,IF(MID(D16,5,2)="15",2015,IF(MID(D16,5,2)="16",2016,IF(MID(D16,5,2)="17",2017,IF(MID(D16,5,2)="18",2018,2019)))))))))))))))) -> 2005 | AM16: =COUNTIF([6]Daftar!$D$5:$D$851,D16) -> #VALUE! | AN16: =COUNTIF([7]daftar!$D$4:$D$885,D16) -> #VALUE! | AS16: =C16 -> Rematomatra Rahmansyah | AT16: =D16 -> F1B005062 | AU16: =A16 -> 13
A17: =A16+1 -> 14 | C17: =VLOOKUP(D17,'[4]mhs elektro-kecil'!$B$5:$C$1847,2,0) -> Aditya Putra | D17: F1B005002 | E17: Perancangan Game Edukasi Matematika SD Menggunakan Macromedia Flash | F17: Dr. Rismon H. Sianipar, S.T., M.Eng. | G17: Ir. Sri Endang Anjarwani, M.Kom. | H17: Made Sutha Yadnya, S.T., M.T. | I17: I B K Widiartha, S.T., M.T. | J17: Budi Irmawati, S. Kom., M.T. | K17: Sabtu | L17: 40271 | M17: 10.00-12.00 | O17: Lulus | Q17: 33 | R17: 38 | S17: 19 | T17: 27 | U17: 20 | W17: =TEXT(L17,"dd mmmm yyyy") -> 03 April 2010 | X17: =IFERROR(VLOOKUP(D17,'[5]mhs elektro-kecil'!$B$5:$E$2151,3,0),"CEK") -> CEK | Y17: =IFERROR(VLOOKUP(D17,'[5]mhs elektro-kecil'!$B$5:$E$2151,4,0),"CEK") -> CEK | Z17: =L17 -> 40271 | AA17: =Z17+180 -> 40451 | AC17: Lulus | AI17: =MID(D17,5,2) -> 05 | AL17: =IF(MID(D17,5,2)="06",2006,IF(MID(D17,5,2)="07",2007,IF(MID(D17,5,2)="08",2008,IF(MID(D17,5,2)="09",2009,IF(MID(D17,5,2)="10",2010,IF(MID(D17,5,2)="11",2011,IF(MID(D17,5,2)="12",2012,IF(MID(D17,5,2)="05",2005,IF(MID(D17,5,2)="04",2004,IF(MID(D17,5,2)="03",2003,IF(MID(D17,5,2)="13",2013,IF(MID(D17,5,2)="14",2014,IF(MID(D17,5,2)="15",2015,IF(MID(D17,5,2)="16",2016,IF(MID(D17,5,2)="17",2017,IF(MID(D17,5,2)="18",2018,2019)))))))))))))))) -> 2005 | AM17: =COUNTIF([6]Daftar!$D$5:$D$851,D17) -> #VALUE! | AN17: =COUNTIF([7]daftar!$D$4:$D$885,D17) -> #VALUE! | AS17: =C17 -> Aditya Putra | AT17: =D17 -> F1B005002 | AU17: =A17 -> 14
A18: =A17+1 -> 15 | B18: 40282 | C18: =VLOOKUP(D18,'[4]mhs elektro-kecil'!$B$5:$C$1847,2,0) -> Alpan Hadi | D18: F1B005005 | E18: Pengatur Posisi Ketinggian Tiang Mikrofof Otomatis Berbasis Mikrokontroler Seri AVR ATMega 8535 | F18: Paniran, S.T., M.T. | G18: Syafarudin Ch, S.T., M.T. | H18: Abdullah Zainuddin, S.T., M.T. | I18: Sudi M. Al Sasongko, S.T., M.T. | J18: Djul Fikry Budiman, S.T., M.T. | K18: Senin | L18: 40289 | M18: 10.00-12.00 | N18: D2 | O18: Lulus | Q18: 28 | R18: 4 | S18: 15 | T18: 6 | U18: 35 | W18: =TEXT(L18,"dd mmmm yyyy") -> 21 April 2010 | X18: =IFERROR(VLOOKUP(D18,'[5]mhs elektro-kecil'!$B$5:$E$2151,3,0),"CEK") -> CEK | Y18: =IFERROR(VLOOKUP(D18,'[5]mhs elektro-kecil'!$B$5:$E$2151,4,0),"CEK") -> CEK | Z18: =L18 -> 40289 | AA18: =Z18+180 -> 40469 | AC18: Lulus | AI18: =MID(D18,5,2) -> 05 | AL18: =IF(MID(D18,5,2)="06",2006,IF(MID(D18,5,2)="07",2007,IF(MID(D18,5,2)="08",2008,IF(MID(D18,5,2)="09",2009,IF(MID(D18,5,2)="10",2010,IF(MID(D18,5,2)="11",2011,IF(MID(D18,5,2)="12",2012,IF(MID(D18,5,2)="05",2005,IF(MID(D18,5,2)="04",2004,IF(MID(D18,5,2)="03",2003,IF(MID(D18,5,2)="13",2013,IF(MID(D18,5,2)="14",2014,IF(MID(D18,5,2)="15",2015,IF(MID(D18,5,2)="16",2016,IF(MID(D18,5,2)="17",2017,IF(MID(D18,5,2)="18",2018,2019)))))))))))))))) -> 2005 | AM18: =COUNTIF([6]Daftar!$D$5:$D$851,D18) -> #VALUE! | AN18: =COUNTIF([7]daftar!$D$4:$D$885,D18) -> #VALUE! | AS18: =C18 -> Alpan Hadi | AT18: =D18 -> F1B005005 | AU18: =A18 -> 15
A19: =A18+1 -> 16 | B19: 40301 | C19: =VLOOKUP(D19,'[4]mhs elektro-kecil'!$B$5:$C$1847,2,0) -> Muhammad Wahyudi | D19: F1B005053 | E19: Rancang Bangun Alat Pengendali Penerangan Ruangan Menggunakan Metode Fuzzy Logic Berbasis Mikrokontroler ATMEGA8535 | F19: I Made Budi Suksmadana, S.T., M.T. | G19: Dr. Misbahuddin, S.T., M.T. | H19: Paniran, S.T., M.T. | I19: Sultan, S.T., M.T. | J19: I Ketut Wiryajati, S.T., M.T. | K19: Sabtu | L19: 40306 | M19: 08.00-10.00 | N19: R. Studio | O19: Lulus | Q19: 24 | R19: 7 | S19: 28 | T19: 5 | U19: 3 | W19: =TEXT(L19,"dd mmmm yyyy") -> 08 Mei 2010 | X19: =IFERROR(VLOOKUP(D19,'[5]mhs elektro-kecil'!$B$5:$E$2151,3,0),"CEK") -> CEK | Y19: =IFERROR(VLOOKUP(D19,'[5]mhs elektro-kecil'!$B$5:$E$2151,4,0),"CEK") -> CEK | Z19: =L19 -> 40306 | AA19: =Z19+180 -> 40486 | AB19: =AA19+180 -> 40666 | AC19: Lulus | AI19: =MID(D19,5,2) -> 05 | AL19: =IF(MID(D19,5,2)="06",2006,IF(MID(D19,5,2)="07",2007,IF(MID(D19,5,2)="08",2008,IF(MID(D19,5,2)="09",2009,IF(MID(D19,5,2)="10",2010,IF(MID(D19,5,2)="11",2011,IF(MID(D19,5,2)="12",2012,IF(MID(D19,5,2)="05",2005,IF(MID(D19,5,2)="04",2004,IF(MID(D19,5,2)="03",2003,IF(MID(D19,5,2)="13",2013,IF(MID(D19,5,2)="14",2014,IF(MID(D19,5,2)="15",2015,IF(MID(D19,5,2)="16",2016,IF(MID(D19,5,2)="17",2017,IF(MID(D19,5,2)="18",2018,2019)))))))))))))))) -> 2005 | AM19: =COUNTIF([6]Daftar!$D$5:$D$851,D19) -> #VALUE! | AN19: =COUNTIF([7]daftar!$D$4:$D$885,D19) -> #VALUE! | AS19: =C19 -> Muhammad Wahyudi | AT19: =D19 -> F1B005053 | AU19: =A19 -> 16
A20: =A19+1 -> 17 | B20: 40305 | C20: =VLOOKUP(D20,'[4]mhs elektro-kecil'!$B$5:$C$1847,2,0) -> Satriasyah Haris S. | D20: F1B003062 | E20: Analisa Kelayakan Implementasi Internet Protokol Television (IP-Tv) Berbasis Perangkat Lunak Open Source | F20: Dr. Misbahuddin, S.T., M.T. | G20: Heri Wijayanto, S.T., M.T. | H20: Muhamad Syamsu Iqbal, S.T., M.T., Ph.D. | I20: I B K Widiartha, S.T., M.T. | J20: Muhamad Irwan, S.T., M.T. | K20: Sabtu | L20: 40306 | M20: 10.00-12.00 | N20: R. Studio | O20: Lulus | Q20: 7 | R20: 32 | S20: 18 | T20: 27 | U20: 39 | W20: =TEXT(L20,"dd mmmm yyyy") -> 08 Mei 2010 | X20: =IFERROR(VLOOKUP(D20,'[5]mhs elektro-kecil'!$B$5:$E$2151,3,0),"CEK") -> CEK | Y20: =IFERROR(VLOOKUP(D20,'[5]mhs elektro-kecil'!$B$5:$E$2151,4,0),"CEK") -> CEK | Z20: =L20 -> 40306 | AA20: =Z20+180 -> 40486 | AC20: Lulus | AI20: =MID(D20,5,2) -> 03 | AL20: =IF(MID(D20,5,2)="06",2006,IF(MID(D20,5,2)="07",2007,IF(MID(D20,5,2)="08",2008,IF(MID(D20,5,2)="09",2009,IF(MID(D20,5,2)="10",2010,IF(MID(D20,5,2)="11",2011,IF(MID(D20,5,2)="12",2012,IF(MID(D20,5,2)="05",2005,IF(MID(D20,5,2)="04",2004,IF(MID(D20,5,2)="03",2003,IF(MID(D20,5,2)="13",2013,IF(MID(D20,5,2)="14",2014,IF(MID(D20,5,2)="15",2015,IF(MID(D20,5,2)="16",2016,IF(MID(D20,5,2)="17",2017,IF(MID(D20,5,2)="18",2018,2019)))))))))))))))) -> 2003 | AM20: =COUNTIF([6]Daftar!$D$5:$D$851,D20) -> #VALUE! | AN20: =COUNTIF([7]daftar!$D$4:$D$885,D20) -> #VALUE! | AS20: =C20 -> Satriasyah Haris S. | AT20: =D20 -> F1B003062 | AU20: =A20 -> 17
A21: =A20+1 -> 18 | B21: 40308 | C21: =VLOOKUP(D21,'[4]mhs elektro-kecil'!$B$5:$C$1847,2,0) -> Trie Adriany Sofiana | D21: F1B006083 | E21: Penentuan Posisi Sensor Mitigasi Curah Hujan untuk Komunikasi LMDS dengan Metode SST (Synthetic Storm Technique) di Mataram | F21: Made Sutha Yadnya, S.T., M.T. | G21: Djul Fikry Budiman, S.T., M.T. | H21: Sudi M. Al Sasongko, S.T., M.T. | I21: Muhamad Syamsu Iqbal, S.T., M.T., Ph.D. | J21: Bulkis Kanata, S.T., M.T. | K21: Sabtu | L21: 40313 | M21: 10.00-12.00 | N21: R. Lab. Elka & Digital | O21: Lulus | Q21: 19 | R21: 35 | S21: 6 | T21: 18 | U21: 21 | W21: =TEXT(L21,"dd mmmm yyyy") -> 15 Mei 2010 | X21: =IFERROR(VLOOKUP(D21,'[5]mhs elektro-kecil'!$B$5:$E$2151,3,0),"CEK") -> CEK | Y21: =IFERROR(VLOOKUP(D21,'[5]mhs elektro-kecil'!$B$5:$E$2151,4,0),"CEK") -> CEK | Z21: =L21 -> 40313 | AA21: =Z21+180 -> 40493 | AC21: Lulus | AI21: =MID(D21,5,2) -> 06 | AL21: =IF(MID(D21,5,2)="06",2006,IF(MID(D21,5,2)="07",2007,IF(MID(D21,5,2)="08",2008,IF(MID(D21,5,2)="09",2009,IF(MID(D21,5,2)="10",2010,IF(MID(D21,5,2)="11",2011,IF(MID(D21,5,2)="12",2012,IF(MID(D21,5,2)="05",2005,IF(MID(D21,5,2)="04",2004,IF(MID(D21,5,2)="03",2003,IF(MID(D21,5,2)="13",2013,IF(MID(D21,5,2)="14",2014,IF(MID(D21,5,2)="15",2015,IF(MID(D21,5,2)="16",2016,IF(MID(D21,5,2)="17",2017,IF(MID(D21,5,2)="18",2018,2019)))))))))))))))) -> 2006 | AM21: =COUNTIF([6]Daftar!$D$5:$D$851,D21) -> #VALUE! | AN21: =COUNTIF([7]daftar!$D$4:$D$885,D21) -> #VALUE! | AS21: =C21 -> Trie Adriany Sofiana | AT21: =D21 -> F1B006083 | AU21: =A21 -> 18
A22: =A21+1 -> 19 | B22: 40329 | C22: =VLOOKUP(D22,'[4]mhs elektro-kecil'!$B$5:$C$1847,2,0) -> Isnu Handibrata Eko Putra | D22: F1B006042 | E22: Analisis Stabilitas Transien pada Sistem Tenaga Listrik Pulau Lombok Menggunakan Kriteria Luas Sama dan Jaringan Syaraf Tiruan | F22: Abdul Natsir, S.T., M.T. | G22: I Made Ari Nrartha, S.T., M.T. | H22: Rosmaliati, S.T., M.T. | I22: I Ketut Perdana Putra, S.T., M.T. | J22: Supriono, S.T., M.T. | K22: Sabtu | L22: 40334 | M22: 08.00-10.00 | N22: R. D2 | O22: Lulus | Q22: 14 | R22: 25 | S22: 16 | T22: 23 | U22: 29 | W22: =TEXT(L22,"dd mmmm yyyy") -> 05 Juni 2010 | X22: =IFERROR(VLOOKUP(D22,'[5]mhs elektro-kecil'!$B$5:$E$2151,3,0),"CEK") -> CEK | Y22: =IFERROR(VLOOKUP(D22,'[5]mhs elektro-kecil'!$B$5:$E$2151,4,0),"CEK") -> CEK | Z22: =L22 -> 40334 | AA22: =Z22+180 -> 40514 | AC22: Lulus | AI22: =MID(D22,5,2) -> 06 | AL22: =IF(MID(D22,5,2)="06",2006,IF(MID(D22,5,2)="07",2007,IF(MID(D22,5,2)="08",2008,IF(MID(D22,5,2)="09",2009,IF(MID(D22,5,2)="10",2010,IF(MID(D22,5,2)="11",2011,IF(MID(D22,5,2)="12",2012,IF(MID(D22,5,2)="05",2005,IF(MID(D22,5,2)="04",2004,IF(MID(D22,5,2)="03",2003,IF(MID(D22,5,2)="13",2013,IF(MID(D22,5,2)="14",2014,IF(MID(D22,5,2)="15",2015,IF(MID(D22,5,2)="16",2016,IF(MID(D22,5,2)="17",2017,IF(MID(D22,5,2)="18",2018,2019)))))))))))))))) -> 2006 | AM22: =COUNTIF([6]Daftar!$D$5:$D$851,D22) -> #VALUE! | AN22: =COUNTIF([7]daftar!$D$4:$D$885,D22) -> #VALUE! | AS22: =C22 -> Isnu Handibrata Eko Putra | AT22: =D22 -> F1B006042 | AU22: =A22 -> 19
A23: =A22+1 -> 20 | B23: 40329 | C23: =VLOOKUP(D23,'[4]mhs elektro-kecil'!$B$5:$C$1847,2,0) -> Agus Nugroho | D23: F1B002003 | E23: Rancang Bangun Pembangkit Listrik Tenaga Angin (PLTB) dengan Menggunakan Turbin Savonius | F23: Sabar Nababan, S.T., M.T. | G23: Agung Budi Muljono, S.T., M.T. | H23: Ni Made Seniari, S.T., M.T. | I23: Supriyatna, S.T., M.T. | J23: I Ketut Perdana Putra, S.T., M.T. | K23: Sabtu | L23: 40334 | M23: 10.00-12.00 | N23: R. D2 | O23: Lulus | Q23: 31 | R23: 13 | S23: 1 | T23: 2 | U23: 23 | W23: =TEXT(L23,"dd mmmm yyyy") -> 05 Juni 2010 | X23: =IFERROR(VLOOKUP(D23,'[5]mhs elektro-kecil'!$B$5:$E$2151,3,0),"CEK") -> CEK | Y23: =IFERROR(VLOOKUP(D23,'[5]mhs elektro-kecil'!$B$5:$E$2151,4,0),"CEK") -> CEK | Z23: =L23 -> 40334 | AA23: =Z23+180 -> 40514 | AB23: =AA23+180 -> 40694 | AC23: Lulus | AI23: =MID(D23,5,2) -> 02 | AL23: =IF(MID(D23,5,2)="06",2006,IF(MID(D23,5,2)="07",2007,IF(MID(D23,5,2)="08",2008,IF(MID(D23,5,2)="09",2009,IF(MID(D23,5,2)="10",2010,IF(MID(D23,5,2)="11",2011,IF(MID(D23,5,2)="12",2012,IF(MID(D23,5,2)="05",2005,IF(MID(D23,5,2)="04",2004,IF(MID(D23,5,2)="03",2003,IF(MID(D23,5,2)="13",2013,IF(MID(D23,5,2)="14",2014,IF(MID(D23,5,2)="15",2015,IF(MID(D23,5,2)="16",2016,IF(MID(D23,5,2)="17",2017,IF(MID(D23,5,2)="18",2018,2019)))))))))))))))) -> 2019 | AM23: =COUNTIF([6]Daftar!$D$5:$D$851,D23) -> #VALUE! | AN23: =COUNTIF([7]daftar!$D$4:$D$885,D23) -> #VALUE! | AS23: =C23 -> Agus Nugroho | AT23: =D23 -> F1B002003 | AU23: =A23 -> 20
A24: =A23+1 -> 21 | B24: 40329 | C24: =VLOOKUP(D24,'[4]mhs elektro-kecil'!$B$5:$C$1847,2,0) -> Parlinawati | D24: F1B005059 | E24: Simulasi dan Analisis Perbandingan Kinerja Sistem OFCDM Berbasis Wavelet terhadap Sistem OFCDM Berbasis FFT | F24: Sudi M. Al Sasongko, S.T., M.T. | G24: I Made Budi Suksmadana, S.T., M.T. | H24: Abdullah Zainuddin, S.T., M.T. | I24: Made Sutha Yadnya, S.T., M.T. | J24: Muhamad Syamsu Iqbal, S.T., M.T., Ph.D. | K24: Sabtu | L24: 40334 | M24: 10.00-12.00 | N24: R. Studio | O24: Lulus | Q24: 6 | R24: 24 | S24: 15 | T24: 19 | U24: 18 | W24: =TEXT(L24,"dd mmmm yyyy") -> 05 Juni 2010 | X24: =IFERROR(VLOOKUP(D24,'[5]mhs elektro-kecil'!$B$5:$E$2151,3,0),"CEK") -> CEK | Y24: =IFERROR(VLOOKUP(D24,'[5]mhs elektro-kecil'!$B$5:$E$2151,4,0),"CEK") -> CEK | Z24: =L24 -> 40334 | AA24: =Z24+180 -> 40514 | AB24: =AA24+180 -> 40694 | AI24: =MID(D24,5,2) -> 05 | AL24: =IF(MID(D24,5,2)="06",2006,IF(MID(D24,5,2)="07",2007,IF(MID(D24,5,2)="08",2008,IF(MID(D24,5,2)="09",2009,IF(MID(D24,5,2)="10",2010,IF(MID(D24,5,2)="11",2011,IF(MID(D24,5,2)="12",2012,IF(MID(D24,5,2)="05",2005,IF(MID(D24,5,2)="04",2004,IF(MID(D24,5,2)="03",2003,IF(MID(D24,5,2)="13",2013,IF(MID(D24,5,2)="14",2014,IF(MID(D24,5,2)="15",2015,IF(MID(D24,5,2)="16",2016,IF(MID(D24,5,2)="17",2017,IF(MID(D24,5,2)="18",2018,2019)))))))))))))))) -> 2005 | AM24: =COUNTIF([6]Daftar!$D$5:$D$851,D24) -> #VALUE! | AN24: =COUNTIF([7]daftar!$D$4:$D$885,D24) -> #VALUE! | AS24: =C24 -> Parlinawati | AT24: =D24 -> F1B005059 | AU24: =A24 -> 21
A25: =A24+1 -> 22 | B25: 40329 | C25: =VLOOKUP(D25,'[4]mhs elektro-kecil'!$B$5:$C$1847,2,0) -> Eddy Kurniawan | D25: F1B003014 | E25: Data Encryption Standard (DES) Cryptosystem Berfungsi sebagai Fungsi Hash untuk Menguji Integritas Sinyal Audio | F25: Dr. Rismon H. Sianipar, S.T., M.Eng. | G25: Heri Wijayanto, S.T., M.T. | H25: I B K Widiartha, S.T., M.T. | I25: Muhamad Irwan, S.T., M.T. | J25: Budi Irmawati, S. Kom., M.T. | K25: Rabu | L25: 40338 | M25: 10.00-12.00 | N25: R. WLTI | O25: Lulus | Q25: 33 | R25: 32 | S25: 27 | T25: 39 | U25: 20 | W25: =TEXT(L25,"dd mmmm yyyy") -> 09 Juni 2010 | X25: =IFERROR(VLOOKUP(D25,'[5]mhs elektro-kecil'!$B$5:$E$2151,3,0),"CEK") -> CEK | Y25: =IFERROR(VLOOKUP(D25,'[5]mhs elektro-kecil'!$B$5:$E$2151,4,0),"CEK") -> CEK | Z25: =L25 -> 40338 | AA25: =Z25+180 -> 40518 | AC25: Lulus | AI25: =MID(D25,5,2) -> 03 | AL25: =IF(MID(D25,5,2)="06",2006,IF(MID(D25,5,2)="07",2007,IF(MID(D25,5,2)="08",2008,IF(MID(D25,5,2)="09",2009,IF(MID(D25,5,2)="10",2010,IF(MID(D25,5,2)="11",2011,IF(MID(D25,5,2)="12",2012,IF(MID(D25,5,2)="05",2005,IF(MID(D25,5,2)="04",2004,IF(MID(D25,5,2)="03",2003,IF(MID(D25,5,2)="13",2013,IF(MID(D25,5,2)="14",2014,IF(MID(D25,5,2)="15",2015,IF(MID(D25,5,2)="16",2016,IF(MID(D25,5,2)="17",2017,IF(MID(D25,5,2)="18",2018,2019)))))))))))))))) -> 2003 | AM25: =COUNTIF([6]Daftar!$D$5:$D$851,D25) -> #VALUE! | AN25: =COUNTIF([7]daftar!$D$4:$D$885,D25) -> #VALUE! | AS25: =C25 -> Eddy Kurniawan | AT25: =D25 -> F1B003014 | AU25: =A25 -> 22
A26: =A25+1 -> 23 | B26: 40338 | C26: =VLOOKUP(D26,'[4]mhs elektro-kecil'!$B$5:$C$1847,2,0) -> I Gusti Ayu Ita Kusmira | D26: F1B006034 | E26: Economi Dispatch Menggunakan Algoritma Genetika (Studi Kasus : Sistem Kelistrikan Lombok) | F26: Agung Budi Muljono, S.T., M.T. | G26: I Made Ari Nrartha, S.T., M.T. | H26: Dr.rer.nat. Teti Zubaidah, S.T., M.T. | I26: Ida Bagus Fery Citarsa, S.T., M.T. | J26: Supriyatna, S.T., M.T. | K26: Sabtu | L26: 40341 | M26: 08.00-10.00 | N26: R. D2 | O26: Lulus | Q26: 13 | R26: 25 | S26: 22 | T26: 12 | U26: 2 | W26: =TEXT(L26,"dd mmmm yyyy") -> 12 Juni 2010 | X26: =IFERROR(VLOOKUP(D26,'[5]mhs elektro-kecil'!$B$5:$E$2151,3,0),"CEK") -> CEK | Y26: =IFERROR(VLOOKUP(D26,'[5]mhs elektro-kecil'!$B$5:$E$2151,4,0),"CEK") -> CEK | Z26: =L26 -> 40341 | AA26: =Z26+180 -> 40521 | AC26: Lulus | AI26: =MID(D26,5,2) -> 06 | AL26: =IF(MID(D26,5,2)="06",2006,IF(MID(D26,5,2)="07",2007,IF(MID(D26,5,2)="08",2008,IF(MID(D26,5,2)="09",2009,IF(MID(D26,5,2)="10",2010,IF(MID(D26,5,2)="11",2011,IF(MID(D26,5,2)="12",2012,IF(MID(D26,5,2)="05",2005,IF(MID(D26,5,2)="04",2004,IF(MID(D26,5,2)="03",2003,IF(MID(D26,5,2)="13",2013,IF(MID(D26,5,2)="14",2014,IF(MID(D26,5,2)="15",2015,IF(MID(D26,5,2)="16",2016,IF(MID(D26,5,2)="17",2017,IF(MID(D26,5,2)="18",2018,2019)))))))))))))))) -> 2006 | AM26: =COUNTIF([6]Daftar!$D$5:$D$851,D26) -> #VALUE! | AN26: =COUNTIF([7]daftar!$D$4:$D$885,D26) -> #VALUE! | AS26: =C26 -> I Gusti Ayu Ita Kusmira | AT26: =D26 -> F1B006034 | AU26: =A26 -> 23
A27: =A26+1 -> 24 | B27: 40338 | C27: =VLOOKUP(D27,'[4]mhs elektro-kecil'!$B$5:$C$1847,2,0) -> Dedek Hudayana | D27: F1B005011 | E27: Alat Pengontrol dan Pemonitor Lingkungan Rumah Kaca pada Tanaman Kamboja Jepang di Dinas Pertanian Narmada Berbasiskan Mikrokontroler ATMEGA8535 | F27: Paniran, S.T., M.T. | G27: Supriono, S.T., M.T. | H27: I Ketut Wiryajati, S.T., M.T. | I27: Muhammad Firad, S.T. | J27: Lalu A. Syamsul Irfan A., S.T., M.Eng. | K27: Sabtu | L27: 40341 | M27: 08.00-10.00 | N27: R. Studio | O27: Lulus | Q27: 28 | R27: 29 | S27: 3 | T27: 11 | U27: 40 | W27: =TEXT(L27,"dd mmmm yyyy") -> 12 Juni 2010 | X27: =IFERROR(VLOOKUP(D27,'[5]mhs elektro-kecil'!$B$5:$E$2151,3,0),"CEK") -> CEK | Y27: =IFERROR(VLOOKUP(D27,'[5]mhs elektro-kecil'!$B$5:$E$2151,4,0),"CEK") -> CEK | Z27: =L27 -> 40341 | AA27: =Z27+180 -> 40521 | AC27: Lulus | AI27: =MID(D27,5,2) -> 05 | AL27: =IF(MID(D27,5,2)="06",2006,IF(MID(D27,5,2)="07",2007,IF(MID(D27,5,2)="08",2008,IF(MID(D27,5,2)="09",2009,IF(MID(D27,5,2)="10",2010,IF(MID(D27,5,2)="11",2011,IF(MID(D27,5,2)="12",2012,IF(MID(D27,5,2)="05",2005,IF(MID(D27,5,2)="04",2004,IF(MID(D27,5,2)="03",2003,IF(MID(D27,5,2)="13",2013,IF(MID(D27,5,2)="14",2014,IF(MID(D27,5,2)="15",2015,IF(MID(D27,5,2)="16",2016,IF(MID(D27,5,2)="17",2017,IF(MID(D27,5,2)="18",2018,2019)))))))))))))))) -> 2005 | AM27: =COUNTIF([6]Daftar!$D$5:$D$851,D27) -> #VALUE! | AN27: =COUNTIF([7]daftar!$D$4:$D$885,D27) -> #VALUE! | AS27: =C27 -> Dedek Hudayana | AT27: =D27 -> F1B005011 | AU27: =A27 -> 24
A28: =A27+1 -> 25 | B28: 40357 | C28: =VLOOKUP(D28,'[4]mhs elektro-kecil'!$B$5:$C$1847,2,0) -> Kamarudin | D28: F1B005033 | E28: Perancangan Sistem Pengaman Sepeda Motor Menggunakan Telepon Seluler (Handphone) Berbasis Mikrokontroller ATMEGA 8535 | F28: Supriono, S.T., M.T. | G28: I Made Budi Suksmadana, S.T., M.T. | H28: Syafarudin Ch, S.T., M.T. | I28: Sabar Nababan, S.T., M.T. | J28: Muhamad Irwan, S.T., M.T. | K28: Kamis | L28: 40360 | M28: 08.00-10.00 | N28: R. Studio | O28: Lulus | Q28: 29 | R28: 24 | S28: 4 | T28: 31 | U28: 39 | W28: =TEXT(L28,"dd mmmm yyyy") -> 01 Juli 2010 | X28: =IFERROR(VLOOKUP(D28,'[5]mhs elektro-kecil'!$B$5:$E$2151,3,0),"CEK") -> CEK | Y28: =IFERROR(VLOOKUP(D28,'[5]mhs elektro-kecil'!$B$5:$E$2151,4,0),"CEK") -> CEK | Z28: =L28 -> 40360 | AA28: =Z28+180 -> 40540 | AC28: Lulus | AI28: =MID(D28,5,2) -> 05 | AL28: =IF(MID(D28,5,2)="06",2006,IF(MID(D28,5,2)="07",2007,IF(MID(D28,5,2)="08",2008,IF(MID(D28,5,2)="09",2009,IF(MID(D28,5,2)="10",2010,IF(MID(D28,5,2)="11",2011,IF(MID(D28,5,2)="12",2012,IF(MID(D28,5,2)="05",2005,IF(MID(D28,5,2)="04",2004,IF(MID(D28,5,2)="03",2003,IF(MID(D28,5,2)="13",2013,IF(MID(D28,5,2)="14",2014,IF(MID(D28,5,2)="15",2015,IF(MID(D28,5,2)="16",2016,IF(MID(D28,5,2)="17",2017,IF(MID(D28,5,2)="18",2018,2019)))))))))))))))) -> 2005 | AM28: =COUNTIF([6]Daftar!$D$5:$D$851,D28) -> #VALUE! | AN28: =COUNTIF([7]daftar!$D$4:$D$885,D28) -> #VALUE! | AS28: =C28 -> Kamarudin | AT28: =D28 -> F1B005033 | AU28: =A28 -> 25
A29: =A28+1 -> 26 | B29: 40373 | C29: =VLOOKUP(D29,'[4]mhs elektro-kecil'!$B$5:$C$1847,2,0) -> Henry Sayyidiman | D29: F1B006030 | E29: Optimalisasi Kapasitas Pembangkit Tersebar dalam Mengurangi Rugi Saluran dan Meningkatkan Profil Tegangan Menggunakan Particle Swarm Optimization | F29: I Made Ari Nrartha, S.T., M.T. | G29: Agung Budi Muljono, S.T., M.T. | H29: Abdul Natsir, S.T., M.T. | I29: Ida Bagus Fery Citarsa, S.T., M.T. | J29: Dr. Misbahuddin, S.T., M.T. | K29: Sabtu | L29: 40376 | M29: 10.00-12.00 | N29: R. D2 | O29: Lulus | Q29: 25 | R29: 13 | S29: 14 | T29: 12 | U29: 7 | W29: =TEXT(L29,"dd mmmm yyyy") -> 17 Juli 2010 | X29: =IFERROR(VLOOKUP(D29,'[5]mhs elektro-kecil'!$B$5:$E$2151,3,0),"CEK") -> CEK | Y29: =IFERROR(VLOOKUP(D29,'[5]mhs elektro-kecil'!$B$5:$E$2151,4,0),"CEK") -> CEK | Z29: =L29 -> 40376 | AA29: =Z29+180 -> 40556 | AC29: Lulus | AI29: =MID(D29,5,2) -> 06 | AL29: =IF(MID(D29,5,2)="06",2006,IF(MID(D29,5,2)="07",2007,IF(MID(D29,5,2)="08",2008,IF(MID(D29,5,2)="09",2009,IF(MID(D29,5,2)="10",2010,IF(MID(D29,5,2)="11",2011,IF(MID(D29,5,2)="12",2012,IF(MID(D29,5,2)="05",2005,IF(MID(D29,5,2)="04",2004,IF(MID(D29,5,2)="03",2003,IF(MID(D29,5,2)="13",2013,IF(MID(D29,5,2)="14",2014,IF(MID(D29,5,2)="15",2015,IF(MID(D29,5,2)="16",2016,IF(MID(D29,5,2)="17",2017,IF(MID(D29,5,2)="18",2018,2019)))))))))))))))) -> 2006 | AM29: =COUNTIF([6]Daftar!$D$5:$D$851,D29) -> #VALUE! | AN29: =COUNTIF([7]daftar!$D$4:$D$885,D29) -> #VALUE! | AS29: =C29 -> Henry Sayyidiman | AT29: =D29 -> F1B006030 | AU29: =A29 -> 26
A30: =A29+1 -> 27 | B30: 40373 | C30: =VLOOKUP(D30,'[4]mhs elektro-kecil'!$B$5:$C$1847,2,0) -> Ria Fitriani | D30: F1B003057 | E30: Analisa Proteksi Sistem Kelistrikan Lombok pada Express Feeder Ampenan - Paokmotong | F30: Supriyatna, S.T., M.T. | G30: Supriono, S.T., M.T. | H30: Dr.rer.nat. Teti Zubaidah, S.T., M.T. | I30: Sultan, S.T., M.T. | J30: Ni Made Seniari, S.T., M.T. | K30: Sabtu | L30: 40376 | M30: 08.00-10.00 | N30: R. Studio | O30: Lulus | Q30: 2 | R30: 29 | S30: 22 | T30: 5 | U30: 1 | W30: =TEXT(L30,"dd mmmm yyyy") -> 17 Juli 2010 | X30: =IFERROR(VLOOKUP(D30,'[5]mhs elektro-kecil'!$B$5:$E$2151,3,0),"CEK") -> CEK | Y30: =IFERROR(VLOOKUP(D30,'[5]mhs elektro-kecil'!$B$5:$E$2151,4,0),"CEK") -> CEK | Z30: =L30 -> 40376 | AA30: =Z30+180 -> 40556 | AC30: Lulus | AI30: =MID(D30,5,2) -> 03 | AL30: =IF(MID(D30,5,2)="06",2006,IF(MID(D30,5,2)="07",2007,IF(MID(D30,5,2)="08",2008,IF(MID(D30,5,2)="09",2009,IF(MID(D30,5,2)="10",2010,IF(MID(D30,5,2)="11",2011,IF(MID(D30,5,2)="12",2012,IF(MID(D30,5,2)="05",2005,IF(MID(D30,5,2)="04",2004,IF(MID(D30,5,2)="03",2003,IF(MID(D30,5,2)="13",2013,IF(MID(D30,5,2)="14",2014,IF(MID(D30,5,2)="15",2015,IF(MID(D30,5,2)="16",2016,IF(MID(D30,5,2)="17",2017,IF(MID(D30,5,2)="18",2018,2019)))))))))))))))) -> 2003 | AM30: =COUNTIF([6]Daftar!$D$5:$D$851,D30) -> #VALUE! | AN30: =COUNTIF([7]daftar!$D$4:$D$885,D30) -> #VALUE! | AS30: =C30 -> Ria Fitriani | AT30: =D30 -> F1B003057 | AU30: =A30 -> 27
A31: =A30+1 -> 28 | B31: 40406 | C31: =VLOOKUP(D31,'[4]mhs elektro-kecil'!$B$5:$C$1847,2,0) -> I Gde Aditya P S | D31: F1B004032 | E31: Sistem Proteksi Keamanan Ruangan dan Pengendali Lampu Berbasis SMS | F31: Supriono, S.T., M.T. | G31: I Made Budi Suksmadana, S.T., M.T. | H31: I Ketut Wiryajati, S.T., M.T. | I31: Syafarudin Ch, S.T., M.T. | J31: Paniran, S.T., M.T. | K31: Rabu | L31: 40408 | M31: 10.00-12.00 | N31: R. Studio | O31: Lulus | Q31: 29 | R31: 24 | S31: 3 | T31: 4 | U31: 28 | W31: =TEXT(L31,"dd mmmm yyyy") -> 18 Agustus 2010 | X31: =IFERROR(VLOOKUP(D31,'[5]mhs elektro-kecil'!$B$5:$E$2151,3,0),"CEK") -> CEK | Y31: =IFERROR(VLOOKUP(D31,'[5]mhs elektro-kecil'!$B$5:$E$2151,4,0),"CEK") -> CEK | Z31: =L31 -> 40408 | AA31: =Z31+180 -> 40588 | AC31: Lulus | AI31: =MID(D31,5,2) -> 04 | AL31: =IF(MID(D31,5,2)="06",2006,IF(MID(D31,5,2)="07",2007,IF(MID(D31,5,2)="08",2008,IF(MID(D31,5,2)="09",2009,IF(MID(D31,5,2)="10",2010,IF(MID(D31,5,2)="11",2011,IF(MID(D31,5,2)="12",2012,IF(MID(D31,5,2)="05",2005,IF(MID(D31,5,2)="04",2004,IF(MID(D31,5,2)="03",2003,IF(MID(D31,5,2)="13",2013,IF(MID(D31,5,2)="14",2014,IF(MID(D31,5,2)="15",2015,IF(MID(D31,5,2)="16",2016,IF(MID(D31,5,2)="17",2017,IF(MID(D31,5,2)="18",2018,2019)))))))))))))))) -> 2004 | AM31: =COUNTIF([6]Daftar!$D$5:$D$851,D31) -> #VALUE! | AN31: =COUNTIF([7]daftar!$D$4:$D$885,D31) -> #VALUE! | AS31: =C31 -> I Gde Aditya P S | AT31: =D31 -> F1B004032 | AU31: =A31 -> 28
A32: =A31+1 -> 29 | B32: 40403 | C32: =VLOOKUP(D32,'[4]mhs elektro-kecil'!$B$5:$C$1847,2,0) -> Edi Waskita Putra | D32: F1B003015 | E32: Rancang Bangun Sistem Absensi Mengajar Dosen dengan SMS Gateway | F32: Dr. Misbahuddin, S.T., M.T. | G32: Heri Wijayanto, S.T., M.T. | H32: Budi Irmawati, S. Kom., M.T. | I32: I B K Widiartha, S.T., M.T. | J32: Ir. Sri Endang Anjarwani, M.Kom. | K32: Rabu | L32: 40408 | M32: 08.00-10.00 | N32: R. D2 | O32: Lulus | Q32: 7 | R32: 32 | S32: 20 | T32: 27 | U32: 38 | W32: =TEXT(L32,"dd mmmm yyyy") -> 18 Agustus 2010 | X32: =IFERROR(VLOOKUP(D32,'[5]mhs elektro-kecil'!$B$5:$E$2151,3,0),"CEK") -> CEK | Y32: =IFERROR(VLOOKUP(D32,'[5]mhs elektro-kecil'!$B$5:$E$2151,4,0),"CEK") -> CEK | Z32: =L32 -> 40408 | AA32: =Z32+180 -> 40588 | AC32: Lulus | AI32: =MID(D32,5,2) -> 03 | AL32: =IF(MID(D32,5,2)="06",2006,IF(MID(D32,5,2)="07",2007,IF(MID(D32,5,2)="08",2008,IF(MID(D32,5,2)="09",2009,IF(MID(D32,5,2)="10",2010,IF(MID(D32,5,2)="11",2011,IF(MID(D32,5,2)="12",2012,IF(MID(D32,5,2)="05",2005,IF(MID(D32,5,2)="04",2004,IF(MID(D32,5,2)="03",2003,IF(MID(D32,5,2)="13",2013,IF(MID(D32,5,2)="14",2014,IF(MID(D32,5,2)="15",2015,IF(MID(D32,5,2)="16",2016,IF(MID(D32,5,2)="17",2017,IF(MID(D32,5,2)="18",2018,2019)))))))))))))))) -> 2003 | AM32: =COUNTIF([6]Daftar!$D$5:$D$851,D32) -> #VALUE! | AN32: =COUNTIF([7]daftar!$D$4:$D$885,D32) -> #VALUE! | AS32: =C32 -> Edi Waskita Putra | AT32: =D32 -> F1B003015 | AU32: =A32 -> 29
A33: =A32+1 -> 30 | B33: 40410 | C33: =VLOOKUP(D33,'[4]mhs elektro-kecil'!$B$5:$C$1847,2,0) -> Donny Adithia | D33: F1B005013 | E33: Rancang Bangun prototipe Pembangkit Listrik Gelombang Laut dengan Sistem Rakit | F33: Syafarudin Ch, S.T., M.T. | G33: Abdul Natsir, S.T., M.T. | H33: Ni Made Seniari, S.T., M.T. | I33: Ida Bagus Fery Citarsa, S.T., M.T. | J33: Rosmaliati, S.T., M.T. | K33: Selasa | L33: 40414 | M33: 08.00-10.00 | N33: R. Studio | O33: Lulus | Q33: 4 | R33: 14 | S33: 1 | T33: 12 | U33: 16 | W33: =TEXT(L33,"dd mmmm yyyy") -> 24 Agustus 2010 | X33: =IFERROR(VLOOKUP(D33,'[5]mhs elektro-kecil'!$B$5:$E$2151,3,0),"CEK") -> CEK | Y33: =IFERROR(VLOOKUP(D33,'[5]mhs elektro-kecil'!$B$5:$E$2151,4,0),"CEK") -> CEK | Z33: =L33 -> 40414 | AA33: =Z33+180 -> 40594 | AC33: Lulus | AI33: =MID(D33,5,2) -> 05 | AL33: =IF(MID(D33,5,2)="06",2006,IF(MID(D33,5,2)="07",2007,IF(MID(D33,5,2)="08",2008,IF(MID(D33,5,2)="09",2009,IF(MID(D33,5,2)="10",2010,IF(MID(D33,5,2)="11",2011,IF(MID(D33,5,2)="12",2012,IF(MID(D33,5,2)="05",2005,IF(MID(D33,5,2)="04",2004,IF(MID(D33,5,2)="03",2003,IF(MID(D33,5,2)="13",2013,IF(MID(D33,5,2)="14",2014,IF(MID(D33,5,2)="15",2015,IF(MID(D33,5,2)="16",2016,IF(MID(D33,5,2)="17",2017,IF(MID(D33,5,2)="18",2018,2019)))))))))))))))) -> 2005 | AM33: =COUNTIF([6]Daftar!$D$5:$D$851,D33) -> #VALUE! | AN33: =COUNTIF([7]daftar!$D$4:$D$885,D33) -> #VALUE! | AS33: =C33 -> Donny Adithia | AT33: =D33 -> F1B005013 | AU33: =A33 -> 30
A34: =A33+1 -> 31 | B34: 40450 | C34: =VLOOKUP(D34,'[4]mhs elektro-kecil'!$B$5:$C$1847,2,0) -> Supandi | D34: F1B005071 | E34: Economic Dispatch Menggunakan Algoritma Partikel Swarm Optimization | F34: I Made Ari Nrartha, S.T., M.T. | G34: Sultan, S.T., M.T. | H34: Supriyatna, S.T., M.T. | I34: Agung Budi Muljono, S.T., M.T. | J34: Sabar Nababan, S.T., M.T. | K34: Sabtu | L34: 40453 | M34: 08.00-10.00 | N34: R. Studio | O34: Lulus | Q34: 25 | R34: 5 | S34: 2 | T34: 13 | U34: 31 | W34: =TEXT(L34,"dd mmmm yyyy") -> 02 Oktober 2010 | X34: =IFERROR(VLOOKUP(D34,'[5]mhs elektro-kecil'!$B$5:$E$2151,3,0),"CEK") -> CEK | Y34: =IFERROR(VLOOKUP(D34,'[5]mhs elektro-kecil'!$B$5:$E$2151,4,0),"CEK") -> CEK | Z34: =L34 -> 40453 | AA34: =Z34+180 -> 40633 | AB34: =AA34+180 -> 40813 | AI34: =MID(D34,5,2) -> 05 | AL34: =IF(MID(D34,5,2)="06",2006,IF(MID(D34,5,2)="07",2007,IF(MID(D34,5,2)="08",2008,IF(MID(D34,5,2)="09",2009,IF(MID(D34,5,2)="10",2010,IF(MID(D34,5,2)="11",2011,IF(MID(D34,5,2)="12",2012,IF(MID(D34,5,2)="05",2005,IF(MID(D34,5,2)="04",2004,IF(MID(D34,5,2)="03",2003,IF(MID(D34,5,2)="13",2013,IF(MID(D34,5,2)="14",2014,IF(MID(D34,5,2)="15",2015,IF(MID(D34,5,2)="16",2016,IF(MID(D34,5,2)="17",2017,IF(MID(D34,5,2)="18",2018,2019)))))))))))))))) -> 2005 | AM34: =COUNTIF([6]Daftar!$D$5:$D$851,D34) -> #VALUE! | AN34: =COUNTIF([7]daftar!$D$4:$D$885,D34) -> #VALUE! | AS34: =C34 -> Supandi | AT34: =D34 -> F1B005071 | AU34: =A34 -> 31
A35: =A34+1 -> 32 | B35: 40454 | C35: =VLOOKUP(D35,'[4]mhs elektro-kecil'!$B$5:$C$1847,2,0) -> Prasetyadiguna | D35: F1B004063 | E35: Design Realisasi Power Splitter Mikrostrip pada Pemancar TV Kampus dengan Model Eksponensial Menggunakan HFSS | F35: Sudi M. Al Sasongko, S.T., M.T. | G35: Abdullah Zainuddin, S.T., M.T. | H35: Djul Fikry Budiman, S.T., M.T. | I35: Muhamad Syamsu Iqbal, S.T., M.T., Ph.D. | J35: Bulkis Kanata, S.T., M.T. | K35: Rabu | L35: 40457 | M35: 09.30-11.30 | N35: Lab. Telkom | O35: Lulus | Q35: 6 | R35: 15 | S35: 35 | T35: 18 | U35: 21 | W35: =TEXT(L35,"dd mmmm yyyy") -> 06 Oktober 2010 | X35: =IFERROR(VLOOKUP(D35,'[5]mhs elektro-kecil'!$B$5:$E$2151,3,0),"CEK") -> CEK | Y35: =IFERROR(VLOOKUP(D35,'[5]mhs elektro-kecil'!$B$5:$E$2151,4,0),"CEK") -> CEK | Z35: =L35 -> 40457 | AA35: =Z35+180 -> 40637 | AB35: =AA35+180 -> 40817 | AI35: =MID(D35,5,2) -> 04 | AL35: =IF(MID(D35,5,2)="06",2006,IF(MID(D35,5,2)="07",2007,IF(MID(D35,5,2)="08",2008,IF(MID(D35,5,2)="09",2009,IF(MID(D35,5,2)="10",2010,IF(MID(D35,5,2)="11",2011,IF(MID(D35,5,2)="12",2012,IF(MID(D35,5,2)="05",2005,IF(MID(D35,5,2)="04",2004,IF(MID(D35,5,2)="03",2003,IF(MID(D35,5,2)="13",2013,IF(MID(D35,5,2)="14",2014,IF(MID(D35,5,2)="15",2015,IF(MID(D35,5,2)="16",2016,IF(MID(D35,5,2)="17",2017,IF(MID(D35,5,2)="18",2018,2019)))))))))))))))) -> 2004 | AM35: =COUNTIF([6]Daftar!$D$5:$D$851,D35) -> #VALUE! | AN35: =COUNTIF([7]daftar!$D$4:$D$885,D35) -> #VALUE! | AS35: =C35 -> Prasetyadiguna | AT35: =D35 -> F1B004063 | AU35: =A35 -> 32
A36: =A35+1 -> 33 | B36: 40454 | C36: =VLOOKUP(D36,'[4]mhs elektro-kecil'!$B$5:$C$1847,2,0) -> Amir Hasanudin Fauzi | D36: F1B006008 | E36: Pattern Matching Method Based On Aho-Corasick Algorithm to Detect Malicious Code | F36: Dr. Rismon H. Sianipar, S.T., M.Eng. | G36: Heri Wijayanto, S.T., M.T. | H36: Budi Irmawati, S. Kom., M.T. | I36: I B K Widiartha, S.T., M.T. | J36: Muhamad Irwan, S.T., M.T. | K36: Rabu | L36: 40457 | M36: 07.30-09.30 | N36: Lab. Komputer | O36: Lulus | Q36: 33 | R36: 32 | S36: 20 | T36: 27 | U36: 39 | W36: =TEXT(L36,"dd mmmm yyyy") -> 06 Oktober 2010 | X36: =IFERROR(VLOOKUP(D36,'[5]mhs elektro-kecil'!$B$5:$E$2151,3,0),"CEK") -> CEK | Y36: =IFERROR(VLOOKUP(D36,'[5]mhs elektro-kecil'!$B$5:$E$2151,4,0),"CEK") -> CEK | Z36: =L36 -> 40457 | AA36: =Z36+180 -> 40637 | AC36: Lulus | AI36: =MID(D36,5,2) -> 06 | AL36: =IF(MID(D36,5,2)="06",2006,IF(MID(D36,5,2)="07",2007,IF(MID(D36,5,2)="08",2008,IF(MID(D36,5,2)="09",2009,IF(MID(D36,5,2)="10",2010,IF(MID(D36,5,2)="11",2011,IF(MID(D36,5,2)="12",2012,IF(MID(D36,5,2)="05",2005,IF(MID(D36,5,2)="04",2004,IF(MID(D36,5,2)="03",2003,IF(MID(D36,5,2)="13",2013,IF(MID(D36,5,2)="14",2014,IF(MID(D36,5,2)="15",2015,IF(MID(D36,5,2)="16",2016,IF(MID(D36,5,2)="17",2017,IF(MID(D36,5,2)="18",2018,2019)))))))))))))))) -> 2006 | AM36: =COUNTIF([6]Daftar!$D$5:$D$851,D36) -> #VALUE! | AN36: =COUNTIF([7]daftar!$D$4:$D$885,D36) -> #VALUE! | AS36: =C36 -> Amir Hasanudin Fauzi | AT36: =D36 -> F1B006008 | AU36: =A36 -> 33
A37: =A36+1 -> 34 | B37: 40483 | C37: =VLOOKUP(D37,'[4]mhs elektro-kecil'!$B$5:$C$1847,2,0) -> Siswadi | D37: F1B005067 | E37: Prototype Pengendalian System Buka Tutup Gerbang dan Berpengunci Otomatis Menggunakan Mikrokontroller ATMEGA 8535 | F37: Paniran, S.T., M.T. | G37: Supriono, S.T., M.T. | H37: Syafarudin Ch, S.T., M.T. | I37: I Made Budi Suksmadana, S.T., M.T. | J37: Ida Bagus Fery Citarsa, S.T., M.T. | K37: Kamis | L37: 40486 | M37: 08.00-10.00 | N37: R. D2 | O37: Lulus | Q37: 28 | R37: 29 | S37: 4 | T37: 24 | U37: 12 | W37: =TEXT(L37,"dd mmmm yyyy") -> 04 November 2010 | X37: =IFERROR(VLOOKUP(D37,'[5]mhs elektro-kecil'!$B$5:$E$2151,3,0),"CEK") -> CEK | Y37: =IFERROR(VLOOKUP(D37,'[5]mhs elektro-kecil'!$B$5:$E$2151,4,0),"CEK") -> CEK | Z37: =L37 -> 40486 | AA37: =Z37+180 -> 40666 | AB37: =AA37+180 -> 40846 | AI37: =MID(D37,5,2) -> 05 | AL37: =IF(MID(D37,5,2)="06",2006,IF(MID(D37,5,2)="07",2007,IF(MID(D37,5,2)="08",2008,IF(MID(D37,5,2)="09",2009,IF(MID(D37,5,2)="10",2010,IF(MID(D37,5,2)="11",2011,IF(MID(D37,5,2)="12",2012,IF(MID(D37,5,2)="05",2005,IF(MID(D37,5,2)="04",2004,IF(MID(D37,5,2)="03",2003,IF(MID(D37,5,2)="13",2013,IF(MID(D37,5,2)="14",2014,IF(MID(D37,5,2)="15",2015,IF(MID(D37,5,2)="16",2016,IF(MID(D37,5,2)="17",2017,IF(MID(D37,5,2)="18",2018,2019)))))))))))))))) -> 2005 | AM37: =COUNTIF([6]Daftar!$D$5:$D$851,D37) -> #VALUE! | AN37: =COUNTIF([7]daftar!$D$4:$D$885,D37) -> #VALUE! | AS37: =C37 -> Siswadi | AT37: =D37 -> F1B005067 | AU37: =A37 -> 34
A38: =A37+1 -> 35 | B38: 40483 | C38: =VLOOKUP(D38,'[4]mhs elektro-kecil'!$B$5:$C$1847,2,0) -> Fetty Nursofy Ristianty | D38: F1B006024 | E38: Simulasi Analisa Unjuk Kerja Transmisi Paket Data pada Jaringan GSM (Global System For Mobile) Menggunakan Network Simulator - 2 (NS2) | F38: Muhamad Syamsu Iqbal, S.T., M.T., Ph.D. | G38: Heri Wijayanto, S.T., M.T. | H38: Sudi M. Al Sasongko, S.T., M.T. | I38: Dr. Misbahuddin, S.T., M.T. | J38: Muhamad Irwan, S.T., M.T. | K38: Kamis | L38: 40486 | M38: 10.00-12.00 | N38: R. D2 | O38: Lulus | Q38: 18 | R38: 32 | S38: 6 | T38: 7 | U38: 39 | W38: =TEXT(L38,"dd mmmm yyyy") -> 04 November 2010 | X38: =IFERROR(VLOOKUP(D38,'[5]mhs elektro-kecil'!$B$5:$E$2151,3,0),"CEK") -> CEK | Y38: =IFERROR(VLOOKUP(D38,'[5]mhs elektro-kecil'!$B$5:$E$2151,4,0),"CEK") -> CEK | Z38: =L38 -> 40486 | AA38: =Z38+180 -> 40666 | AC38: Lulus | AI38: =MID(D38,5,2) -> 06 | AL38: =IF(MID(D38,5,2)="06",2006,IF(MID(D38,5,2)="07",2007,IF(MID(D38,5,2)="08",2008,IF(MID(D38,5,2)="09",2009,IF(MID(D38,5,2)="10",2010,IF(MID(D38,5,2)="11",2011,IF(MID(D38,5,2)="12",2012,IF(MID(D38,5,2)="05",2005,IF(MID(D38,5,2)="04",2004,IF(MID(D38,5,2)="03",2003,IF(MID(D38,5,2)="13",2013,IF(MID(D38,5,2)="14",2014,IF(MID(D38,5,2)="15",2015,IF(MID(D38,5,2)="16",2016,IF(MID(D38,5,2)="17",2017,IF(MID(D38,5,2)="18",2018,2019)))))))))))))))) -> 2006 | AM38: =COUNTIF([6]Daftar!$D$5:$D$851,D38) -> #VALUE! | AN38: =COUNTIF([7]daftar!$D$4:$D$885,D38) -> #VALUE! | AS38: =C38 -> Fetty Nursofy Ristianty | AT38: =D38 -> F1B006024 | AU38: =A38 -> 35
A39: =A38+1 -> 36 | B39: 40498 | C39: =VLOOKUP(D39,'[4]mhs elektro-kecil'!$B$5:$C$1847,2,0) -> En Mahsyar | D39: F1B006021 | E39: Perencanaan Instalasi Listrik yang Optimal dalam Menekan Pengaruh Interferensi Gelombang Elektromagnetik di Observatorium Geomagnetik Lombok (OGL) | F39: Dr.rer.nat. Teti Zubaidah, S.T., M.T. | G39: Sultan, S.T., M.T. | H39: Abdul Natsir, S.T., M.T. | I39: Rosmaliati, S.T., M.T. | J39: I Made Ari Nrartha, S.T., M.T. | K39: Sabtu | L39: 40502 | M39: 08.00-10.00 | N39: R. D2 | O39: Lulus | Q39: 22 | R39: 5 | S39: 14 | T39: 16 | U39: 25 | W39: =TEXT(L39,"dd mmmm yyyy") -> 20 November 2010 | X39: =IFERROR(VLOOKUP(D39,'[5]mhs elektro-kecil'!$B$5:$E$2151,3,0),"CEK") -> CEK | Y39: =IFERROR(VLOOKUP(D39,'[5]mhs elektro-kecil'!$B$5:$E$2151,4,0),"CEK") -> CEK | Z39: =L39 -> 40502 | AA39: =Z39+180 -> 40682 | AB39: =AA39+180 -> 40862 | AI39: =MID(D39,5,2) -> 06 | AL39: =IF(MID(D39,5,2)="06",2006,IF(MID(D39,5,2)="07",2007,IF(MID(D39,5,2)="08",2008,IF(MID(D39,5,2)="09",2009,IF(MID(D39,5,2)="10",2010,IF(MID(D39,5,2)="11",2011,IF(MID(D39,5,2)="12",2012,IF(MID(D39,5,2)="05",2005,IF(MID(D39,5,2)="04",2004,IF(MID(D39,5,2)="03",2003,IF(MID(D39,5,2)="13",2013,IF(MID(D39,5,2)="14",2014,IF(MID(D39,5,2)="15",2015,IF(MID(D39,5,2)="16",2016,IF(MID(D39,5,2)="17",2017,IF(MID(D39,5,2)="18",2018,2019)))))))))))))))) -> 2006 | AM39: =COUNTIF([6]Daftar!$D$5:$D$851,D39) -> #VALUE! | AN39: =COUNTIF([7]daftar!$D$4:$D$885,D39) -> #VALUE! | AS39: =C39 -> En Mahsyar | AT39: =D39 -> F1B006021 | AU39: =A39 -> 36
A40: =A39+1 -> 37 | B40: 40498 | C40: =VLOOKUP(D40,'[4]mhs elektro-kecil'!$B$5:$C$1847,2,0) -> Akbar Satryantho | D40: F1B005004 | E40: Sistem Kontrol dan Monitoring Meteo Payload Roket sebagai Aplikasi Pemantau Suhu dan Kelembaban diudara Menggunakan Teknologi Wireless YS-1020 | F40: I Made Budi Suksmadana, S.T., M.T. | G40: Paniran, S.T., M.T. | H40: Supriono, S.T., M.T. | I40: Syafarudin Ch, S.T., M.T. | J40: Muhamad Irwan, S.T., M.T. | K40: Sabtu | L40: 40502 | M40: 10.00-12.00 | N40: R. D2 | O40: Lulus | Q40: 24 | R40: 28 | S40: 29 | T40: 4 | U40: 39 | W40: =TEXT(L40,"dd mmmm yyyy") -> 20 November 2010 | X40: =IFERROR(VLOOKUP(D40,'[5]mhs elektro-kecil'!$B$5:$E$2151,3,0),"CEK") -> CEK | Y40: =IFERROR(VLOOKUP(D40,'[5]mhs elektro-kecil'!$B$5:$E$2151,4,0),"CEK") -> CEK | Z40: =L40 -> 40502 | AA40: =Z40+180 -> 40682 | AC40: Lulus | AI40: =MID(D40,5,2) -> 05 | AL40: =IF(MID(D40,5,2)="06",2006,IF(MID(D40,5,2)="07",2007,IF(MID(D40,5,2)="08",2008,IF(MID(D40,5,2)="09",2009,IF(MID(D40,5,2)="10",2010,IF(MID(D40,5,2)="11",2011,IF(MID(D40,5,2)="12",2012,IF(MID(D40,5,2)="05",2005,IF(MID(D40,5,2)="04",2004,IF(MID(D40,5,2)="03",2003,IF(MID(D40,5,2)="13",2013,IF(MID(D40,5,2)="14",2014,IF(MID(D40,5,2)="15",2015,IF(MID(D40,5,2)="16",2016,IF(MID(D40,5,2)="17",2017,IF(MID(D40,5,2)="18",2018,2019)))))))))))))))) -> 2005 | AM40: =COUNTIF([6]Daftar!$D$5:$D$851,D40) -> #VALUE! | AN40: =COUNTIF([7]daftar!$D$4:$D$885,D40) -> #VALUE! | AS40: =C40 -> Akbar Satryantho | AT40: =D40 -> F1B005004 | AU40: =A40 -> 37
A41: =A40+1 -> 38 | B41: 40501 | C41: =VLOOKUP(D41,'[4]mhs elektro-kecil'!$B$5:$C$1847,2,0) -> Rosiawan | D41: F1B006073 | E41: Pengukuran dan Analisa Pengaruh Interferensi terhadap Quality of Service (QOS) pada Standar Jaringan 802.11B | F41: Abdullah Zainuddin, S.T., M.T. | G41: Sudi M. Al Sasongko, S.T., M.T. | H41: Muhamad Syamsu Iqbal, S.T., M.T., Ph.D. | I41: Djul Fikry Budiman, S.T., M.T. | J41: Lalu A. Syamsul Irfan A., S.T., M.Eng. | K41: Sabtu | L41: 40502 | M41: 10.00-12.00 | N41: R. Studio | O41: Lulus | Q41: 15 | R41: 6 | S41: 18 | T41: 35 | U41: 40 | W41: =TEXT(L41,"dd mmmm yyyy") -> 20 November 2010 | X41: =IFERROR(VLOOKUP(D41,'[5]mhs elektro-kecil'!$B$5:$E$2151,3,0),"CEK") -> CEK | Y41: =IFERROR(VLOOKUP(D41,'[5]mhs elektro-kecil'!$B$5:$E$2151,4,0),"CEK") -> CEK | Z41: =L41 -> 40502 | AA41: =Z41+180 -> 40682 | AC41: Lulus | AI41: =MID(D41,5,2) -> 06 | AL41: =IF(MID(D41,5,2)="06",2006,IF(MID(D41,5,2)="07",2007,IF(MID(D41,5,2)="08",2008,IF(MID(D41,5,2)="09",2009,IF(MID(D41,5,2)="10",2010,IF(MID(D41,5,2)="11",2011,IF(MID(D41,5,2)="12",2012,IF(MID(D41,5,2)="05",2005,IF(MID(D41,5,2)="04",2004,IF(MID(D41,5,2)="03",2003,IF(MID(D41,5,2)="13",2013,IF(MID(D41,5,2)="14",2014,IF(MID(D41,5,2)="15",2015,IF(MID(D41,5,2)="16",2016,IF(MID(D41,5,2)="17",2017,IF(MID(D41,5,2)="18",2018,2019)))))))))))))))) -> 2006 | AM41: =COUNTIF([6]Daftar!$D$5:$D$851,D41) -> #VALUE! | AN41: =COUNTIF([7]daftar!$D$4:$D$885,D41) -> #VALUE! | AS41: =C41 -> Rosiawan | AT41: =D41 -> F1B006073 | AU41: =A41 -> 38
A42: =A41+1 -> 39 | B42: 40505 | C42: =VLOOKUP(D42,'[4]mhs elektro-kecil'!$B$5:$C$1847,2,0) -> M. Septiadi Rangga Permana | D42: F1B006054 | E42: Pembangkit Kode Batang Unik Menggunakan Fungsi Hash SHA-512 | F42: Heri Wijayanto, S.T., M.T. | G42: Dr. Rismon H. Sianipar, S.T., M.Eng. | H42: I B K Widiartha, S.T., M.T. | I42: Ir. Sri Endang Anjarwani, M.Kom. | J42: Lalu A. Syamsul Irfan A., S.T., M.Eng. | K42: Sabtu | L42: 40509 | M42: 08.00-10.00 | N42: R. Studio | O42: Lulus | Q42: 32 | R42: 33 | S42: 27 | T42: 38 | U42: 40 | W42: =TEXT(L42,"dd mmmm yyyy") -> 27 November 2010 | X42: =IFERROR(VLOOKUP(D42,'[5]mhs elektro-kecil'!$B$5:$E$2151,3,0),"CEK") -> CEK | Y42: =IFERROR(VLOOKUP(D42,'[5]mhs elektro-kecil'!$B$5:$E$2151,4,0),"CEK") -> CEK | Z42: =L42 -> 40509 | AA42: =Z42+180 -> 40689 | AC42: Lulus | AI42: =MID(D42,5,2) -> 06 | AL42: =IF(MID(D42,5,2)="06",2006,IF(MID(D42,5,2)="07",2007,IF(MID(D42,5,2)="08",2008,IF(MID(D42,5,2)="09",2009,IF(MID(D42,5,2)="10",2010,IF(MID(D42,5,2)="11",2011,IF(MID(D42,5,2)="12",2012,IF(MID(D42,5,2)="05",2005,IF(MID(D42,5,2)="04",2004,IF(MID(D42,5,2)="03",2003,IF(MID(D42,5,2)="13",2013,IF(MID(D42,5,2)="14",2014,IF(MID(D42,5,2)="15",2015,IF(MID(D42,5,2)="16",2016,IF(MID(D42,5,2)="17",2017,IF(MID(D42,5,2)="18",2018,2019)))))))))))))))) -> 2006 | AM42: =COUNTIF([6]Daftar!$D$5:$D$851,D42) -> #VALUE! | AN42: =COUNTIF([7]daftar!$D$4:$D$885,D42) -> #VALUE! | AS42: =C42 -> M. Septiadi Rangga Permana | AT42: =D42 -> F1B006054 | AU42: =A42 -> 39
A43: =A42+1 -> 40 | B43: 40505 | C43: =VLOOKUP(D43,'[4]mhs elektro-kecil'!$B$5:$C$1847,2,0) -> Taufan Timur | D43: F1B005074 | E43: Implementasi Algoritma LZ77 dengan Metode Kompresi Bit Menggunakan Adaptive Huffman untuk Kompresi File Teks | F43: Dr. Rismon H. Sianipar, S.T., M.Eng. | G43: Heri Wijayanto, S.T., M.T. | H43: I B K Widiartha, S.T., M.T. | I43: Lalu A. Syamsul Irfan A., S.T., M.Eng. | J43: Ir. Sri Endang Anjarwani, M.Kom. | K43: Sabtu | L43: 40509 | M43: 10.00-12.00 | N43: R. Studio | O43: Lulus | Q43: 33 | R43: 32 | S43: 27 | T43: 40 | U43: 38 | W43: =TEXT(L43,"dd mmmm yyyy") -> 27 November 2010 | X43: =IFERROR(VLOOKUP(D43,'[5]mhs elektro-kecil'!$B$5:$E$2151,3,0),"CEK") -> CEK | Y43: =IFERROR(VLOOKUP(D43,'[5]mhs elektro-kecil'!$B$5:$E$2151,4,0),"CEK") -> CEK | Z43: =L43 -> 40509 | AA43: =Z43+180 -> 40689 | AC43: Lulus | AI43: =MID(D43,5,2) -> 05 | AL43: =IF(MID(D43,5,2)="06",2006,IF(MID(D43,5,2)="07",2007,IF(MID(D43,5,2)="08",2008,IF(MID(D43,5,2)="09",2009,IF(MID(D43,5,2)="10",2010,IF(MID(D43,5,2)="11",2011,IF(MID(D43,5,2)="12",2012,IF(MID(D43,5,2)="05",2005,IF(MID(D43,5,2)="04",2004,IF(MID(D43,5,2)="03",2003,IF(MID(D43,5,2)="13",2013,IF(MID(D43,5,2)="14",2014,IF(MID(D43,5,2)="15",2015,IF(MID(D43,5,2)="16",2016,IF(MID(D43,5,2)="17",2017,IF(MID(D43,5,2)="18",2018,2019)))))))))))))))) -> 2005 | AM43: =COUNTIF([6]Daftar!$D$5:$D$851,D43) -> #VALUE! | AN43: =COUNTIF([7]daftar!$D$4:$D$885,D43) -> #VALUE! | AS43: =C43 -> Taufan Timur | AT43: =D43 -> F1B005074 | AU43: =A43 -> 40
A44: =A43+1 -> 41 | B44: 40518 | C44: =VLOOKUP(D44,'[4]mhs elektro-kecil'!$B$5:$C$1847,2,0) -> Rosihan Musa | D44: F1B005063 | E44: Optimalisasi Perencanaan Sistem Penerangan yang Hemat Energi pada Gedung Observatorium Geomagnet Lombok | F44: Dr.rer.nat. Teti Zubaidah, S.T., M.T. | G44: Sultan, S.T., M.T. | H44: Ni Made Seniari, S.T., M.T. | I44: Supriyatna, S.T., M.T. | J44: Agung Budi Muljono, S.T., M.T. | K44: Jum'at | L44: 40522 | M44: 10.00-12.00 | N44: R. D2 | O44: Lulus | Q44: 22 | R44: 5 | S44: 1 | T44: 2 | U44: 13 | W44: =TEXT(L44,"dd mmmm yyyy") -> 10 Desember 2010 | X44: =IFERROR(VLOOKUP(D44,'[5]mhs elektro-kecil'!$B$5:$E$2151,3,0),"CEK") -> CEK | Y44: =IFERROR(VLOOKUP(D44,'[5]mhs elektro-kecil'!$B$5:$E$2151,4,0),"CEK") -> CEK | Z44: =L44 -> 40522 | AA44: =Z44+180 -> 40702 | AI44: =MID(D44,5,2) -> 05 | AL44: =IF(MID(D44,5,2)="06",2006,IF(MID(D44,5,2)="07",2007,IF(MID(D44,5,2)="08",2008,IF(MID(D44,5,2)="09",2009,IF(MID(D44,5,2)="10",2010,IF(MID(D44,5,2)="11",2011,IF(MID(D44,5,2)="12",2012,IF(MID(D44,5,2)="05",2005,IF(MID(D44,5,2)="04",2004,IF(MID(D44,5,2)="03",2003,IF(MID(D44,5,2)="13",2013,IF(MID(D44,5,2)="14",2014,IF(MID(D44,5,2)="15",2015,IF(MID(D44,5,2)="16",2016,IF(MID(D44,5,2)="17",2017,IF(MID(D44,5,2)="18",2018,2019)))))))))))))))) -> 2005 | AM44: =COUNTIF([6]Daftar!$D$5:$D$851,D44) -> #VALUE! | AN44: =COUNTIF([7]daftar!$D$4:$D$885,D44) -> #VALUE! | AS44: =C44 -> Rosihan Musa | AT44: =D44 -> F1B005063 | AU44: =A44 -> 41
A45: =A44+1 -> 42 | B45: 40505 | C45: =VLOOKUP(D45,'[4]mhs elektro-kecil'!$B$5:$C$1847,2,0) -> Dwi Agussusanti F. | D45: F1B006020 | E45: Simulasi dan Analisa BAS (Building Automation System) Berbasis Jaringan Sensor Nirkabel untuk Manajemen Energi Menggunakan Network Simulator 2 | F45: Muhamad Syamsu Iqbal, S.T., M.T., Ph.D. | G45: I Made Budi Suksmadana, S.T., M.T. | H45: Bulkis Kanata, S.T., M.T. | I45: Djul Fikry Budiman, S.T., M.T. | J45: Made Sutha Yadnya, S.T., M.T. | K45: Sabtu | L45: 40509 | M45: 10.00-12.00 | N45: R. D2 | O45: Lulus | Q45: 18 | R45: 24 | S45: 21 | T45: 35 | U45: 19 | W45: =TEXT(L45,"dd mmmm yyyy") -> 27 November 2010 | X45: =IFERROR(VLOOKUP(D45,'[5]mhs elektro-kecil'!$B$5:$E$2151,3,0),"CEK") -> CEK | Y45: =IFERROR(VLOOKUP(D45,'[5]mhs elektro-kecil'!$B$5:$E$2151,4,0),"CEK") -> CEK | Z45: =L45 -> 40509 | AA45: =Z45+180 -> 40689 | AC45: Lulus | AI45: =MID(D45,5,2) -> 06 | AL45: =IF(MID(D45,5,2)="06",2006,IF(MID(D45,5,2)="07",2007,IF(MID(D45,5,2)="08",2008,IF(MID(D45,5,2)="09",2009,IF(MID(D45,5,2)="10",2010,IF(MID(D45,5,2)="11",2011,IF(MID(D45,5,2)="12",2012,IF(MID(D45,5,2)="05",2005,IF(MID(D45,5,2)="04",2004,IF(MID(D45,5,2)="03",2003,IF(MID(D45,5,2)="13",2013,IF(MID(D45,5,2)="14",2014,IF(MID(D45,5,2)="15",2015,IF(MID(D45,5,2)="16",2016,IF(MID(D45,5,2)="17",2017,IF(MID(D45,5,2)="18",2018,2019)))))))))))))))) -> 2006 | AM45: =COUNTIF([6]Daftar!$D$5:$D$851,D45) -> #VALUE! | AN45: =COUNTIF([7]daftar!$D$4:$D$885,D45) -> #VALUE! | AS45: =C45 -> Dwi Agussusanti F. | AT45: =D45 -> F1B006020 | AU45: =A45 -> 42
A46: =A45+1 -> 43 | B46: 40527 | C46: =VLOOKUP(D46,'[4]mhs elektro-kecil'!$B$5:$C$1847,2,0) -> Ni Nym. Komala Pradini | D46: F1B006064 | E46: Analisis Pengurangan Harmonisa Transformator Distribusi dengan Menggunakan Filter Pasif (STF dan HDF) | F46: Ni Made Seniari, S.T., M.T. | G46: Sabar Nababan, S.T., M.T. | H46: I Ketut Wiryajati, S.T., M.T. | I46: I Made Ari Nrartha, S.T., M.T. | J46: Sultan, S.T., M.T. | K46: Senin | L46: 40532 | M46: 07.30-09.30 | N46: Lab. LD | O46: Lulus | Q46: 1 | R46: 31 | S46: 3 | T46: 25 | U46: 5 | W46: =TEXT(L46,"dd mmmm yyyy") -> 20 Desember 2010 | X46: =IFERROR(VLOOKUP(D46,'[5]mhs elektro-kecil'!$B$5:$E$2151,3,0),"CEK") -> CEK | Y46: =IFERROR(VLOOKUP(D46,'[5]mhs elektro-kecil'!$B$5:$E$2151,4,0),"CEK") -> CEK | Z46: =L46 -> 40532 | AA46: =Z46+180 -> 40712 | AB46: =AA46+180 -> 40892 | AI46: =MID(D46,5,2) -> 06 | AL46: =IF(MID(D46,5,2)="06",2006,IF(MID(D46,5,2)="07",2007,IF(MID(D46,5,2)="08",2008,IF(MID(D46,5,2)="09",2009,IF(MID(D46,5,2)="10",2010,IF(MID(D46,5,2)="11",2011,IF(MID(D46,5,2)="12",2012,IF(MID(D46,5,2)="05",2005,IF(MID(D46,5,2)="04",2004,IF(MID(D46,5,2)="03",2003,IF(MID(D46,5,2)="13",2013,IF(MID(D46,5,2)="14",2014,IF(MID(D46,5,2)="15",2015,IF(MID(D46,5,2)="16",2016,IF(MID(D46,5,2)="17",2017,IF(MID(D46,5,2)="18",2018,2019)))))))))))))))) -> 2006 | AM46: =COUNTIF([6]Daftar!$D$5:$D$851,D46) -> #VALUE! | AN46: =COUNTIF([7]daftar!$D$4:$D$885,D46) -> #VALUE! | AS46: =C46 -> Ni Nym. Komala Pradini | AT46: =D46 -> F1B006064 | AU46: =A46 -> 43
A47: =A46+1 -> 44 | B47: 40539 | C47: =VLOOKUP(D47,'[4]mhs elektro-kecil'!$B$5:$C$1847,2,0) -> Linda Rahmawati S. | D47: F1B006049 | E47: Aplikasi Penerjemah Bahasa Sasak Ke Bahasa Indonesia dengan Menggunakan Metode Parsing Brute Force | F47: Heri Wijayanto, S.T., M.T. | G47: Budi Irmawati, S. Kom., M.T. | H47: Dr. Misbahuddin, S.T., M.T. | I47: Lalu A. Syamsul Irfan A., S.T., M.Eng. | J47: Ir. Sri Endang Anjarwani, M.Kom. | K47: Rabu | L47: 40541 | M47: 08.00-10.00 | N47: R. D2 | O47: Lulus | Q47: 32 | R47: 20 | S47: 7 | T47: 40 | U47: 38 | W47: =TEXT(L47,"dd mmmm yyyy") -> 29 Desember 2010 | X47: =IFERROR(VLOOKUP(D47,'[5]mhs elektro-kecil'!$B$5:$E$2151,3,0),"CEK") -> CEK | Y47: =IFERROR(VLOOKUP(D47,'[5]mhs elektro-kecil'!$B$5:$E$2151,4,0),"CEK") -> CEK | Z47: =L47 -> 40541 | AA47: =Z47+180 -> 40721 | AC47: Lulus | AI47: =MID(D47,5,2) -> 06 | AL47: =IF(MID(D47,5,2)="06",2006,IF(MID(D47,5,2)="07",2007,IF(MID(D47,5,2)="08",2008,IF(MID(D47,5,2)="09",2009,IF(MID(D47,5,2)="10",2010,IF(MID(D47,5,2)="11",2011,IF(MID(D47,5,2)="12",2012,IF(MID(D47,5,2)="05",2005,IF(MID(D47,5,2)="04",2004,IF(MID(D47,5,2)="03",2003,IF(MID(D47,5,2)="13",2013,IF(MID(D47,5,2)="14",2014,IF(MID(D47,5,2)="15",2015,IF(MID(D47,5,2)="16",2016,IF(MID(D47,5,2)="17",2017,IF(MID(D47,5,2)="18",2018,2019)))))))))))))))) -> 2006 | AM47: =COUNTIF([6]Daftar!$D$5:$D$851,D47) -> #VALUE! | AN47: =COUNTIF([7]daftar!$D$4:$D$885,D47) -> #VALUE! | AS47: =C47 -> Linda Rahmawati S. | AT47: =D47 -> F1B006049 | AU47: =A47 -> 44
A48: =A47+1 -> 45 | B48: 40543 | C48: =VLOOKUP(D48,'[4]mhs elektro-kecil'!$B$5:$C$1847,2,0) -> Rita Dewi Sukmawati S. | D48: F1B006072 | E48: Analisa Kelayakan Implementasi Layanan VoIP (Voice Over Internet Protocol) Menggunakan Jaringan WLAN (Wireless Local Area Network) di Fakultas Teknik Unram | F48: Heri Wijayanto, S.T., M.T. | G48: Muhamad Syamsu Iqbal, S.T., M.T., Ph.D. | H48: Sudi M. Al Sasongko, S.T., M.T. | I48: I B K Widiartha, S.T., M.T. | J48: Dr. Misbahuddin, S.T., M.T. | K48: Senin | L48: 40546 | M48: 08.00-10.00 | N48: R. D2 | O48: Lulus | Q48: 32 | R48: 18 | S48: 6 | T48: 27 | U48: 7 | W48: =TEXT(L48,"dd mmmm yyyy") -> 03 Januari 2011 | X48: =IFERROR(VLOOKUP(D48,'[5]mhs elektro-kecil'!$B$5:$E$2151,3,0),"CEK") -> CEK | Y48: =IFERROR(VLOOKUP(D48,'[5]mhs elektro-kecil'!$B$5:$E$2151,4,0),"CEK") -> CEK | Z48: =L48 -> 40546 | AA48: =Z48+180 -> 40726 | AI48: =MID(D48,5,2) -> 06 | AL48: =IF(MID(D48,5,2)="06",2006,IF(MID(D48,5,2)="07",2007,IF(MID(D48,5,2)="08",2008,IF(MID(D48,5,2)="09",2009,IF(MID(D48,5,2)="10",2010,IF(MID(D48,5,2)="11",2011,IF(MID(D48,5,2)="12",2012,IF(MID(D48,5,2)="05",2005,IF(MID(D48,5,2)="04",2004,IF(MID(D48,5,2)="03",2003,IF(MID(D48,5,2)="13",2013,IF(MID(D48,5,2)="14",2014,IF(MID(D48,5,2)="15",2015,IF(MID(D48,5,2)="16",2016,IF(MID(D48,5,2)="17",2017,IF(MID(D48,5,2)="18",2018,2019)))))))))))))))) -> 2006 | AM48: =COUNTIF([6]Daftar!$D$5:$D$851,D48) -> #VALUE! | AN48: =COUNTIF([7]daftar!$D$4:$D$885,D48) -> #VALUE! | AS48: =C48 -> Rita Dewi Sukmawati S. | AT48: =D48 -> F1B006072 | AU48: =A48 -> 45
A49: =A48+1 -> 46 | B49: 40554 | C49: =VLOOKUP(D49,'[4]mhs elektro-kecil'!$B$5:$C$1847,2,0) -> Thendriani Yastenti | D49: F1B006081 | E49: Peta Interaktif untuk Pencarian Rute terpendek Jaringan Jalan Kota Mataram Berbasis Algoritma DJIKSTRA Shortest Path Menggunakan Adobe Flash 7 | F49: Heri Wijayanto, S.T., M.T. | G49: I B K Widiartha, S.T., M.T. | H49: Dr. Misbahuddin, S.T., M.T. | I49: Muhamad Irwan, S.T., M.T. | J49: Lalu A. Syamsul Irfan A., S.T., M.Eng. | K49: Sabtu | L49: 40558 | M49: 08.00-10.00 | N49: R. Studio | O49: Lulus | Q49: 32 | R49: 27 | S49: 7 | T49: 39 | U49: 40 | W49: =TEXT(L49,"dd mmmm yyyy") -> 15 Januari 2011 | X49: =IFERROR(VLOOKUP(D49,'[5]mhs elektro-kecil'!$B$5:$E$2151,3,0),"CEK") -> CEK | Y49: =IFERROR(VLOOKUP(D49,'[5]mhs elektro-kecil'!$B$5:$E$2151,4,0),"CEK") -> CEK | Z49: =L49 -> 40558 | AA49: =Z49+180 -> 40738 | AI49: =MID(D49,5,2) -> 06 | AL49: =IF(MID(D49,5,2)="06",2006,IF(MID(D49,5,2)="07",2007,IF(MID(D49,5,2)="08",2008,IF(MID(D49,5,2)="09",2009,IF(MID(D49,5,2)="10",2010,IF(MID(D49,5,2)="11",2011,IF(MID(D49,5,2)="12",2012,IF(MID(D49,5,2)="05",2005,IF(MID(D49,5,2)="04",2004,IF(MID(D49,5,2)="03",2003,IF(MID(D49,5,2)="13",2013,IF(MID(D49,5,2)="14",2014,IF(MID(D49,5,2)="15",2015,IF(MID(D49,5,2)="16",2016,IF(MID(D49,5,2)="17",2017,IF(MID(D49,5,2)="18",2018,2019)))))))))))))))) -> 2006 | AM49: =COUNTIF([6]Daftar!$D$5:$D$851,D49) -> #VALUE! | AN49: =COUNTIF([7]daftar!$D$4:$D$885,D49) -> #VALUE! | AS49: =C49 -> Thendriani Yastenti | AT49: =D49 -> F1B006081 | AU49: =A49 -> 46
A50: =A49+1 -> 47 | B50: 40554 | C50: =VLOOKUP(D50,'[4]mhs elektro-kecil'!$B$5:$C$1847,2,0) -> Das Rizal | D50: F1B006015 | E50: Perbaikan Kinerja PLTS dengan Simulasi Minimalisasi Harmonisa pada PLTS Dusun Selak, Lombok Tengah | F50: Sabar Nababan, S.T., M.T. | G50: Supriono, S.T., M.T. | H50: Ida Bagus Fery Citarsa, S.T., M.T. | I50: Abdul Natsir, S.T., M.T. | J50: Rosmaliati, S.T., M.T. | K50: Sabtu | L50: 40558 | M50: 08.00-10.00 | N50: R. D2 | O50: Lulus | Q50: 31 | R50: 29 | S50: 12 | T50: 14 | U50: 16 | W50: =TEXT(L50,"dd mmmm yyyy") -> 15 Januari 2011 | X50: =IFERROR(VLOOKUP(D50,'[5]mhs elektro-kecil'!$B$5:$E$2151,3,0),"CEK") -> CEK | Y50: =IFERROR(VLOOKUP(D50,'[5]mhs elektro-kecil'!$B$5:$E$2151,4,0),"CEK") -> CEK | Z50: =L50 -> 40558 | AA50: =Z50+180 -> 40738 | AI50: =MID(D50,5,2) -> 06 | AL50: =IF(MID(D50,5,2)="06",2006,IF(MID(D50,5,2)="07",2007,IF(MID(D50,5,2)="08",2008,IF(MID(D50,5,2)="09",2009,IF(MID(D50,5,2)="10",2010,IF(MID(D50,5,2)="11",2011,IF(MID(D50,5,2)="12",2012,IF(MID(D50,5,2)="05",2005,IF(MID(D50,5,2)="04",2004,IF(MID(D50,5,2)="03",2003,IF(MID(D50,5,2)="13",2013,IF(MID(D50,5,2)="14",2014,IF(MID(D50,5,2)="15",2015,IF(MID(D50,5,2)="16",2016,IF(MID(D50,5,2)="17",2017,IF(MID(D50,5,2)="18",2018,2019)))))))))))))))) -> 2006 | AM50: =COUNTIF([6]Daftar!$D$5:$D$851,D50) -> #VALUE! | AN50: =COUNTIF([7]daftar!$D$4:$D$885,D50) -> #VALUE! | AS50: =C50 -> Das Rizal | AT50: =D50 -> F1B006015 | AU50: =A50 -> 47
A51: =A50+1 -> 48 | B51: 40554 | C51: =VLOOKUP(D51,'[4]mhs elektro-kecil'!$B$5:$C$1847,2,0) -> Eva Rosdiana Dewi | D51: F1B006022 | E51: Pengukuran dan Analisa Pengaruh Interferensi terhadap Kuat Sinyal yang diterima Propagasi Kanal Radio dalam Ruang pada Frekuensi 2,4 GHz | F51: Abdullah Zainuddin, S.T., M.T. | G51: Sudi M. Al Sasongko, S.T., M.T. | H51: Djul Fikry Budiman, S.T., M.T. | I51: Syafarudin Ch, S.T., M.T. | J51: Made Sutha Yadnya, S.T., M.T. | K51: Sabtu | L51: 40558 | M51: 10.00-12.00 | N51: R. Studio | O51: Lulus | P51: 30 | Q51: 15 | R51: 6 | S51: 35 | T51: 4 | U51: 19 | W51: =TEXT(L51,"dd mmmm yyyy") -> 15 Januari 2011 | X51: =IFERROR(VLOOKUP(D51,'[5]mhs elektro-kecil'!$B$5:$E$2151,3,0),"CEK") -> CEK | Y51: =IFERROR(VLOOKUP(D51,'[5]mhs elektro-kecil'!$B$5:$E$2151,4,0),"CEK") -> CEK | Z51: =L51 -> 40558 | AA51: =Z51+180 -> 40738 | AC51: Lulus | AI51: =MID(D51,5,2) -> 06 | AL51: =IF(MID(D51,5,2)="06",2006,IF(MID(D51,5,2)="07",2007,IF(MID(D51,5,2)="08",2008,IF(MID(D51,5,2)="09",2009,IF(MID(D51,5,2)="10",2010,IF(MID(D51,5,2)="11",2011,IF(MID(D51,5,2)="12",2012,IF(MID(D51,5,2)="05",2005,IF(MID(D51,5,2)="04",2004,IF(MID(D51,5,2)="03",2003,IF(MID(D51,5,2)="13",2013,IF(MID(D51,5,2)="14",2014,IF(MID(D51,5,2)="15",2015,IF(MID(D51,5,2)="16",2016,IF(MID(D51,5,2)="17",2017,IF(MID(D51,5,2)="18",2018,2019)))))))))))))))) -> 2006 | AM51: =COUNTIF([6]Daftar!$D$5:$D$851,D51) -> #VALUE! | AN51: =COUNTIF([7]daftar!$D$4:$D$885,D51) -> #VALUE! | AS51: =C51 -> Eva Rosdiana Dewi | AT51: =D51 -> F1B006022 | AU51: =A51 -> 48
A52: =A51+1 -> 49 | B52: 40554 | C52: =VLOOKUP(D52,'[4]mhs elektro-kecil'!$B$5:$C$1847,2,0) -> Abdul Ra'Uf Alfansani | D52: F1B006002 | E52: Teknik Penyandian dan Penyembunyian Data Berbasis Algoritma Kriptosistem El Gamal dan Algoritma SVD (Singular Value Decomposition) | F52: Dr. Rismon H. Sianipar, S.T., M.Eng. | G52: Muhamad Irwan, S.T., M.T. | H52: Heri Wijayanto, S.T., M.T. | I52: I B K Widiartha, S.T., M.T. | J52: Lalu A. Syamsul Irfan A., S.T., M.Eng. | K52: Sabtu | L52: 40558 | M52: 10.00-12.00 | N52: R. D2 | O52: Lulus | Q52: 33 | R52: 39 | S52: 32 | T52: 27 | U52: 40 | W52: =TEXT(L52,"dd mmmm yyyy") -> 15 Januari 2011 | X52: =IFERROR(VLOOKUP(D52,'[5]mhs elektro-kecil'!$B$5:$E$2151,3,0),"CEK") -> CEK | Y52: =IFERROR(VLOOKUP(D52,'[5]mhs elektro-kecil'!$B$5:$E$2151,4,0),"CEK") -> CEK | Z52: =L52 -> 40558 | AA52: =Z52+180 -> 40738 | AC52: Lulus | AI52: =MID(D52,5,2) -> 06 | AL52: =IF(MID(D52,5,2)="06",2006,IF(MID(D52,5,2)="07",2007,IF(MID(D52,5,2)="08",2008,IF(MID(D52,5,2)="09",2009,IF(MID(D52,5,2)="10",2010,IF(MID(D52,5,2)="11",2011,IF(MID(D52,5,2)="12",2012,IF(MID(D52,5,2)="05",2005,IF(MID(D52,5,2)="04",2004,IF(MID(D52,5,2)="03",2003,IF(MID(D52,5,2)="13",2013,IF(MID(D52,5,2)="14",2014,IF(MID(D52,5,2)="15",2015,IF(MID(D52,5,2)="16",2016,IF(MID(D52,5,2)="17",2017,IF(MID(D52,5,2)="18",2018,2019)))))))))))))))) -> 2006 | AM52: =COUNTIF([6]Daftar!$D$5:$D$851,D52) -> #VALUE! | AN52: =COUNTIF([7]daftar!$D$4:$D$885,D52) -> #VALUE! | AS52: =C52 -> Abdul Ra'Uf Alfansani | AT52: =D52 -> F1B006002 | AU52: =A52 -> 49
A53: =A52+1 -> 50 | B53: 40556 | C53: =VLOOKUP(D53,'[4]mhs elektro-kecil'!$B$5:$C$1847,2,0) -> Agung Surya Wiguna | D53: F1B006004 | E53: Merekonstruksi Virus Melissa dan Pengembangan Fiturnya untuk Menghapus File-file Kritis dan Menghapus Semua File pada Drive D dan Cara Mengatasinya | F53: Dr. Rismon H. Sianipar, S.T., M.Eng. | G53: Heri Wijayanto, S.T., M.T. | H53: I B K Widiartha, S.T., M.T. | I53: Ir. Sri Endang Anjarwani, M.Kom. | J53: Muhamad Irwan, S.T., M.T. | K53: Senin | L53: 40560 | M53: 08.00-10.00 | N53: R. D2 | O53: Lulus | Q53: 33 | R53: 32 | S53: 27 | T53: 38 | U53: 39 | W53: =TEXT(L53,"dd mmmm yyyy") -> 17 Januari 2011 | X53: =IFERROR(VLOOKUP(D53,'[5]mhs elektro-kecil'!$B$5:$E$2151,3,0),"CEK") -> CEK | Y53: =IFERROR(VLOOKUP(D53,'[5]mhs elektro-kecil'!$B$5:$E$2151,4,0),"CEK") -> CEK | Z53: =L53 -> 40560 | AA53: =Z53+180 -> 40740 | AC53: Lulus | AI53: =MID(D53,5,2) -> 06 | AL53: =IF(MID(D53,5,2)="06",2006,IF(MID(D53,5,2)="07",2007,IF(MID(D53,5,2)="08",2008,IF(MID(D53,5,2)="09",2009,IF(MID(D53,5,2)="10",2010,IF(MID(D53,5,2)="11",2011,IF(MID(D53,5,2)="12",2012,IF(MID(D53,5,2)="05",2005,IF(MID(D53,5,2)="04",2004,IF(MID(D53,5,2)="03",2003,IF(MID(D53,5,2)="13",2013,IF(MID(D53,5,2)="14",2014,IF(MID(D53,5,2)="15",2015,IF(MID(D53,5,2)="16",2016,IF(MID(D53,5,2)="17",2017,IF(MID(D53,5,2)="18",2018,2019)))))))))))))))) -> 2006 | AM53: =COUNTIF([6]Daftar!$D$5:$D$851,D53) -> #VALUE! | AN53: =COUNTIF([7]daftar!$D$4:$D$885,D53) -> #VALUE! | AS53: =C53 -> Agung Surya Wiguna | AT53: =D53 -> F1B006004 | AU53: =A53 -> 50
A54: =A53+1 -> 51 | B54: 40571 | C54: =VLOOKUP(D54,'[4]mhs elektro-kecil'!$B$5:$C$1847,2,0) -> I Nyoman Gede Aryarta | D54: F1B006035 | E54: Identifikasi Karakteristik Suara Mesin Asinkron 3 Fasa terhadap Kerusakan Akibat Pembebanan Lebih dengan Metode FFT (Fast Fourier Transform) | F54: I Ketut Wiryajati, S.T., M.T. | G54: Dr. Rismon H. Sianipar, S.T., M.Eng. | H54: Ida Bagus Fery Citarsa, S.T., M.T. | I54: Agung Budi Muljono, S.T., M.T. | J54: Sabar Nababan, S.T., M.T. | K54: Senin | L54: 40574 | M54: 08.00-10.00 | N54: R. D2 | O54: Lulus | Q54: 3 | R54: 33 | S54: 12 | T54: 13 | U54: 31 | W54: =TEXT(L54,"dd mmmm yyyy") -> 31 Januari 2011 | X54: =IFERROR(VLOOKUP(D54,'[5]mhs elektro-kecil'!$B$5:$E$2151,3,0),"CEK") -> CEK | Y54: =IFERROR(VLOOKUP(D54,'[5]mhs elektro-kecil'!$B$5:$E$2151,4,0),"CEK") -> CEK | Z54: =L54 -> 40574 | AA54: =Z54+180 -> 40754 | AI54: =MID(D54,5,2) -> 06 | AL54: =IF(MID(D54,5,2)="06",2006,IF(MID(D54,5,2)="07",2007,IF(MID(D54,5,2)="08",2008,IF(MID(D54,5,2)="09",2009,IF(MID(D54,5,2)="10",2010,IF(MID(D54,5,2)="11",2011,IF(MID(D54,5,2)="12",2012,IF(MID(D54,5,2)="05",2005,IF(MID(D54,5,2)="04",2004,IF(MID(D54,5,2)="03",2003,IF(MID(D54,5,2)="13",2013,IF(MID(D54,5,2)="14",2014,IF(MID(D54,5,2)="15",2015,IF(MID(D54,5,2)="16",2016,IF(MID(D54,5,2)="17",2017,IF(MID(D54,5,2)="18",2018,2019)))))))))))))))) -> 2006 | AM54: =COUNTIF([6]Daftar!$D$5:$D$851,D54) -> #VALUE! | AN54: =COUNTIF([7]daftar!$D$4:$D$885,D54) -> #VALUE! | AS54: =C54 -> I Nyoman Gede Aryarta | AT54: =D54 -> F1B006035 | AU54: =A54 -> 51
A55: =A54+1 -> 52 | B55: 40571 | C55: =VLOOKUP(D55,'[4]mhs elektro-kecil'!$B$5:$C$1847,2,0) -> Ibnu Shina | D55: F1B006037 | E55: Identifikasi Karakteristik Suara Mesin DC Eksitasi Diri terhadap Kerusakan Akibat Pembebanan Lebih dengan Metode Wavelet | F55: I Ketut Wiryajati, S.T., M.T. | G55: Dr. Rismon H. Sianipar, S.T., M.Eng. | H55: I Made Ari Nrartha, S.T., M.T. | I55: Dr.rer.nat. Teti Zubaidah, S.T., M.T. | J55: Paniran, S.T., M.T. | K55: Senin | L55: 40574 | M55: 10.00-12.00 | N55: R. Studio | O55: Lulus | Q55: 3 | R55: 33 | S55: 25 | T55: 22 | U55: 28 | W55: =TEXT(L55,"dd mmmm yyyy") -> 31 Januari 2011 | X55: =IFERROR(VLOOKUP(D55,'[5]mhs elektro-kecil'!$B$5:$E$2151,3,0),"CEK") -> CEK | Y55: =IFERROR(VLOOKUP(D55,'[5]mhs elektro-kecil'!$B$5:$E$2151,4,0),"CEK") -> CEK | Z55: =L55 -> 40574 | AA55: =Z55+180 -> 40754 | AI55: =MID(D55,5,2) -> 06 | AL55: =IF(MID(D55,5,2)="06",2006,IF(MID(D55,5,2)="07",2007,IF(MID(D55,5,2)="08",2008,IF(MID(D55,5,2)="09",2009,IF(MID(D55,5,2)="10",2010,IF(MID(D55,5,2)="11",2011,IF(MID(D55,5,2)="12",2012,IF(MID(D55,5,2)="05",2005,IF(MID(D55,5,2)="04",2004,IF(MID(D55,5,2)="03",2003,IF(MID(D55,5,2)="13",2013,IF(MID(D55,5,2)="14",2014,IF(MID(D55,5,2)="15",2015,IF(MID(D55,5,2)="16",2016,IF(MID(D55,5,2)="17",2017,IF(MID(D55,5,2)="18",2018,2019)))))))))))))))) -> 2006 | AM55: =COUNTIF([6]Daftar!$D$5:$D$851,D55) -> #VALUE! | AN55: =COUNTIF([7]daftar!$D$4:$D$885,D55) -> #VALUE! | AS55: =C55 -> Ibnu Shina | AT55: =D55 -> F1B006037 | AU55: =A55 -> 52
A56: =A55+1 -> 53 | B56: 40571 | C56: =VLOOKUP(D56,'[4]mhs elektro-kecil'!$B$5:$C$1847,2,0) -> Indra Darmawan | D56: F1B006041 | E56: Identifikasi Karakteristik Suara Mesin Asinkron 3 Fasa terhadap Kerusakan Akibat Pembebanan Lebih dengan Metode DCT (Discrete Cosine Transform) | F56: I Ketut Wiryajati, S.T., M.T. | G56: Dr. Rismon H. Sianipar, S.T., M.Eng. | H56: Abdul Natsir, S.T., M.T. | I56: Rosmaliati, S.T., M.T. | J56: Supriono, S.T., M.T. | K56: Selasa | L56: 40575 | M56: 08.00-10.00 | N56: R. Studio | O56: Lulus | Q56: 3 | R56: 33 | S56: 14 | T56: 16 | U56: 29 | W56: =TEXT(L56,"dd mmmm yyyy") -> 01 Februari 2011 | X56: =IFERROR(VLOOKUP(D56,'[5]mhs elektro-kecil'!$B$5:$E$2151,3,0),"CEK") -> CEK | Y56: =IFERROR(VLOOKUP(D56,'[5]mhs elektro-kecil'!$B$5:$E$2151,4,0),"CEK") -> CEK | Z56: =L56 -> 40575 | AA56: =Z56+180 -> 40755 | AI56: =MID(D56,5,2) -> 06 | AL56: =IF(MID(D56,5,2)="06",2006,IF(MID(D56,5,2)="07",2007,IF(MID(D56,5,2)="08",2008,IF(MID(D56,5,2)="09",2009,IF(MID(D56,5,2)="10",2010,IF(MID(D56,5,2)="11",2011,IF(MID(D56,5,2)="12",2012,IF(MID(D56,5,2)="05",2005,IF(MID(D56,5,2)="04",2004,IF(MID(D56,5,2)="03",2003,IF(MID(D56,5,2)="13",2013,IF(MID(D56,5,2)="14",2014,IF(MID(D56,5,2)="15",2015,IF(MID(D56,5,2)="16",2016,IF(MID(D56,5,2)="17",2017,IF(MID(D56,5,2)="18",2018,2019)))))))))))))))) -> 2006 | AM56: =COUNTIF([6]Daftar!$D$5:$D$851,D56) -> #VALUE! | AN56: =COUNTIF([7]daftar!$D$4:$D$885,D56) -> #VALUE! | AS56: =C56 -> Indra Darmawan | AT56: =D56 -> F1B006041 | AU56: =A56 -> 53
A57: =A56+1 -> 54 | B57: 40590 | C57: =VLOOKUP(D57,'[4]mhs elektro-kecil'!$B$5:$C$1847,2,0) -> Salimyul Pathurrahmah | D57: F1B006075 | E57: Pengolahan Sinyal Fluktuasi Geomagnetik untuk Analisa Aktifitas Seismik Regional Menggunakan Prosedur Diferensiasi (Moving Average) dan Metode Analisis Polarisasi Magnetik | F57: Bulkis Kanata, S.T., M.T. | G57: Dr.rer.nat. Teti Zubaidah, S.T., M.T. | H57: Abdullah Zainuddin, S.T., M.T. | I57: I Made Budi Suksmadana, S.T., M.T. | J57: Ni Made Seniari, S.T., M.T. | K57: Jum'at | L57: 40592 | M57: 08.00-10.00 | N57: R. Studio | O57: Lulus | Q57: 21 | R57: 22 | S57: 15 | T57: 24 | U57: 1 | W57: =TEXT(L57,"dd mmmm yyyy") -> 18 Februari 2011 | X57: =IFERROR(VLOOKUP(D57,'[5]mhs elektro-kecil'!$B$5:$E$2151,3,0),"CEK") -> CEK | Y57: =IFERROR(VLOOKUP(D57,'[5]mhs elektro-kecil'!$B$5:$E$2151,4,0),"CEK") -> CEK | Z57: =L57 -> 40592 | AA57: =Z57+180 -> 40772 | AI57: =MID(D57,5,2) -> 06 | AL57: =IF(MID(D57,5,2)="06",2006,IF(MID(D57,5,2)="07",2007,IF(MID(D57,5,2)="08",2008,IF(MID(D57,5,2)="09",2009,IF(MID(D57,5,2)="10",2010,IF(MID(D57,5,2)="11",2011,IF(MID(D57,5,2)="12",2012,IF(MID(D57,5,2)="05",2005,IF(MID(D57,5,2)="04",2004,IF(MID(D57,5,2)="03",2003,IF(MID(D57,5,2)="13",2013,IF(MID(D57,5,2)="14",2014,IF(MID(D57,5,2)="15",2015,IF(MID(D57,5,2)="16",2016,IF(MID(D57,5,2)="17",2017,IF(MID(D57,5,2)="18",2018,2019)))))))))))))))) -> 2006 | AM57: =COUNTIF([6]Daftar!$D$5:$D$851,D57) -> #VALUE! | AN57: =COUNTIF([7]daftar!$D$4:$D$885,D57) -> #VALUE! | AS57: =C57 -> Salimyul Pathurrahmah | AT57: =D57 -> F1B006075 | AU57: =A57 -> 54
A58: =A57+1 -> 55 | B58: 40590 | C58: =VLOOKUP(D58,'[4]mhs elektro-kecil'!$B$5:$C$1847,2,0) -> Suhaidi | D58: F1B004072 | E58: Pengukuran Kandungan Sedimen Suspensi dengan Metode Intensitas Cahaya Berbasis Mikrokontroller AVR ATMEGA 8535 | F58: Supriono, S.T., M.T. | G58: Bulkis Kanata, S.T., M.T. | H58: Sudi M. Al Sasongko, S.T., M.T. | I58: Made Sutha Yadnya, S.T., M.T. | J58: Paniran, S.T., M.T. | K58: Sabtu | L58: 40593 | M58: 08.00-10.00 | N58: R. Studio | O58: DO | Q58: 29 | R58: 21 | S58: 6 | T58: 19 | U58: 28 | W58: =TEXT(L58,"dd mmmm yyyy") -> 19 Februari 2011 | X58: =IFERROR(VLOOKUP(D58,'[5]mhs elektro-kecil'!$B$5:$E$2151,3,0),"CEK") -> CEK | Y58: =IFERROR(VLOOKUP(D58,'[5]mhs elektro-kecil'!$B$5:$E$2151,4,0),"CEK") -> CEK | Z58: =L58 -> 40593 | AA58: =Z58+180 -> 40773 | AI58: =MID(D58,5,2) -> 04 | AL58: =IF(MID(D58,5,2)="06",2006,IF(MID(D58,5,2)="07",2007,IF(MID(D58,5,2)="08",2008,IF(MID(D58,5,2)="09",2009,IF(MID(D58,5,2)="10",2010,IF(MID(D58,5,2)="11",2011,IF(MID(D58,5,2)="12",2012,IF(MID(D58,5,2)="05",2005,IF(MID(D58,5,2)="04",2004,IF(MID(D58,5,2)="03",2003,IF(MID(D58,5,2)="13",2013,IF(MID(D58,5,2)="14",2014,IF(MID(D58,5,2)="15",2015,IF(MID(D58,5,2)="16",2016,IF(MID(D58,5,2)="17",2017,IF(MID(D58,5,2)="18",2018,2019)))))))))))))))) -> 2004 | AM58: =COUNTIF([6]Daftar!$D$5:$D$851,D58) -> #VALUE! | AN58: =COUNTIF([7]daftar!$D$4:$D$885,D58) -> #VALUE! | AS58: =C58 -> Suhaidi | AT58: =D58 -> F1B004072 | AU58: =A58 -> 55
A59: =A58+1 -> 56 | B59: 40590 | C59: =VLOOKUP(D59,'[4]mhs elektro-kecil'!$B$5:$C$1847,2,0) -> Shinta Primasari | D59: F1B006076 | E59: Simulasi Propagasi Pentransmisian LMDS untuk Redaman Hujan pada Daerah Mataram - Sesaot | F59: Made Sutha Yadnya, S.T., M.T. | G59: Bulkis Kanata, S.T., M.T. | H59: Muhamad Syamsu Iqbal, S.T., M.T., Ph.D. | I59: Abdullah Zainuddin, S.T., M.T. | J59: Sudi M. Al Sasongko, S.T., M.T. | K59: Sabtu | L59: 40593 | M59: 10.00-12.00 | N59: R. Studio | O59: Lulus | Q59: 19 | R59: 21 | S59: 18 | T59: 15 | U59: 6 | W59: =TEXT(L59,"dd mmmm yyyy") -> 19 Februari 2011 | X59: =IFERROR(VLOOKUP(D59,'[5]mhs elektro-kecil'!$B$5:$E$2151,3,0),"CEK") -> CEK | Y59: =IFERROR(VLOOKUP(D59,'[5]mhs elektro-kecil'!$B$5:$E$2151,4,0),"CEK") -> CEK | Z59: =L59 -> 40593 | AA59: =Z59+180 -> 40773 | AI59: =MID(D59,5,2) -> 06 | AL59: =IF(MID(D59,5,2)="06",2006,IF(MID(D59,5,2)="07",2007,IF(MID(D59,5,2)="08",2008,IF(MID(D59,5,2)="09",2009,IF(MID(D59,5,2)="10",2010,IF(MID(D59,5,2)="11",2011,IF(MID(D59,5,2)="12",2012,IF(MID(D59,5,2)="05",2005,IF(MID(D59,5,2)="04",2004,IF(MID(D59,5,2)="03",2003,IF(MID(D59,5,2)="13",2013,IF(MID(D59,5,2)="14",2014,IF(MID(D59,5,2)="15",2015,IF(MID(D59,5,2)="16",2016,IF(MID(D59,5,2)="17",2017,IF(MID(D59,5,2)="18",2018,2019)))))))))))))))) -> 2006 | AM59: =COUNTIF([6]Daftar!$D$5:$D$851,D59) -> #VALUE! | AN59: =COUNTIF([7]daftar!$D$4:$D$885,D59) -> #VALUE! | AS59: =C59 -> Shinta Primasari | AT59: =D59 -> F1B006076 | AU59: =A59 -> 56
A60: =A59+1 -> 57 | B60: 40590 | C60: =VLOOKUP(D60,'[4]mhs elektro-kecil'!$B$5:$C$1847,2,0) -> Kenyya Venaringan De Side | D60: F1B006044 | E60: Perancangan Pengatur Catu Daya Hybrid Otomatis pada Observatorium Geomagnetik Lombok (OGL) | F60: Dr.rer.nat. Teti Zubaidah, S.T., M.T. | G60: Paniran, S.T., M.T. | H60: I Made Ari Nrartha, S.T., M.T. | I60: Supriyatna, S.T., M.T. | J60: Ida Bagus Fery Citarsa, S.T., M.T. | K60: Sabtu | L60: 40593 | M60: 08.00-10.00 | N60: R. D2 | Q60: 22 | R60: 28 | S60: 25 | T60: 2 | U60: 12 | W60: =TEXT(L60,"dd mmmm yyyy") -> 19 Februari 2011 | X60: =IFERROR(VLOOKUP(D60,'[5]mhs elektro-kecil'!$B$5:$E$2151,3,0),"CEK") -> CEK | Y60: =IFERROR(VLOOKUP(D60,'[5]mhs elektro-kecil'!$B$5:$E$2151,4,0),"CEK") -> CEK | Z60: =L60 -> 40593 | AA60: =Z60+180 -> 40773 | AI60: =MID(D60,5,2) -> 06 | AL60: =IF(MID(D60,5,2)="06",2006,IF(MID(D60,5,2)="07",2007,IF(MID(D60,5,2)="08",2008,IF(MID(D60,5,2)="09",2009,IF(MID(D60,5,2)="10",2010,IF(MID(D60,5,2)="11",2011,IF(MID(D60,5,2)="12",2012,IF(MID(D60,5,2)="05",2005,IF(MID(D60,5,2)="04",2004,IF(MID(D60,5,2)="03",2003,IF(MID(D60,5,2)="13",2013,IF(MID(D60,5,2)="14",2014,IF(MID(D60,5,2)="15",2015,IF(MID(D60,5,2)="16",2016,IF(MID(D60,5,2)="17",2017,IF(MID(D60,5,2)="18",2018,2019)))))))))))))))) -> 2006 | AM60: =COUNTIF([6]Daftar!$D$5:$D$851,D60) -> #VALUE! | AN60: =COUNTIF([7]daftar!$D$4:$D$885,D60) -> #VALUE! | AS60: =C60 -> Kenyya Venaringan De Side | AT60: =D60 -> F1B006044 | AU60: =A60 -> 57
A61: =A60+1 -> 58 | B61: 40590 | C61: =VLOOKUP(D61,'[4]mhs elektro-kecil'!$B$5:$C$1847,2,0) -> R. R. Dwie Rosmiyati | D61: F1B006074 | E61: Sistem Pendukung Keputusan Seleksi Penentuan Jabatan pada PT. PLN (Persero) dengan Metode Profile Matching | F61: Heri Wijayanto, S.T., M.T. | G61: Dr. Misbahuddin, S.T., M.T. | H61: Budi Irmawati, S. Kom., M.T. | I61: Dr. Rismon H. Sianipar, S.T., M.Eng. | J61: Rosmaliati, S.T., M.T. | K61: Sabtu | L61: 40593 | M61: 10.00-12.00 | N61: R. D2 | O61: Lulus | Q61: 32 | R61: 7 | S61: 20 | T61: 33 | U61: 16 | W61: =TEXT(L61,"dd mmmm yyyy") -> 19 Februari 2011 | X61: =IFERROR(VLOOKUP(D61,'[5]mhs elektro-kecil'!$B$5:$E$2151,3,0),"CEK") -> CEK | Y61: =IFERROR(VLOOKUP(D61,'[5]mhs elektro-kecil'!$B$5:$E$2151,4,0),"CEK") -> CEK | Z61: =L61 -> 40593 | AA61: =Z61+180 -> 40773 | AI61: =MID(D61,5,2) -> 06 | AL61: =IF(MID(D61,5,2)="06",2006,IF(MID(D61,5,2)="07",2007,IF(MID(D61,5,2)="08",2008,IF(MID(D61,5,2)="09",2009,IF(MID(D61,5,2)="10",2010,IF(MID(D61,5,2)="11",2011,IF(MID(D61,5,2)="12",2012,IF(MID(D61,5,2)="05",2005,IF(MID(D61,5,2)="04",2004,IF(MID(D61,5,2)="03",2003,IF(MID(D61,5,2)="13",2013,IF(MID(D61,5,2)="14",2014,IF(MID(D61,5,2)="15",2015,IF(MID(D61,5,2)="16",2016,IF(MID(D61,5,2)="17",2017,IF(MID(D61,5,2)="18",2018,2019)))))))))))))))) -> 2006 | AM61: =COUNTIF([6]Daftar!$D$5:$D$851,D61) -> #VALUE! | AN61: =COUNTIF([7]daftar!$D$4:$D$885,D61) -> #VALUE! | AS61: =C61 -> R. R. Dwie Rosmiyati | AT61: =D61 -> F1B006074 | AU61: =A61 -> 58
A62: =A61+1 -> 59 | B62: 40602 | C62: =VLOOKUP(D62,'[4]mhs elektro-kecil'!$B$5:$C$1847,2,0) -> Suwandi Jaya Pratama | D62: F1B006078 | E62: Perancangan Sistem Telemetri Suhu Berbasis Layanan SMS (short message servive) Jaringan GSM untuk Pemantauan Aktifitas Serta Peringatan Dini Bencana Gunung Merapi | F62: Abdullah Zainuddin, S.T., M.T. | G62: Syafarudin Ch, S.T., M.T. | H62: Muhamad Syamsu Iqbal, S.T., M.T., Ph.D. | I62: Djul Fikry Budiman, S.T., M.T. | J62: Paniran, S.T., M.T. | K62: Kamis | L62: 40605 | M62: 14.00-16.00 | N62: R. Studio | O62: Sdh Ujian | Q62: 15 | R62: 4 | S62: 18 | T62: 35 | U62: 28 | W62: =TEXT(L62,"dd mmmm yyyy") -> 03 Maret 2011 | X62: =IFERROR(VLOOKUP(D62,'[5]mhs elektro-kecil'!$B$5:$E$2151,3,0),"CEK") -> CEK | Y62: =IFERROR(VLOOKUP(D62,'[5]mhs elektro-kecil'!$B$5:$E$2151,4,0),"CEK") -> CEK | Z62: =L62 -> 40605 | AA62: =Z62+180 -> 40785 | AI62: =MID(D62,5,2) -> 06 | AL62: =IF(MID(D62,5,2)="06",2006,IF(MID(D62,5,2)="07",2007,IF(MID(D62,5,2)="08",2008,IF(MID(D62,5,2)="09",2009,IF(MID(D62,5,2)="10",2010,IF(MID(D62,5,2)="11",2011,IF(MID(D62,5,2)="12",2012,IF(MID(D62,5,2)="05",2005,IF(MID(D62,5,2)="04",2004,IF(MID(D62,5,2)="03",2003,IF(MID(D62,5,2)="13",2013,IF(MID(D62,5,2)="14",2014,IF(MID(D62,5,2)="15",2015,IF(MID(D62,5,2)="16",2016,IF(MID(D62,5,2)="17",2017,IF(MID(D62,5,2)="18",2018,2019)))))))))))))))) -> 2006 | AM62: =COUNTIF([6]Daftar!$D$5:$D$851,D62) -> #VALUE! | AN62: =COUNTIF([7]daftar!$D$4:$D$885,D62) -> #VALUE! | AS62: =C62 -> Suwandi Jaya Pratama | AT62: =D62 -> F1B006078 | AU62: =A62 -> 59
A63: =A62+1 -> 60 | B63: 40602 | C63: =VLOOKUP(D63,'[4]mhs elektro-kecil'!$B$5:$C$1847,2,0) -> M. Riza Rizky | D63: F1B006058 | E63: Optimasi Ekonomi Dispacth Pembangkit Termal Sistem Kelistrikan Lombok dengan Menggunakan Metode MIPSO | F63: Supriyatna, S.T., M.T. | G63: Dr. Misbahuddin, S.T., M.T. | H63: Abdul Natsir, S.T., M.T. | I63: Agung Budi Muljono, S.T., M.T. | J63: Ni Made Seniari, S.T., M.T. | K63: Jum'at | L63: 40606 | M63: 09.30-11.30 | N63: Lab. Tenaga | O63: Lulus | Q63: 2 | R63: 7 | S63: 14 | T63: 13 | U63: 1 | W63: =TEXT(L63,"dd mmmm yyyy") -> 04 Maret 2011 | X63: =IFERROR(VLOOKUP(D63,'[5]mhs elektro-kecil'!$B$5:$E$2151,3,0),"CEK") -> CEK | Y63: =IFERROR(VLOOKUP(D63,'[5]mhs elektro-kecil'!$B$5:$E$2151,4,0),"CEK") -> CEK | Z63: =L63 -> 40606 | AA63: =Z63+180 -> 40786 | AI63: =MID(D63,5,2) -> 06 | AL63: =IF(MID(D63,5,2)="06",2006,IF(MID(D63,5,2)="07",2007,IF(MID(D63,5,2)="08",2008,IF(MID(D63,5,2)="09",2009,IF(MID(D63,5,2)="10",2010,IF(MID(D63,5,2)="11",2011,IF(MID(D63,5,2)="12",2012,IF(MID(D63,5,2)="05",2005,IF(MID(D63,5,2)="04",2004,IF(MID(D63,5,2)="03",2003,IF(MID(D63,5,2)="13",2013,IF(MID(D63,5,2)="14",2014,IF(MID(D63,5,2)="15",2015,IF(MID(D63,5,2)="16",2016,IF(MID(D63,5,2)="17",2017,IF(MID(D63,5,2)="18",2018,2019)))))))))))))))) -> 2006 | AM63: =COUNTIF([6]Daftar!$D$5:$D$851,D63) -> #VALUE! | AN63: =COUNTIF([7]daftar!$D$4:$D$885,D63) -> #VALUE! | AS63: =C63 -> M. Riza Rizky | AT63: =D63 -> F1B006058 | AU63: =A63 -> 60
A64: =A63+1 -> 61 | B64: 40609 | C64: =VLOOKUP(D64,'[4]mhs elektro-kecil'!$B$5:$C$1847,2,0) -> Mardiyah Hidayati | D64: F1B006056 | E64: Implementasi Algoritma Best First Search (BFS) untuk Permainan CIWA (congklak sasak) Menggunakan Java Server Pages (JSP) | F64: Heri Wijayanto, S.T., M.T. | G64: Budi Irmawati, S. Kom., M.T. | H64: I B K Widiartha, S.T., M.T. | I64: Dr. Rismon H. Sianipar, S.T., M.Eng. | J64: Lalu A. Syamsul Irfan A., S.T., M.Eng. | K64: Kamis | L64: 40612 | M64: 07.30-09.30 | N64: Lab. Komputer | O64: Lulus | Q64: 32 | R64: 20 | S64: 27 | T64: 33 | U64: 40 | W64: =TEXT(L64,"dd mmmm yyyy") -> 10 Maret 2011 | X64: =IFERROR(VLOOKUP(D64,'[5]mhs elektro-kecil'!$B$5:$E$2151,3,0),"CEK") -> CEK | Y64: =IFERROR(VLOOKUP(D64,'[5]mhs elektro-kecil'!$B$5:$E$2151,4,0),"CEK") -> CEK | Z64: =L64 -> 40612 | AA64: =Z64+180 -> 40792 | AI64: =MID(D64,5,2) -> 06 | AL64: =IF(MID(D64,5,2)="06",2006,IF(MID(D64,5,2)="07",2007,IF(MID(D64,5,2)="08",2008,IF(MID(D64,5,2)="09",2009,IF(MID(D64,5,2)="10",2010,IF(MID(D64,5,2)="11",2011,IF(MID(D64,5,2)="12",2012,IF(MID(D64,5,2)="05",2005,IF(MID(D64,5,2)="04",2004,IF(MID(D64,5,2)="03",2003,IF(MID(D64,5,2)="13",2013,IF(MID(D64,5,2)="14",2014,IF(MID(D64,5,2)="15",2015,IF(MID(D64,5,2)="16",2016,IF(MID(D64,5,2)="17",2017,IF(MID(D64,5,2)="18",2018,2019)))))))))))))))) -> 2006 | AM64: =COUNTIF([6]Daftar!$D$5:$D$851,D64) -> #VALUE! | AN64: =COUNTIF([7]daftar!$D$4:$D$885,D64) -> #VALUE! | AS64: =C64 -> Mardiyah Hidayati | AT64: =D64 -> F1B006056 | AU64: =A64 -> 61
A65: =A64+1 -> 62 | B65: 40623 | C65: =VLOOKUP(D65,'[4]mhs elektro-kecil'!$B$5:$C$1847,2,0) -> Azhari Hasbi | D65: F1B005008 | E65: Desain dan Implementasi Jaringan Hotspot Fakultas Teknik Universitas Mataram Menggunakan Chillispot Autentifikasi System dan Radius Server | F65: I B K Widiartha, S.T., M.T. | G65: Dr. Misbahuddin, S.T., M.T. | H65: Budi Irmawati, S. Kom., M.T. | I65: Ir. Sri Endang Anjarwani, M.Kom. | J65: Lalu A. Syamsul Irfan A., S.T., M.Eng. | K65: Kamis | L65: 40626 | M65: 14.00-16.00 | N65: R. D2 | O65: Lulus | Q65: 27 | R65: 7 | S65: 20 | T65: 38 | U65: 40 | W65: =TEXT(L65,"dd mmmm yyyy") -> 24 Maret 2011 | X65: =IFERROR(VLOOKUP(D65,'[5]mhs elektro-kecil'!$B$5:$E$2151,3,0),"CEK") -> CEK | Y65: =IFERROR(VLOOKUP(D65,'[5]mhs elektro-kecil'!$B$5:$E$2151,4,0),"CEK") -> CEK | Z65: =L65 -> 40626 | AA65: =Z65+180 -> 40806 | AI65: =MID(D65,5,2) -> 05 | AL65: =IF(MID(D65,5,2)="06",2006,IF(MID(D65,5,2)="07",2007,IF(MID(D65,5,2)="08",2008,IF(MID(D65,5,2)="09",2009,IF(MID(D65,5,2)="10",2010,IF(MID(D65,5,2)="11",2011,IF(MID(D65,5,2)="12",2012,IF(MID(D65,5,2)="05",2005,IF(MID(D65,5,2)="04",2004,IF(MID(D65,5,2)="03",2003,IF(MID(D65,5,2)="13",2013,IF(MID(D65,5,2)="14",2014,IF(MID(D65,5,2)="15",2015,IF(MID(D65,5,2)="16",2016,IF(MID(D65,5,2)="17",2017,IF(MID(D65,5,2)="18",2018,2019)))))))))))))))) -> 2005 | AM65: =COUNTIF([6]Daftar!$D$5:$D$851,D65) -> #VALUE! | AN65: =COUNTIF([7]daftar!$D$4:$D$885,D65) -> #VALUE! | AS65: =C65 -> Azhari Hasbi | AT65: =D65 -> F1B005008 | AU65: =A65 -> 62
A66: =A65+1 -> 63 | B66: 40625 | C66: =VLOOKUP(D66,'[4]mhs elektro-kecil'!$B$5:$C$1847,2,0) -> Arya Bangbang Sastra G. | D66: F1B006012 | E66: Pemanfaatan Algoritma Ant Colony System (ACS) untuk Penyelesaian Masalah Penjadwalan Praktikum pada Jurusan Teknik Elektro Universitas Mataram | F66: Heri Wijayanto, S.T., M.T. | G66: Dr. Misbahuddin, S.T., M.T. | H66: Ir. Sri Endang Anjarwani, M.Kom. | I66: Budi Irmawati, S. Kom., M.T. | J66: Supriyatna, S.T., M.T. | K66: Sabtu | L66: 40628 | M66: 10.00-12.00 | N66: R. Studio | O66: 40621 | Q66: 32 | R66: 7 | S66: 38 | T66: 20 | U66: 2 | W66: =TEXT(L66,"dd mmmm yyyy") -> 26 Maret 2011 | X66: =IFERROR(VLOOKUP(D66,'[5]mhs elektro-kecil'!$B$5:$E$2151,3,0),"CEK") -> CEK | Y66: =IFERROR(VLOOKUP(D66,'[5]mhs elektro-kecil'!$B$5:$E$2151,4,0),"CEK") -> CEK | Z66: =L66 -> 40628 | AA66: =Z66+180 -> 40808 | AI66: =MID(D66,5,2) -> 06 | AL66: =IF(MID(D66,5,2)="06",2006,IF(MID(D66,5,2)="07",2007,IF(MID(D66,5,2)="08",2008,IF(MID(D66,5,2)="09",2009,IF(MID(D66,5,2)="10",2010,IF(MID(D66,5,2)="11",2011,IF(MID(D66,5,2)="12",2012,IF(MID(D66,5,2)="05",2005,IF(MID(D66,5,2)="04",2004,IF(MID(D66,5,2)="03",2003,IF(MID(D66,5,2)="13",2013,IF(MID(D66,5,2)="14",2014,IF(MID(D66,5,2)="15",2015,IF(MID(D66,5,2)="16",2016,IF(MID(D66,5,2)="17",2017,IF(MID(D66,5,2)="18",2018,2019)))))))))))))))) -> 2006 | AM66: =COUNTIF([6]Daftar!$D$5:$D$851,D66) -> #VALUE! | AN66: =COUNTIF([7]daftar!$D$4:$D$885,D66) -> #VALUE! | AS66: =C66 -> Arya Bangbang Sastra G. | AT66: =D66 -> F1B006012 | AU66: =A66 -> 63
A67: =A66+1 -> 64 | B67: 40630 | C67: =VLOOKUP(D67,'[4]mhs elektro-kecil'!$B$5:$C$1847,2,0) -> Supriadi | D67: F1B004073 | E67: Perancangan dan Pembuatan Alat Ukur Kadar Alkohol dengan Osilator Berbasis Mikrontroller ATMEGA 8535 | F67: Supriono, S.T., M.T. | G67: I Made Budi Suksmadana, S.T., M.T. | H67: Syafarudin Ch, S.T., M.T. | I67: I Ketut Wiryajati, S.T., M.T. | J67: Muhamad Irwan, S.T., M.T. | K67: Kamis | L67: 40633 | M67: 09.30-11.30 | N67: Lab. Kendali | O67: Lulus | Q67: 29 | R67: 24 | S67: 4 | T67: 3 | U67: 39 | W67: =TEXT(L67,"dd mmmm yyyy") -> 31 Maret 2011 | X67: =IFERROR(VLOOKUP(D67,'[5]mhs elektro-kecil'!$B$5:$E$2151,3,0),"CEK") -> CEK | Y67: =IFERROR(VLOOKUP(D67,'[5]mhs elektro-kecil'!$B$5:$E$2151,4,0),"CEK") -> CEK | Z67: =L67 -> 40633 | AA67: =Z67+180 -> 40813 | AI67: =MID(D67,5,2) -> 04 | AL67: =IF(MID(D67,5,2)="06",2006,IF(MID(D67,5,2)="07",2007,IF(MID(D67,5,2)="08",2008,IF(MID(D67,5,2)="09",2009,IF(MID(D67,5,2)="10",2010,IF(MID(D67,5,2)="11",2011,IF(MID(D67,5,2)="12",2012,IF(MID(D67,5,2)="05",2005,IF(MID(D67,5,2)="04",2004,IF(MID(D67,5,2)="03",2003,IF(MID(D67,5,2)="13",2013,IF(MID(D67,5,2)="14",2014,IF(MID(D67,5,2)="15",2015,IF(MID(D67,5,2)="16",2016,IF(MID(D67,5,2)="17",2017,IF(MID(D67,5,2)="18",2018,2019)))))))))))))))) -> 2004 | AM67: =COUNTIF([6]Daftar!$D$5:$D$851,D67) -> #VALUE! | AN67: =COUNTIF([7]daftar!$D$4:$D$885,D67) -> #VALUE! | AS67: =C67 -> Supriadi | AT67: =D67 -> F1B004073 | AU67: =A67 -> 64
A68: =A67+1 -> 65 | B68: 40644 | C68: =VLOOKUP(D68,'[4]mhs elektro-kecil'!$B$5:$C$1847,2,0) -> Gst. Bgs. Surya Dharma Wibawa | D68: F1B006027 | E68: Mencari Pola Desain Kain Songket Sasak Menggunakan Fraktal Julia Set | F68: Dr. Rismon H. Sianipar, S.T., M.Eng. | H68: Ir. Sri Endang Anjarwani, M.Kom. | I68: I Made Budi Suksmadana, S.T., M.T. | J68: Muhamad Irwan, S.T., M.T. | K68: Jum'at | L68: 40648 | M68: 07.30-09.30 | N68: Lab. Komputer | O68: Lulus | P68: 379 | Q68: 33 | S68: 38 | T68: 24 | U68: 39 | W68: =TEXT(L68,"dd mmmm yyyy") -> 15 April 2011 | X68: =IFERROR(VLOOKUP(D68,'[5]mhs elektro-kecil'!$B$5:$E$2151,3,0),"CEK") -> CEK | Y68: =IFERROR(VLOOKUP(D68,'[5]mhs elektro-kecil'!$B$5:$E$2151,4,0),"CEK") -> CEK | Z68: =L68 -> 40648 | AA68: =Z68+180 -> 40828 | AI68: =MID(D68,5,2) -> 06 | AL68: =IF(MID(D68,5,2)="06",2006,IF(MID(D68,5,2)="07",2007,IF(MID(D68,5,2)="08",2008,IF(MID(D68,5,2)="09",2009,IF(MID(D68,5,2)="10",2010,IF(MID(D68,5,2)="11",2011,IF(MID(D68,5,2)="12",2012,IF(MID(D68,5,2)="05",2005,IF(MID(D68,5,2)="04",2004,IF(MID(D68,5,2)="03",2003,IF(MID(D68,5,2)="13",2013,IF(MID(D68,5,2)="14",2014,IF(MID(D68,5,2)="15",2015,IF(MID(D68,5,2)="16",2016,IF(MID(D68,5,2)="17",2017,IF(MID(D68,5,2)="18",2018,2019)))))))))))))))) -> 2006 | AM68: =COUNTIF([6]Daftar!$D$5:$D$851,D68) -> #VALUE! | AN68: =COUNTIF([7]daftar!$D$4:$D$885,D68) -> #VALUE! | AS68: =C68 -> Gst. Bgs. Surya Dharma Wibawa | AT68: =D68 -> F1B006027 | AU68: =A68 -> 65
A69: =A68+1 -> 66 | B69: 40644 | C69: =VLOOKUP(D69,'[4]mhs elektro-kecil'!$B$5:$C$1847,2,0) -> I Wyn Eka Rudytha Harimbawa | D69: F1B006036 | E69: Analisa Tingkat Keacakan dan Kemiripan Nilai Hash Haval dan Tiger Menggunakan Variabel Uji Probabilitas Bersyarat dan Korelasi Silang | F69: Dr. Rismon H. Sianipar, S.T., M.Eng. | H69: Made Sutha Yadnya, S.T., M.T. | I69: Muhamad Irwan, S.T., M.T. | J69: Lalu A. Syamsul Irfan A., S.T., M.Eng. | K69: Sabtu | L69: 40649 | M69: 10.00-12.00 | N69: Lab. Komputer | O69: Lulus | P69: 380 | Q69: 33 | S69: 19 | T69: 39 | U69: 40 | W69: =TEXT(L69,"dd mmmm yyyy") -> 16 April 2011 | X69: =IFERROR(VLOOKUP(D69,'[5]mhs elektro-kecil'!$B$5:$E$2151,3,0),"CEK") -> CEK | Y69: =IFERROR(VLOOKUP(D69,'[5]mhs elektro-kecil'!$B$5:$E$2151,4,0),"CEK") -> CEK | Z69: =L69 -> 40649 | AA69: =Z69+180 -> 40829 | AI69: =MID(D69,5,2) -> 06 | AL69: =IF(MID(D69,5,2)="06",2006,IF(MID(D69,5,2)="07",2007,IF(MID(D69,5,2)="08",2008,IF(MID(D69,5,2)="09",2009,IF(MID(D69,5,2)="10",2010,IF(MID(D69,5,2)="11",2011,IF(MID(D69,5,2)="12",2012,IF(MID(D69,5,2)="05",2005,IF(MID(D69,5,2)="04",2004,IF(MID(D69,5,2)="03",2003,IF(MID(D69,5,2)="13",2013,IF(MID(D69,5,2)="14",2014,IF(MID(D69,5,2)="15",2015,IF(MID(D69,5,2)="16",2016,IF(MID(D69,5,2)="17",2017,IF(MID(D69,5,2)="18",2018,2019)))))))))))))))) -> 2006 | AM69: =COUNTIF([6]Daftar!$D$5:$D$851,D69) -> #VALUE! | AN69: =COUNTIF([7]daftar!$D$4:$D$885,D69) -> #VALUE! | AS69: =C69 -> I Wyn Eka Rudytha Harimbawa | AT69: =D69 -> F1B006036 | AU69: =A69 -> 66
A70: =A69+1 -> 67 | B70: 40644 | C70: =VLOOKUP(D70,'[4]mhs elektro-kecil'!$B$5:$C$1847,2,0) -> M. Mizan Asrori | D70: F1B006053 | E70: Analisa Trafik dan Coverage Area pada Sistem Telekomunikasi Seluler Berbasis CDMA2000-1X di Wilayah Mataram | F70: Abdullah Zainuddin, S.T., M.T. | G70: Muhamad Syamsu Iqbal, S.T., M.T., Ph.D. | H70: Dr. Misbahuddin, S.T., M.T. | I70: Made Sutha Yadnya, S.T., M.T. | J70: Syafarudin Ch, S.T., M.T. | K70: Senin | L70: 40651 | M70: 10.00-12.00 | N70: Lab. Kendali | O70: DO | P70: 381 | Q70: 15 | R70: 18 | S70: 7 | T70: 19 | U70: 4 | W70: =TEXT(L70,"dd mmmm yyyy") -> 18 April 2011 | X70: =IFERROR(VLOOKUP(D70,'[5]mhs elektro-kecil'!$B$5:$E$2151,3,0),"CEK") -> CEK | Y70: =IFERROR(VLOOKUP(D70,'[5]mhs elektro-kecil'!$B$5:$E$2151,4,0),"CEK") -> CEK | Z70: =L70 -> 40651 | AA70: =Z70+180 -> 40831 | AI70: =MID(D70,5,2) -> 06 | AL70: =IF(MID(D70,5,2)="06",2006,IF(MID(D70,5,2)="07",2007,IF(MID(D70,5,2)="08",2008,IF(MID(D70,5,2)="09",2009,IF(MID(D70,5,2)="10",2010,IF(MID(D70,5,2)="11",2011,IF(MID(D70,5,2)="12",2012,IF(MID(D70,5,2)="05",2005,IF(MID(D70,5,2)="04",2004,IF(MID(D70,5,2)="03",2003,IF(MID(D70,5,2)="13",2013,IF(MID(D70,5,2)="14",2014,IF(MID(D70,5,2)="15",2015,IF(MID(D70,5,2)="16",2016,IF(MID(D70,5,2)="17",2017,IF(MID(D70,5,2)="18",2018,2019)))))))))))))))) -> 2006 | AM70: =COUNTIF([6]Daftar!$D$5:$D$851,D70) -> #VALUE! | AN70: =COUNTIF([7]daftar!$D$4:$D$885,D70) -> #VALUE! | AS70: =C70 -> M. Mizan Asrori | AT70: =D70 -> F1B006053 | AU70: =A70 -> 67
A71: =A70+1 -> 68 | B71: 40644 | C71: =VLOOKUP(D71,'[4]mhs elektro-kecil'!$B$5:$C$1847,2,0) -> Ariyan Nurrahman | D71: F1B006011 | E71: Mencari Pola Desain Kain Batik Yogakarta Menggunakan Fraktal Mandelbrot Set | F71: Dr. Rismon H. Sianipar, S.T., M.Eng. | H71: Ir. Sri Endang Anjarwani, M.Kom. | I71: Muhamad Irwan, S.T., M.T. | J71: Lalu A. Syamsul Irfan A., S.T., M.Eng. | K71: Senin | L71: 40651 | M71: 10.00-12.00 | N71: Lab. Komputer | O71: Lulus | P71: 382 | Q71: 33 | S71: 38 | T71: 39 | U71: 40 | W71: =TEXT(L71,"dd mmmm yyyy") -> 18 April 2011 | X71: =IFERROR(VLOOKUP(D71,'[5]mhs elektro-kecil'!$B$5:$E$2151,3,0),"CEK") -> CEK | Y71: =IFERROR(VLOOKUP(D71,'[5]mhs elektro-kecil'!$B$5:$E$2151,4,0),"CEK") -> CEK | Z71: =L71 -> 40651 | AA71: =Z71+180 -> 40831 | AI71: =MID(D71,5,2) -> 06 | AL71: =IF(MID(D71,5,2)="06",2006,IF(MID(D71,5,2)="07",2007,IF(MID(D71,5,2)="08",2008,IF(MID(D71,5,2)="09",2009,IF(MID(D71,5,2)="10",2010,IF(MID(D71,5,2)="11",2011,IF(MID(D71,5,2)="12",2012,IF(MID(D71,5,2)="05",2005,IF(MID(D71,5,2)="04",2004,IF(MID(D71,5,2)="03",2003,IF(MID(D71,5,2)="13",2013,IF(MID(D71,5,2)="14",2014,IF(MID(D71,5,2)="15",2015,IF(MID(D71,5,2)="16",2016,IF(MID(D71,5,2)="17",2017,IF(MID(D71,5,2)="18",2018,2019)))))))))))))))) -> 2006 | AM71: =COUNTIF([6]Daftar!$D$5:$D$851,D71) -> #VALUE! | AN71: =COUNTIF([7]daftar!$D$4:$D$885,D71) -> #VALUE! | AS71: =C71 -> Ariyan Nurrahman | AT71: =D71 -> F1B006011 | AU71: =A71 -> 68
A72: =A71+1 -> 69 | B72: 40669 | C72: =VLOOKUP(D72,'[4]mhs elektro-kecil'!$B$5:$C$1847,2,0) -> I Wayan Agus Sudharma | D72: F1B006043 | E72: Desain dan Realisasi Antenna Mikrostrip Recangular dengan Metode EMC (Electromagnetically Coupled) untuk Aplikasi Wireless LAN | F72: Sudi M. Al Sasongko, S.T., M.T. | G72: Abdullah Zainuddin, S.T., M.T. | H72: Muhamad Syamsu Iqbal, S.T., M.T., Ph.D. | I72: Bulkis Kanata, S.T., M.T. | J72: Djul Fikry Budiman, S.T., M.T. | K72: Selasa | L72: 40673 | M72: 09.30-11.30 | N72: Lab. Kendali | O72: Lulus | P72: 450 | Q72: 6 | R72: 15 | S72: 18 | T72: 21 | U72: 35 | W72: =TEXT(L72,"dd mmmm yyyy") -> 10 Mei 2011 | X72: =IFERROR(VLOOKUP(D72,'[5]mhs elektro-kecil'!$B$5:$E$2151,3,0),"CEK") -> CEK | Y72: =IFERROR(VLOOKUP(D72,'[5]mhs elektro-kecil'!$B$5:$E$2151,4,0),"CEK") -> CEK | Z72: =L72 -> 40673 | AA72: =Z72+180 -> 40853 | AI72: =MID(D72,5,2) -> 06 | AL72: =IF(MID(D72,5,2)="06",2006,IF(MID(D72,5,2)="07",2007,IF(MID(D72,5,2)="08",2008,IF(MID(D72,5,2)="09",2009,IF(MID(D72,5,2)="10",2010,IF(MID(D72,5,2)="11",2011,IF(MID(D72,5,2)="12",2012,IF(MID(D72,5,2)="05",2005,IF(MID(D72,5,2)="04",2004,IF(MID(D72,5,2)="03",2003,IF(MID(D72,5,2)="13",2013,IF(MID(D72,5,2)="14",2014,IF(MID(D72,5,2)="15",2015,IF(MID(D72,5,2)="16",2016,IF(MID(D72,5,2)="17",2017,IF(MID(D72,5,2)="18",2018,2019)))))))))))))))) -> 2006 | AM72: =COUNTIF([6]Daftar!$D$5:$D$851,D72) -> #VALUE! | AN72: =COUNTIF([7]daftar!$D$4:$D$885,D72) -> #VALUE! | AS72: =C72 -> I Wayan Agus Sudharma | AT72: =D72 -> F1B006043 | AU72: =A72 -> 69
A73: =A72+1 -> 70 | C73: =VLOOKUP(D73,'[4]mhs elektro-kecil'!$B$5:$C$1847,2,0) -> #N/A | W73: =TEXT(L73,"dd mmmm yyyy") -> 00 Januari 1900 | X73: =IFERROR(VLOOKUP(D73,'[5]mhs elektro-kecil'!$B$5:$E$2151,3,0),"CEK") -> CEK | Y73: =IFERROR(VLOOKUP(D73,'[5]mhs elektro-kecil'!$B$5:$E$2151,4,0),"CEK") -> CEK | Z73: =L73 -> 0 | AA73: =Z73+180 -> 180 | AI73: =MID(D73,5,2) | AL73: =IF(MID(D73,5,2)="06",2006,IF(MID(D73,5,2)="07",2007,IF(MID(D73,5,2)="08",2008,IF(MID(D73,5,2)="09",2009,IF(MID(D73,5,2)="10",2010,IF(MID(D73,5,2)="11",2011,IF(MID(D73,5,2)="12",2012,IF(MID(D73,5,2)="05",2005,IF(MID(D73,5,2)="04",2004,IF(MID(D73,5,2)="03",2003,IF(MID(D73,5,2)="13",2013,IF(MID(D73,5,2)="14",2014,IF(MID(D73,5,2)="15",2015,IF(MID(D73,5,2)="16",2016,IF(MID(D73,5,2)="17",2017,IF(MID(D73,5,2)="18",2018,2019)))))))))))))))) -> 2019 | AM73: =COUNTIF([6]Daftar!$D$5:$D$851,D73) -> #VALUE! | AN73: =COUNTIF([7]daftar!$D$4:$D$885,D73) -> #VALUE! | AS73: =C73 -> #N/A | AT73: =D73 -> 0 | AU73: =A73 -> 70
A74: =A73+1 -> 71 | B74: 40669 | C74: =VLOOKUP(D74,'[4]mhs elektro-kecil'!$B$5:$C$1847,2,0) -> Yoga Wiguna Pratama | D74: F1B006084 | E74: Rancang Bangun Game Multiplayer dengan Media Koneksi Bluetooth Berbasis J2ME | F74: Heri Wijayanto, S.T., M.T. | G74: Budi Irmawati, S. Kom., M.T. | H74: Dr. Misbahuddin, S.T., M.T. | I74: Ir. Sri Endang Anjarwani, M.Kom. | J74: I Made Budi Suksmadana, S.T., M.T. | K74: Rabu | L74: 40674 | M74: 07.30-09.30 | N74: Lab. Komputer | O74: Lulus | P74: 452 | Q74: 32 | R74: 20 | S74: 7 | T74: 38 | U74: 24 | W74: =TEXT(L74,"dd mmmm yyyy") -> 11 Mei 2011 | X74: =IFERROR(VLOOKUP(D74,'[5]mhs elektro-kecil'!$B$5:$E$2151,3,0),"CEK") -> CEK | Y74: =IFERROR(VLOOKUP(D74,'[5]mhs elektro-kecil'!$B$5:$E$2151,4,0),"CEK") -> CEK | Z74: =L74 -> 40674 | AA74: =Z74+180 -> 40854 | AI74: =MID(D74,5,2) -> 06 | AL74: =IF(MID(D74,5,2)="06",2006,IF(MID(D74,5,2)="07",2007,IF(MID(D74,5,2)="08",2008,IF(MID(D74,5,2)="09",2009,IF(MID(D74,5,2)="10",2010,IF(MID(D74,5,2)="11",2011,IF(MID(D74,5,2)="12",2012,IF(MID(D74,5,2)="05",2005,IF(MID(D74,5,2)="04",2004,IF(MID(D74,5,2)="03",2003,IF(MID(D74,5,2)="13",2013,IF(MID(D74,5,2)="14",2014,IF(MID(D74,5,2)="15",2015,IF(MID(D74,5,2)="16",2016,IF(MID(D74,5,2)="17",2017,IF(MID(D74,5,2)="18",2018,2019)))))))))))))))) -> 2006 | AM74: =COUNTIF([6]Daftar!$D$5:$D$851,D74) -> #VALUE! | AN74: =COUNTIF([7]daftar!$D$4:$D$885,D74) -> #VALUE! | AS74: =C74 -> Yoga Wiguna Pratama | AT74: =D74 -> F1B006084 | AU74: =A74 -> 71
A75: =A74+1 -> 72 | B75: 40673 | C75: =VLOOKUP(D75,'[4]mhs elektro-kecil'!$B$5:$C$1847,2,0) -> Mohamad Isywan | D75: F1B006059 | E75: Identifikasi Karakteristik Suara Mesin Asinkron 3 Fasa dengan Metode Wavelet terhadap Tingkat Pembebanan | F75: I Ketut Wiryajati, S.T., M.T. | G75: Dr. Rismon H. Sianipar, S.T., M.Eng. | H75: Ida Bagus Fery Citarsa, S.T., M.T. | I75: Agung Budi Muljono, S.T., M.T. | J75: I Made Ari Nrartha, S.T., M.T. | K75: Sabtu | L75: 40677 | M75: 08.00-10.00 | N75: R. D2 | O75: Lulus | P75: 456 | Q75: 3 | R75: 33 | S75: 12 | T75: 13 | U75: 25 | W75: =TEXT(L75,"dd mmmm yyyy") -> 14 Mei 2011 | X75: =IFERROR(VLOOKUP(D75,'[5]mhs elektro-kecil'!$B$5:$E$2151,3,0),"CEK") -> CEK | Y75: =IFERROR(VLOOKUP(D75,'[5]mhs elektro-kecil'!$B$5:$E$2151,4,0),"CEK") -> CEK | Z75: =L75 -> 40677 | AA75: =Z75+180 -> 40857 | AI75: =MID(D75,5,2) -> 06 | AL75: =IF(MID(D75,5,2)="06",2006,IF(MID(D75,5,2)="07",2007,IF(MID(D75,5,2)="08",2008,IF(MID(D75,5,2)="09",2009,IF(MID(D75,5,2)="10",2010,IF(MID(D75,5,2)="11",2011,IF(MID(D75,5,2)="12",2012,IF(MID(D75,5,2)="05",2005,IF(MID(D75,5,2)="04",2004,IF(MID(D75,5,2)="03",2003,IF(MID(D75,5,2)="13",2013,IF(MID(D75,5,2)="14",2014,IF(MID(D75,5,2)="15",2015,IF(MID(D75,5,2)="16",2016,IF(MID(D75,5,2)="17",2017,IF(MID(D75,5,2)="18",2018,2019)))))))))))))))) -> 2006 | AM75: =COUNTIF([6]Daftar!$D$5:$D$851,D75) -> #VALUE! | AN75: =COUNTIF([7]daftar!$D$4:$D$885,D75) -> #VALUE! | AS75: =C75 -> Mohamad Isywan | AT75: =D75 -> F1B006059 | AU75: =A75 -> 72
A76: =A75+1 -> 73 | C76: =VLOOKUP(D76,'[4]mhs elektro-kecil'!$B$5:$C$1847,2,0) -> #N/A | W76: =TEXT(L76,"dd mmmm yyyy") -> 00 Januari 1900 | X76: =IFERROR(VLOOKUP(D76,'[5]mhs elektro-kecil'!$B$5:$E$2151,3,0),"CEK") -> CEK | Y76: =IFERROR(VLOOKUP(D76,'[5]mhs elektro-kecil'!$B$5:$E$2151,4,0),"CEK") -> CEK | Z76: =L76 -> 0 | AA76: =Z76+180 -> 180 | AI76: =MID(D76,5,2) | AL76: =IF(MID(D76,5,2)="06",2006,IF(MID(D76,5,2)="07",2007,IF(MID(D76,5,2)="08",2008,IF(MID(D76,5,2)="09",2009,IF(MID(D76,5,2)="10",2010,IF(MID(D76,5,2)="11",2011,IF(MID(D76,5,2)="12",2012,IF(MID(D76,5,2)="05",2005,IF(MID(D76,5,2)="04",2004,IF(MID(D76,5,2)="03",2003,IF(MID(D76,5,2)="13",2013,IF(MID(D76,5,2)="14",2014,IF(MID(D76,5,2)="15",2015,IF(MID(D76,5,2)="16",2016,IF(MID(D76,5,2)="17",2017,IF(MID(D76,5,2)="18",2018,2019)))))))))))))))) -> 2019 | AM76: =COUNTIF([6]Daftar!$D$5:$D$851,D76) -> #VALUE! | AN76: =COUNTIF([7]daftar!$D$4:$D$885,D76) -> #VALUE! | AS76: =C76 -> #N/A | AT76: =D76 -> 0 | AU76: =A76 -> 73
A77: =A76+1 -> 74 | B77: 40674 | C77: =VLOOKUP(D77,'[4]mhs elektro-kecil'!$B$5:$C$1847,2,0) -> Muhamad Adi Tofan | D77: F1B006060 | E77: Implementasi CCTV Menggunakan Webcam sebagai Monitoring Ruang yang Dapat di Akses Melalui Handphone Menggunakan Jaringan Wi-Fi Berbasis WAP | F77: Heri Wijayanto, S.T., M.T. | G77: Budi Irmawati, S. Kom., M.T. | H77: Dr. Misbahuddin, S.T., M.T. | I77: Sudi M. Al Sasongko, S.T., M.T. | J77: Ir. Sri Endang Anjarwani, M.Kom. | K77: Kamis | L77: 40675 | M77: 11.30-13.30 | N77: Lab. Komputer | O77: Lulus | P77: 503 | Q77: 32 | R77: 20 | S77: 7 | T77: 6 | U77: 38 | W77: =TEXT(L77,"dd mmmm yyyy") -> 12 Mei 2011 | X77: =IFERROR(VLOOKUP(D77,'[5]mhs elektro-kecil'!$B$5:$E$2151,3,0),"CEK") -> CEK | Y77: =IFERROR(VLOOKUP(D77,'[5]mhs elektro-kecil'!$B$5:$E$2151,4,0),"CEK") -> CEK | Z77: =L77 -> 40675 | AA77: =Z77+180 -> 40855 | AI77: =MID(D77,5,2) -> 06 | AL77: =IF(MID(D77,5,2)="06",2006,IF(MID(D77,5,2)="07",2007,IF(MID(D77,5,2)="08",2008,IF(MID(D77,5,2)="09",2009,IF(MID(D77,5,2)="10",2010,IF(MID(D77,5,2)="11",2011,IF(MID(D77,5,2)="12",2012,IF(MID(D77,5,2)="05",2005,IF(MID(D77,5,2)="04",2004,IF(MID(D77,5,2)="03",2003,IF(MID(D77,5,2)="13",2013,IF(MID(D77,5,2)="14",2014,IF(MID(D77,5,2)="15",2015,IF(MID(D77,5,2)="16",2016,IF(MID(D77,5,2)="17",2017,IF(MID(D77,5,2)="18",2018,2019)))))))))))))))) -> 2006 | AM77: =COUNTIF([6]Daftar!$D$5:$D$851,D77) -> #VALUE! | AN77: =COUNTIF([7]daftar!$D$4:$D$885,D77) -> #VALUE! | AS77: =C77 -> Muhamad Adi Tofan | AT77: =D77 -> F1B006060 | AU77: =A77 -> 74
A78: =A77+1 -> 75 | B78: 40676 | C78: =VLOOKUP(D78,'[4]mhs elektro-kecil'!$B$5:$C$1847,2,0) -> M. Trisna Abung Z. | D78: F1B006055 | E78: Unjuk Kerja Kamera CCTV Menggunakan Webcam Melalui Jaringan Lokal / Intranet | F78: Heri Wijayanto, S.T., M.T. | G78: I B K Widiartha, S.T., M.T. | H78: Budi Irmawati, S. Kom., M.T. | I78: Abdullah Zainuddin, S.T., M.T. | J78: Ir. Sri Endang Anjarwani, M.Kom. | K78: Sabtu | L78: 40677 | M78: 11.30-13.30 | N78: R. Studio | O78: Lulus | P78: 451 | Q78: 32 | R78: 27 | S78: 20 | T78: 15 | U78: 38 | W78: =TEXT(L78,"dd mmmm yyyy") -> 14 Mei 2011 | X78: =IFERROR(VLOOKUP(D78,'[5]mhs elektro-kecil'!$B$5:$E$2151,3,0),"CEK") -> CEK | Y78: =IFERROR(VLOOKUP(D78,'[5]mhs elektro-kecil'!$B$5:$E$2151,4,0),"CEK") -> CEK | Z78: =L78 -> 40677 | AA78: =Z78+180 -> 40857 | AI78: =MID(D78,5,2) -> 06 | AL78: =IF(MID(D78,5,2)="06",2006,IF(MID(D78,5,2)="07",2007,IF(MID(D78,5,2)="08",2008,IF(MID(D78,5,2)="09",2009,IF(MID(D78,5,2)="10",2010,IF(MID(D78,5,2)="11",2011,IF(MID(D78,5,2)="12",2012,IF(MID(D78,5,2)="05",2005,IF(MID(D78,5,2)="04",2004,IF(MID(D78,5,2)="03",2003,IF(MID(D78,5,2)="13",2013,IF(MID(D78,5,2)="14",2014,IF(MID(D78,5,2)="15",2015,IF(MID(D78,5,2)="16",2016,IF(MID(D78,5,2)="17",2017,IF(MID(D78,5,2)="18",2018,2019)))))))))))))))) -> 2006 | AM78: =COUNTIF([6]Daftar!$D$5:$D$851,D78) -> #VALUE! | AN78: =COUNTIF([7]daftar!$D$4:$D$885,D78) -> #VALUE! | AS78: =C78 -> M. Trisna Abung Z. | AT78: =D78 -> F1B006055 | AU78: =A78 -> 75
A79: =A78+1 -> 76 | B79: 40697 | C79: =VLOOKUP(D79,'[4]mhs elektro-kecil'!$B$5:$C$1847,2,0) -> Irfan Januarianto | D79: F1B007037 | E79: Evaluasi Keandalan Penyulang pada Sistem Kelistrikan Lombok dengan Metode Realibility Network Equivalent Approach (RNEA) | F79: Supriyatna, S.T., M.T. | G79: Abdul Natsir, S.T., M.T. | H79: Agung Budi Muljono, S.T., M.T. | I79: Sabar Nababan, S.T., M.T. | J79: Dr.rer.nat. Teti Zubaidah, S.T., M.T. | K79: Rabu | L79: 40702 | M79: 09.30-11.30 | N79: Lab. Tenaga | O79: Lulus | P79: 545 | Q79: 2 | R79: 14 | S79: 13 | T79: 31 | U79: 22 | W79: =TEXT(L79,"dd mmmm yyyy") -> 08 Juni 2011 | X79: =IFERROR(VLOOKUP(D79,'[5]mhs elektro-kecil'!$B$5:$E$2151,3,0),"CEK") -> CEK | Y79: =IFERROR(VLOOKUP(D79,'[5]mhs elektro-kecil'!$B$5:$E$2151,4,0),"CEK") -> CEK | Z79: =L79 -> 40702 | AA79: =Z79+180 -> 40882 | AI79: =MID(D79,5,2) -> 07 | AL79: =IF(MID(D79,5,2)="06",2006,IF(MID(D79,5,2)="07",2007,IF(MID(D79,5,2)="08",2008,IF(MID(D79,5,2)="09",2009,IF(MID(D79,5,2)="10",2010,IF(MID(D79,5,2)="11",2011,IF(MID(D79,5,2)="12",2012,IF(MID(D79,5,2)="05",2005,IF(MID(D79,5,2)="04",2004,IF(MID(D79,5,2)="03",2003,IF(MID(D79,5,2)="13",2013,IF(MID(D79,5,2)="14",2014,IF(MID(D79,5,2)="15",2015,IF(MID(D79,5,2)="16",2016,IF(MID(D79,5,2)="17",2017,IF(MID(D79,5,2)="18",2018,2019)))))))))))))))) -> 2007 | AM79: =COUNTIF([6]Daftar!$D$5:$D$851,D79) -> #VALUE! | AN79: =COUNTIF([7]daftar!$D$4:$D$885,D79) -> #VALUE! | AS79: =C79 -> Irfan Januarianto | AT79: =D79 -> F1B007037 | AU79: =A79 -> 76
A80: =A79+1 -> 77 | B80: 40697 | C80: =VLOOKUP(D80,'[4]mhs elektro-kecil'!$B$5:$C$1847,2,0) -> Nasrullah | D80: F1B006063 | E80: Rancang Bangun Prototipe Peringatan Ketinggian Air Sungai Menggunakan SMS (short Message Service) Berbasis Mikrokontroller | F80: Syafarudin Ch, S.T., M.T. | G80: Dr. Misbahuddin, S.T., M.T. | H80: I Made Budi Suksmadana, S.T., M.T. | I80: Bulkis Kanata, S.T., M.T. | J80: Supriono, S.T., M.T. | K80: Kamis | L80: 40703 | M80: 09.30-11.30 | N80: Lab. Kendali | P80: 544 | Q80: 4 | R80: 7 | S80: 24 | T80: 21 | U80: 29 | W80: =TEXT(L80,"dd mmmm yyyy") -> 09 Juni 2011 | X80: =IFERROR(VLOOKUP(D80,'[5]mhs elektro-kecil'!$B$5:$E$2151,3,0),"CEK") -> CEK | Y80: =IFERROR(VLOOKUP(D80,'[5]mhs elektro-kecil'!$B$5:$E$2151,4,0),"CEK") -> CEK | Z80: =L80 -> 40703 | AA80: =Z80+180 -> 40883 | AI80: =MID(D80,5,2) -> 06 | AL80: =IF(MID(D80,5,2)="06",2006,IF(MID(D80,5,2)="07",2007,IF(MID(D80,5,2)="08",2008,IF(MID(D80,5,2)="09",2009,IF(MID(D80,5,2)="10",2010,IF(MID(D80,5,2)="11",2011,IF(MID(D80,5,2)="12",2012,IF(MID(D80,5,2)="05",2005,IF(MID(D80,5,2)="04",2004,IF(MID(D80,5,2)="03",2003,IF(MID(D80,5,2)="13",2013,IF(MID(D80,5,2)="14",2014,IF(MID(D80,5,2)="15",2015,IF(MID(D80,5,2)="16",2016,IF(MID(D80,5,2)="17",2017,IF(MID(D80,5,2)="18",2018,2019)))))))))))))))) -> 2006 | AM80: =COUNTIF([6]Daftar!$D$5:$D$851,D80) -> #VALUE! | AN80: =COUNTIF([7]daftar!$D$4:$D$885,D80) -> #VALUE! | AS80: =C80 -> Nasrullah | AT80: =D80 -> F1B006063 | AU80: =A80 -> 77
A81: =A80+1 -> 78 | B81: 40697 | C81: =VLOOKUP(D81,'[4]mhs elektro-kecil'!$B$5:$C$1847,2,0) -> Ibnu Solihin | D81: F1B004037 | E81: Teknik Penyandian Berbasis Kriptosistem Rabin dan Teknik Penanaman Pesan Berbasis DFT (Discrete Fourier Transformation) Diaplikasikan untuk Sinyal Audio | F81: Dr. Rismon H. Sianipar, S.T., M.Eng. | G81: #N/A | H81: Ir. Sri Endang Anjarwani, M.Kom. | I81: Made Sutha Yadnya, S.T., M.T. | J81: Lalu A. Syamsul Irfan A., S.T., M.Eng. | K81: Kamis | L81: 40703 | M81: 09.30-11.30 | N81: Lab. Komputer | O81: Lulus | P81: 542 | Q81: 33 | S81: 38 | T81: 19 | U81: 40 | W81: =TEXT(L81,"dd mmmm yyyy") -> 09 Juni 2011 | X81: =IFERROR(VLOOKUP(D81,'[5]mhs elektro-kecil'!$B$5:$E$2151,3,0),"CEK") -> CEK | Y81: =IFERROR(VLOOKUP(D81,'[5]mhs elektro-kecil'!$B$5:$E$2151,4,0),"CEK") -> CEK | Z81: =L81 -> 40703 | AA81: =Z81+180 -> 40883 | AI81: =MID(D81,5,2) -> 04 | AL81: =IF(MID(D81,5,2)="06",2006,IF(MID(D81,5,2)="07",2007,IF(MID(D81,5,2)="08",2008,IF(MID(D81,5,2)="09",2009,IF(MID(D81,5,2)="10",2010,IF(MID(D81,5,2)="11",2011,IF(MID(D81,5,2)="12",2012,IF(MID(D81,5,2)="05",2005,IF(MID(D81,5,2)="04",2004,IF(MID(D81,5,2)="03",2003,IF(MID(D81,5,2)="13",2013,IF(MID(D81,5,2)="14",2014,IF(MID(D81,5,2)="15",2015,IF(MID(D81,5,2)="16",2016,IF(MID(D81,5,2)="17",2017,IF(MID(D81,5,2)="18",2018,2019)))))))))))))))) -> 2004 | AM81: =COUNTIF([6]Daftar!$D$5:$D$851,D81) -> #VALUE! | AN81: =COUNTIF([7]daftar!$D$4:$D$885,D81) -> #VALUE! | AS81: =C81 -> Ibnu Solihin | AT81: =D81 -> F1B004037 | AU81: =A81 -> 78
A82: =A81+1 -> 79 | B82: 40707 | C82: =VLOOKUP(D82,'[4]mhs elektro-kecil'!$B$5:$C$1847,2,0) -> Jaka Edy Saputra | D82: F1B007039 | E82: Penentuan dan Perbaikan Indeks Kestabilan Saluran dengan Pemilihan Lokasi Penempatan Distributed Generation Menggunakan Metode Contingency (n-1) Analysis | F82: Agung Budi Muljono, S.T., M.T. | G82: I Made Ari Nrartha, S.T., M.T. | H82: Dr.rer.nat. Teti Zubaidah, S.T., M.T. | I82: Ni Made Seniari, S.T., M.T. | J82: Sultan, S.T., M.T. | K82: Rabu | L82: 40709 | M82: 09.30-11.30 | N82: Lab. Tenaga | O82: Lulus | P82: 571 | Q82: 13 | R82: 25 | S82: 22 | T82: 1 | U82: 5 | W82: =TEXT(L82,"dd mmmm yyyy") -> 15 Juni 2011 | X82: =IFERROR(VLOOKUP(D82,'[5]mhs elektro-kecil'!$B$5:$E$2151,3,0),"CEK") -> CEK | Y82: =IFERROR(VLOOKUP(D82,'[5]mhs elektro-kecil'!$B$5:$E$2151,4,0),"CEK") -> CEK | Z82: =L82 -> 40709 | AA82: =Z82+180 -> 40889 | AI82: =MID(D82,5,2) -> 07 | AL82: =IF(MID(D82,5,2)="06",2006,IF(MID(D82,5,2)="07",2007,IF(MID(D82,5,2)="08",2008,IF(MID(D82,5,2)="09",2009,IF(MID(D82,5,2)="10",2010,IF(MID(D82,5,2)="11",2011,IF(MID(D82,5,2)="12",2012,IF(MID(D82,5,2)="05",2005,IF(MID(D82,5,2)="04",2004,IF(MID(D82,5,2)="03",2003,IF(MID(D82,5,2)="13",2013,IF(MID(D82,5,2)="14",2014,IF(MID(D82,5,2)="15",2015,IF(MID(D82,5,2)="16",2016,IF(MID(D82,5,2)="17",2017,IF(MID(D82,5,2)="18",2018,2019)))))))))))))))) -> 2007 | AM82: =COUNTIF([6]Daftar!$D$5:$D$851,D82) -> #VALUE! | AN82: =COUNTIF([7]daftar!$D$4:$D$885,D82) -> #VALUE! | AS82: =C82 -> Jaka Edy Saputra | AT82: =D82 -> F1B007039 | AU82: =A82 -> 79
A83: =A82+1 -> 80 | B83: 40721 | C83: =VLOOKUP(D83,'[4]mhs elektro-kecil'!$B$5:$C$1847,2,0) -> Idkham Affandi | D83: F1B006038 | E83: Perancangan dan Implementasi Antena Microstrip Multiband Slot Rectangular U-shaped Tuning Stub untuk Aplikasi RFID Reader | F83: Abdullah Zainuddin, S.T., M.T. | G83: Sudi M. Al Sasongko, S.T., M.T. | H83: Bulkis Kanata, S.T., M.T. | I83: Made Sutha Yadnya, S.T., M.T. | J83: Muhamad Syamsu Iqbal, S.T., M.T., Ph.D. | K83: Jum'at | L83: 40725 | M83: 08.00-10.00 | N83: R. Studio | O83: Lulus | P83: 608 | Q83: 15 | R83: 6 | S83: 21 | T83: 19 | U83: 18 | W83: =TEXT(L83,"dd mmmm yyyy") -> 01 Juli 2011 | X83: =IFERROR(VLOOKUP(D83,'[5]mhs elektro-kecil'!$B$5:$E$2151,3,0),"CEK") -> CEK | Y83: =IFERROR(VLOOKUP(D83,'[5]mhs elektro-kecil'!$B$5:$E$2151,4,0),"CEK") -> CEK | Z83: =L83 -> 40725 | AA83: =Z83+180 -> 40905 | AI83: =MID(D83,5,2) -> 06 | AL83: =IF(MID(D83,5,2)="06",2006,IF(MID(D83,5,2)="07",2007,IF(MID(D83,5,2)="08",2008,IF(MID(D83,5,2)="09",2009,IF(MID(D83,5,2)="10",2010,IF(MID(D83,5,2)="11",2011,IF(MID(D83,5,2)="12",2012,IF(MID(D83,5,2)="05",2005,IF(MID(D83,5,2)="04",2004,IF(MID(D83,5,2)="03",2003,IF(MID(D83,5,2)="13",2013,IF(MID(D83,5,2)="14",2014,IF(MID(D83,5,2)="15",2015,IF(MID(D83,5,2)="16",2016,IF(MID(D83,5,2)="17",2017,IF(MID(D83,5,2)="18",2018,2019)))))))))))))))) -> 2006 | AM83: =COUNTIF([6]Daftar!$D$5:$D$851,D83) -> #VALUE! | AN83: =COUNTIF([7]daftar!$D$4:$D$885,D83) -> #VALUE! | AS83: =C83 -> Idkham Affandi | AT83: =D83 -> F1B006038 | AU83: =A83 -> 80
A84: =A83+1 -> 81 | B84: 40721 | C84: =VLOOKUP(D84,'[4]mhs elektro-kecil'!$B$5:$C$1847,2,0) -> Hidayati Vitria Ningsih | D84: F1B006032 | E84: Perancangan PLC Berbasis Mikrokontroler pada Aplikasi Counter dan Sorting Barang | F84: I Made Budi Suksmadana, S.T., M.T. | G84: I Made Ari Nrartha, S.T., M.T. | H84: Syafarudin Ch, S.T., M.T. | I84: Supriono, S.T., M.T. | J84: Muhamad Irwan, S.T., M.T. | K84: Sabtu | L84: 40726 | M84: 08.00-10.00 | N84: R. Studio | O84: Sdh Ujian | P84: 606 | Q84: 24 | R84: 25 | S84: 4 | T84: 29 | U84: 39 | W84: =TEXT(L84,"dd mmmm yyyy") -> 02 Juli 2011 | X84: =IFERROR(VLOOKUP(D84,'[5]mhs elektro-kecil'!$B$5:$E$2151,3,0),"CEK") -> CEK | Y84: =IFERROR(VLOOKUP(D84,'[5]mhs elektro-kecil'!$B$5:$E$2151,4,0),"CEK") -> CEK | Z84: =L84 -> 40726 | AA84: =Z84+180 -> 40906 | AI84: =MID(D84,5,2) -> 06 | AL84: =IF(MID(D84,5,2)="06",2006,IF(MID(D84,5,2)="07",2007,IF(MID(D84,5,2)="08",2008,IF(MID(D84,5,2)="09",2009,IF(MID(D84,5,2)="10",2010,IF(MID(D84,5,2)="11",2011,IF(MID(D84,5,2)="12",2012,IF(MID(D84,5,2)="05",2005,IF(MID(D84,5,2)="04",2004,IF(MID(D84,5,2)="03",2003,IF(MID(D84,5,2)="13",2013,IF(MID(D84,5,2)="14",2014,IF(MID(D84,5,2)="15",2015,IF(MID(D84,5,2)="16",2016,IF(MID(D84,5,2)="17",2017,IF(MID(D84,5,2)="18",2018,2019)))))))))))))))) -> 2006 | AM84: =COUNTIF([6]Daftar!$D$5:$D$851,D84) -> #VALUE! | AN84: =COUNTIF([7]daftar!$D$4:$D$885,D84) -> #VALUE! | AS84: =C84 -> Hidayati Vitria Ningsih | AT84: =D84 -> F1B006032 | AU84: =A84 -> 81
A85: =A84+1 -> 82 | B85: 40721 | C85: =VLOOKUP(D85,'[4]mhs elektro-kecil'!$B$5:$C$1847,2,0) -> Wersan Agus Saputra | D85: F1B004081 | E85: Sistem Informasi Inventaris Barang Laboratorium Teknik Elektro Fakultas Teknik Universitas Mataram | F85: Ir. Sri Endang Anjarwani, M.Kom. | G85: I B K Widiartha, S.T., M.T. | H85: Budi Irmawati, S. Kom., M.T. | I85: Supriyatna, S.T., M.T. | J85: Giri Wahyu Wiriasto, S.T., M.T. | K85: Sabtu | L85: 40726 | M85: 08.00-10.00 | N85: R. D2 | O85: Lulus | P85: 607 | Q85: 38 | R85: 27 | S85: 20 | T85: 2 | U85: 41 | W85: =TEXT(L85,"dd mmmm yyyy") -> 02 Juli 2011 | X85: =IFERROR(VLOOKUP(D85,'[5]mhs elektro-kecil'!$B$5:$E$2151,3,0),"CEK") -> CEK | Y85: =IFERROR(VLOOKUP(D85,'[5]mhs elektro-kecil'!$B$5:$E$2151,4,0),"CEK") -> CEK | Z85: =L85 -> 40726 | AA85: =Z85+180 -> 40906 | AI85: =MID(D85,5,2) -> 04 | AL85: =IF(MID(D85,5,2)="06",2006,IF(MID(D85,5,2)="07",2007,IF(MID(D85,5,2)="08",2008,IF(MID(D85,5,2)="09",2009,IF(MID(D85,5,2)="10",2010,IF(MID(D85,5,2)="11",2011,IF(MID(D85,5,2)="12",2012,IF(MID(D85,5,2)="05",2005,IF(MID(D85,5,2)="04",2004,IF(MID(D85,5,2)="03",2003,IF(MID(D85,5,2)="13",2013,IF(MID(D85,5,2)="14",2014,IF(MID(D85,5,2)="15",2015,IF(MID(D85,5,2)="16",2016,IF(MID(D85,5,2)="17",2017,IF(MID(D85,5,2)="18",2018,2019)))))))))))))))) -> 2004 | AM85: =COUNTIF([6]Daftar!$D$5:$D$851,D85) -> #VALUE! | AN85: =COUNTIF([7]daftar!$D$4:$D$885,D85) -> #VALUE! | AS85: =C85 -> Wersan Agus Saputra | AT85: =D85 -> F1B004081 | AU85: =A85 -> 82
A86: =A85+1 -> 83 | B86: 40721 | C86: =VLOOKUP(D86,'[4]mhs elektro-kecil'!$B$5:$C$1847,2,0) -> Hendra Febriawan | D86: F1B004028 | E86: Rancang Bangun Voltage Control Oscillator (VCO) Frequency 100 Mhz-2 Ghz | F86: Sudi M. Al Sasongko, S.T., M.T. | G86: Muhamad Syamsu Iqbal, S.T., M.T., Ph.D. | H86: Abdullah Zainuddin, S.T., M.T. | I86: Bulkis Kanata, S.T., M.T. | J86: Made Sutha Yadnya, S.T., M.T. | K86: Sabtu | L86: 40726 | M86: 10.00-12.00 | N86: R. Studio | O86: Lulus | P86: 608 | Q86: 6 | R86: 18 | S86: 15 | T86: 21 | U86: 19 | W86: =TEXT(L86,"dd mmmm yyyy") -> 02 Juli 2011 | X86: =IFERROR(VLOOKUP(D86,'[5]mhs elektro-kecil'!$B$5:$E$2151,3,0),"CEK") -> CEK | Y86: =IFERROR(VLOOKUP(D86,'[5]mhs elektro-kecil'!$B$5:$E$2151,4,0),"CEK") -> CEK | Z86: =L86 -> 40726 | AA86: =Z86+180 -> 40906 | AI86: =MID(D86,5,2) -> 04 | AL86: =IF(MID(D86,5,2)="06",2006,IF(MID(D86,5,2)="07",2007,IF(MID(D86,5,2)="08",2008,IF(MID(D86,5,2)="09",2009,IF(MID(D86,5,2)="10",2010,IF(MID(D86,5,2)="11",2011,IF(MID(D86,5,2)="12",2012,IF(MID(D86,5,2)="05",2005,IF(MID(D86,5,2)="04",2004,IF(MID(D86,5,2)="03",2003,IF(MID(D86,5,2)="13",2013,IF(MID(D86,5,2)="14",2014,IF(MID(D86,5,2)="15",2015,IF(MID(D86,5,2)="16",2016,IF(MID(D86,5,2)="17",2017,IF(MID(D86,5,2)="18",2018,2019)))))))))))))))) -> 2004 | AM86: =COUNTIF([6]Daftar!$D$5:$D$851,D86) -> #VALUE! | AN86: =COUNTIF([7]daftar!$D$4:$D$885,D86) -> #VALUE! | AS86: =C86 -> Hendra Febriawan | AT86: =D86 -> F1B004028 | AU86: =A86 -> 83
A87: =A86+1 -> 84 | B87: 40726 | C87: =VLOOKUP(D87,'[4]mhs elektro-kecil'!$B$5:$C$1847,2,0) -> M. Takdir Akbari Putra | D87: F1B005044 | E87: Identifikasi Posisi Jarak Melalui Perekaman Objek Sumber Suara | F87: I Made Budi Suksmadana, S.T., M.T. | G87: Sudi M. Al Sasongko, S.T., M.T. | H87: Made Sutha Yadnya, S.T., M.T. | I87: Muhamad Syamsu Iqbal, S.T., M.T., Ph.D. | J87: Abdullah Zainuddin, S.T., M.T. | K87: Selasa | L87: 40729 | M87: 08.00-10.00 | N87: R. Studio | P87: 613 | Q87: 24 | R87: 6 | S87: 19 | T87: 18 | U87: 15 | W87: =TEXT(L87,"dd mmmm yyyy") -> 05 Juli 2011 | X87: =IFERROR(VLOOKUP(D87,'[5]mhs elektro-kecil'!$B$5:$E$2151,3,0),"CEK") -> CEK | Y87: =IFERROR(VLOOKUP(D87,'[5]mhs elektro-kecil'!$B$5:$E$2151,4,0),"CEK") -> CEK | Z87: =L87 -> 40729 | AA87: =Z87+180 -> 40909 | AI87: =MID(D87,5,2) -> 05 | AL87: =IF(MID(D87,5,2)="06",2006,IF(MID(D87,5,2)="07",2007,IF(MID(D87,5,2)="08",2008,IF(MID(D87,5,2)="09",2009,IF(MID(D87,5,2)="10",2010,IF(MID(D87,5,2)="11",2011,IF(MID(D87,5,2)="12",2012,IF(MID(D87,5,2)="05",2005,IF(MID(D87,5,2)="04",2004,IF(MID(D87,5,2)="03",2003,IF(MID(D87,5,2)="13",2013,IF(MID(D87,5,2)="14",2014,IF(MID(D87,5,2)="15",2015,IF(MID(D87,5,2)="16",2016,IF(MID(D87,5,2)="17",2017,IF(MID(D87,5,2)="18",2018,2019)))))))))))))))) -> 2005 | AM87: =COUNTIF([6]Daftar!$D$5:$D$851,D87) -> #VALUE! | AN87: =COUNTIF([7]daftar!$D$4:$D$885,D87) -> #VALUE! | AS87: =C87 -> M. Takdir Akbari Putra | AT87: =D87 -> F1B005044 | AU87: =A87 -> 84
A88: =A87+1 -> 85 | B88: 40737 | C88: =VLOOKUP(D88,'[4]mhs elektro-kecil'!$B$5:$C$1847,2,0) -> Septia Haryani | D88: F1B007072 | E88: Teknik Steganografi dengan Algoritma Penyandian El-Gamal dengan Algoritma Dekomposisi SVD (Singular Value Decomposition) Berbasis Penanaman Bit HDSP (Hierarchical Data Security Protection) | F88: Dr. Rismon H. Sianipar, S.T., M.Eng. | G88: I Ketut Wiryajati, S.T., M.T. | H88: Ir. Sri Endang Anjarwani, M.Kom. | I88: Made Sutha Yadnya, S.T., M.T. | J88: Muhamad Irwan, S.T., M.T. | K88: Senin | L88: 40742 | M88: 08.00-10.00 | N88: R. D2 | O88: Lulus | P88: 654 | Q88: 33 | R88: 3 | S88: 38 | T88: 19 | U88: 39 | W88: =TEXT(L88,"dd mmmm yyyy") -> 18 Juli 2011 | X88: =IFERROR(VLOOKUP(D88,'[5]mhs elektro-kecil'!$B$5:$E$2151,3,0),"CEK") -> CEK | Y88: =IFERROR(VLOOKUP(D88,'[5]mhs elektro-kecil'!$B$5:$E$2151,4,0),"CEK") -> CEK | Z88: =L88 -> 40742 | AA88: =Z88+180 -> 40922 | AI88: =MID(D88,5,2) -> 07 | AL88: =IF(MID(D88,5,2)="06",2006,IF(MID(D88,5,2)="07",2007,IF(MID(D88,5,2)="08",2008,IF(MID(D88,5,2)="09",2009,IF(MID(D88,5,2)="10",2010,IF(MID(D88,5,2)="11",2011,IF(MID(D88,5,2)="12",2012,IF(MID(D88,5,2)="05",2005,IF(MID(D88,5,2)="04",2004,IF(MID(D88,5,2)="03",2003,IF(MID(D88,5,2)="13",2013,IF(MID(D88,5,2)="14",2014,IF(MID(D88,5,2)="15",2015,IF(MID(D88,5,2)="16",2016,IF(MID(D88,5,2)="17",2017,IF(MID(D88,5,2)="18",2018,2019)))))))))))))))) -> 2007 | AM88: =COUNTIF([6]Daftar!$D$5:$D$851,D88) -> #VALUE! | AN88: =COUNTIF([7]daftar!$D$4:$D$885,D88) -> #VALUE! | AS88: =C88 -> Septia Haryani | AT88: =D88 -> F1B007072 | AU88: =A88 -> 85
A89: =A88+1 -> 86 | B89: 40737 | C89: =VLOOKUP(D89,'[4]mhs elektro-kecil'!$B$5:$C$1847,2,0) -> Erfan Wiranata | D89: F1B007018 | E89: Autentikasi Integritas atas Video Digital AVI Berbasis Fungsi Hash MD6 dengan Skema Matyas Meyer Oseas | F89: Dr. Rismon H. Sianipar, S.T., M.Eng. | G89: I Ketut Wiryajati, S.T., M.T. | H89: Ir. Sri Endang Anjarwani, M.Kom. | I89: Bulkis Kanata, S.T., M.T. | J89: Lalu A. Syamsul Irfan A., S.T., M.Eng. | K89: Senin | L89: 40742 | M89: 10.00-12.00 | N89: R. D2 | O89: Lulus | P89: 655 | Q89: 33 | R89: 3 | S89: 38 | T89: 21 | U89: 40 | W89: =TEXT(L89,"dd mmmm yyyy") -> 18 Juli 2011 | X89: =IFERROR(VLOOKUP(D89,'[5]mhs elektro-kecil'!$B$5:$E$2151,3,0),"CEK") -> CEK | Y89: =IFERROR(VLOOKUP(D89,'[5]mhs elektro-kecil'!$B$5:$E$2151,4,0),"CEK") -> CEK | Z89: =L89 -> 40742 | AA89: =Z89+180 -> 40922 | AI89: =MID(D89,5,2) -> 07 | AL89: =IF(MID(D89,5,2)="06",2006,IF(MID(D89,5,2)="07",2007,IF(MID(D89,5,2)="08",2008,IF(MID(D89,5,2)="09",2009,IF(MID(D89,5,2)="10",2010,IF(MID(D89,5,2)="11",2011,IF(MID(D89,5,2)="12",2012,IF(MID(D89,5,2)="05",2005,IF(MID(D89,5,2)="04",2004,IF(MID(D89,5,2)="03",2003,IF(MID(D89,5,2)="13",2013,IF(MID(D89,5,2)="14",2014,IF(MID(D89,5,2)="15",2015,IF(MID(D89,5,2)="16",2016,IF(MID(D89,5,2)="17",2017,IF(MID(D89,5,2)="18",2018,2019)))))))))))))))) -> 2007 | AM89: =COUNTIF([6]Daftar!$D$5:$D$851,D89) -> #VALUE! | AN89: =COUNTIF([7]daftar!$D$4:$D$885,D89) -> #VALUE! | AS89: =C89 -> Erfan Wiranata | AT89: =D89 -> F1B007018 | AU89: =A89 -> 86
A90: =A89+1 -> 87 | B90: 40736 | C90: =VLOOKUP(D90,'[4]mhs elektro-kecil'!$B$5:$C$1847,2,0) -> Gede Hendy Hardiana | D90: F1B006026 | E90: Pengolahan dan Analisa Data ULF Geomagnetik Menggunakan Metode Gradien Vektor untuk Memprediksi Gempa Bumi | F90: Bulkis Kanata, S.T., M.T. | G90: Dr.rer.nat. Teti Zubaidah, S.T., M.T. | H90: Abdullah Zainuddin, S.T., M.T. | I90: Ni Made Seniari, S.T., M.T. | J90: Syafarudin Ch, S.T., M.T. | K90: Rabu | L90: 40744 | M90: 10.00-12.00 | N90: Lab. Listrik Dasar | O90: Lulus | P90: 665 | Q90: 21 | R90: 22 | S90: 15 | T90: 1 | U90: 4 | W90: =TEXT(L90,"dd mmmm yyyy") -> 20 Juli 2011 | X90: =IFERROR(VLOOKUP(D90,'[5]mhs elektro-kecil'!$B$5:$E$2151,3,0),"CEK") -> CEK | Y90: =IFERROR(VLOOKUP(D90,'[5]mhs elektro-kecil'!$B$5:$E$2151,4,0),"CEK") -> CEK | Z90: =L90 -> 40744 | AA90: =Z90+180 -> 40924 | AI90: =MID(D90,5,2) -> 06 | AL90: =IF(MID(D90,5,2)="06",2006,IF(MID(D90,5,2)="07",2007,IF(MID(D90,5,2)="08",2008,IF(MID(D90,5,2)="09",2009,IF(MID(D90,5,2)="10",2010,IF(MID(D90,5,2)="11",2011,IF(MID(D90,5,2)="12",2012,IF(MID(D90,5,2)="05",2005,IF(MID(D90,5,2)="04",2004,IF(MID(D90,5,2)="03",2003,IF(MID(D90,5,2)="13",2013,IF(MID(D90,5,2)="14",2014,IF(MID(D90,5,2)="15",2015,IF(MID(D90,5,2)="16",2016,IF(MID(D90,5,2)="17",2017,IF(MID(D90,5,2)="18",2018,2019)))))))))))))))) -> 2006 | AM90: =COUNTIF([6]Daftar!$D$5:$D$851,D90) -> #VALUE! | AN90: =COUNTIF([7]daftar!$D$4:$D$885,D90) -> #VALUE! | AS90: =C90 -> Gede Hendy Hardiana | AT90: =D90 -> F1B006026 | AU90: =A90 -> 87
A91: =A90+1 -> 88 | B91: 40736 | C91: =VLOOKUP(D91,'[4]mhs elektro-kecil'!$B$5:$C$1847,2,0) -> Ady Suharyanto | D91: F1B006003 | E91: Pengolahan dan Analisa Data ULF Geomagnetik Menggunakan Metode Kecepatan Fase untuk Memprediksi Aktifitas Seismik | F91: Bulkis Kanata, S.T., M.T. | G91: Dr.rer.nat. Teti Zubaidah, S.T., M.T. | H91: Sudi M. Al Sasongko, S.T., M.T. | I91: Made Sutha Yadnya, S.T., M.T. | J91: Dr. Rismon H. Sianipar, S.T., M.Eng. | K91: Rabu | L91: 40744 | M91: 08.00-10.00 | N91: Lab. Listrik Dasar | O91: Lulus | P91: 666 | Q91: 21 | R91: 22 | S91: 6 | T91: 19 | U91: 33 | W91: =TEXT(L91,"dd mmmm yyyy") -> 20 Juli 2011 | X91: =IFERROR(VLOOKUP(D91,'[5]mhs elektro-kecil'!$B$5:$E$2151,3,0),"CEK") -> CEK | Y91: =IFERROR(VLOOKUP(D91,'[5]mhs elektro-kecil'!$B$5:$E$2151,4,0),"CEK") -> CEK | Z91: =L91 -> 40744 | AA91: =Z91+180 -> 40924 | AI91: =MID(D91,5,2) -> 06 | AL91: =IF(MID(D91,5,2)="06",2006,IF(MID(D91,5,2)="07",2007,IF(MID(D91,5,2)="08",2008,IF(MID(D91,5,2)="09",2009,IF(MID(D91,5,2)="10",2010,IF(MID(D91,5,2)="11",2011,IF(MID(D91,5,2)="12",2012,IF(MID(D91,5,2)="05",2005,IF(MID(D91,5,2)="04",2004,IF(MID(D91,5,2)="03",2003,IF(MID(D91,5,2)="13",2013,IF(MID(D91,5,2)="14",2014,IF(MID(D91,5,2)="15",2015,IF(MID(D91,5,2)="16",2016,IF(MID(D91,5,2)="17",2017,IF(MID(D91,5,2)="18",2018,2019)))))))))))))))) -> 2006 | AM91: =COUNTIF([6]Daftar!$D$5:$D$851,D91) -> #VALUE! | AN91: =COUNTIF([7]daftar!$D$4:$D$885,D91) -> #VALUE! | AS91: =C91 -> Ady Suharyanto | AT91: =D91 -> F1B006003 | AU91: =A91 -> 88
A92: =A91+1 -> 89 | B92: 40744 | C92: =VLOOKUP(D92,'[4]mhs elektro-kecil'!$B$5:$C$1847,2,0) -> Heri Adi Wijaya K | D92: F1B004030 | E92: Rancang Bangun Sistem Transfer Energi Tanpa Kabel (Wireless) Menggunakan Kopling Induktif untuk Charger Handphone (HP) | F92: Abdullah Zainuddin, S.T., M.T. | G92: Syafarudin Ch, S.T., M.T. | H92: Bulkis Kanata, S.T., M.T. | I92: Ni Made Seniari, S.T., M.T. | J92: Sabar Nababan, S.T., M.T. | K92: Senin | L92: 40749 | M92: 08.00-10.00 | N92: R. D2 | O92: Lulus | P92: 684 | Q92: 15 | R92: 4 | S92: 21 | T92: 1 | U92: 31 | W92: =TEXT(L92,"dd mmmm yyyy") -> 25 Juli 2011 | X92: =IFERROR(VLOOKUP(D92,'[5]mhs elektro-kecil'!$B$5:$E$2151,3,0),"CEK") -> CEK | Y92: =IFERROR(VLOOKUP(D92,'[5]mhs elektro-kecil'!$B$5:$E$2151,4,0),"CEK") -> CEK | Z92: =L92 -> 40749 | AA92: =Z92+180 -> 40929 | AI92: =MID(D92,5,2) -> 04 | AL92: =IF(MID(D92,5,2)="06",2006,IF(MID(D92,5,2)="07",2007,IF(MID(D92,5,2)="08",2008,IF(MID(D92,5,2)="09",2009,IF(MID(D92,5,2)="10",2010,IF(MID(D92,5,2)="11",2011,IF(MID(D92,5,2)="12",2012,IF(MID(D92,5,2)="05",2005,IF(MID(D92,5,2)="04",2004,IF(MID(D92,5,2)="03",2003,IF(MID(D92,5,2)="13",2013,IF(MID(D92,5,2)="14",2014,IF(MID(D92,5,2)="15",2015,IF(MID(D92,5,2)="16",2016,IF(MID(D92,5,2)="17",2017,IF(MID(D92,5,2)="18",2018,2019)))))))))))))))) -> 2004 | AM92: =COUNTIF([6]Daftar!$D$5:$D$851,D92) -> #VALUE! | AN92: =COUNTIF([7]daftar!$D$4:$D$885,D92) -> #VALUE! | AS92: =C92 -> Heri Adi Wijaya K | AT92: =D92 -> F1B004030 | AU92: =A92 -> 89
A93: =A92+1 -> 90 | B93: 40744 | C93: =VLOOKUP(D93,'[4]mhs elektro-kecil'!$B$5:$C$1847,2,0) -> Sony Syawaliansyah | D93: F1B007076 | E93: Autentikasi Entitas Atas Video Digital AVI Berbasis Tanda Tangan Digital Schnorr | F93: Dr. Rismon H. Sianipar, S.T., M.Eng. | G93: I Ketut Wiryajati, S.T., M.T. | H93: I B K Widiartha, S.T., M.T. | I93: I Made Budi Suksmadana, S.T., M.T. | J93: Lalu A. Syamsul Irfan A., S.T., M.Eng. | K93: Sabtu | L93: 40747 | M93: 10.00-12.00 | N93: R. Studio | O93: Lulus | P93: 683 | Q93: 33 | R93: 3 | S93: 27 | T93: 24 | U93: 40 | W93: =TEXT(L93,"dd mmmm yyyy") -> 23 Juli 2011 | X93: =IFERROR(VLOOKUP(D93,'[5]mhs elektro-kecil'!$B$5:$E$2151,3,0),"CEK") -> CEK | Y93: =IFERROR(VLOOKUP(D93,'[5]mhs elektro-kecil'!$B$5:$E$2151,4,0),"CEK") -> CEK | Z93: =L93 -> 40747 | AA93: =Z93+180 -> 40927 | AI93: =MID(D93,5,2) -> 07 | AL93: =IF(MID(D93,5,2)="06",2006,IF(MID(D93,5,2)="07",2007,IF(MID(D93,5,2)="08",2008,IF(MID(D93,5,2)="09",2009,IF(MID(D93,5,2)="10",2010,IF(MID(D93,5,2)="11",2011,IF(MID(D93,5,2)="12",2012,IF(MID(D93,5,2)="05",2005,IF(MID(D93,5,2)="04",2004,IF(MID(D93,5,2)="03",2003,IF(MID(D93,5,2)="13",2013,IF(MID(D93,5,2)="14",2014,IF(MID(D93,5,2)="15",2015,IF(MID(D93,5,2)="16",2016,IF(MID(D93,5,2)="17",2017,IF(MID(D93,5,2)="18",2018,2019)))))))))))))))) -> 2007 | AM93: =COUNTIF([6]Daftar!$D$5:$D$851,D93) -> #VALUE! | AN93: =COUNTIF([7]daftar!$D$4:$D$885,D93) -> #VALUE! | AS93: =C93 -> Sony Syawaliansyah | AT93: =D93 -> F1B007076 | AU93: =A93 -> 90
A94: =A93+1 -> 91 | B94: 40754 | C94: =VLOOKUP(D94,'[4]mhs elektro-kecil'!$B$5:$C$1847,2,0) -> Akbar Juliansyah | D94: F1B006006 | E94: Penerapan Teknologi Web Application, SMS Gateway dan J2ME pada Sistem Informasi Penghitung Angka Kredit Dosen (Studi Kasus pada FT Unram) | F94: I B K Widiartha, S.T., M.T. | G94: Ir. Sri Endang Anjarwani, M.Kom. | H94: Heri Wijayanto, S.T., M.T. | I94: Budi Irmawati, S. Kom., M.T. | J94: Paniran, S.T., M.T. | K94: Senin | L94: 40756 | M94: 08.00-10.00 | N94: R. D2 | P94: 713 | Q94: 27 | R94: 38 | S94: 32 | T94: 20 | U94: 28 | W94: =TEXT(L94,"dd mmmm yyyy") -> 01 Agustus 2011 | X94: =IFERROR(VLOOKUP(D94,'[5]mhs elektro-kecil'!$B$5:$E$2151,3,0),"CEK") -> CEK | Y94: =IFERROR(VLOOKUP(D94,'[5]mhs elektro-kecil'!$B$5:$E$2151,4,0),"CEK") -> CEK | Z94: =L94 -> 40756 | AA94: =Z94+180 -> 40936 | AI94: =MID(D94,5,2) -> 06 | AL94: =IF(MID(D94,5,2)="06",2006,IF(MID(D94,5,2)="07",2007,IF(MID(D94,5,2)="08",2008,IF(MID(D94,5,2)="09",2009,IF(MID(D94,5,2)="10",2010,IF(MID(D94,5,2)="11",2011,IF(MID(D94,5,2)="12",2012,IF(MID(D94,5,2)="05",2005,IF(MID(D94,5,2)="04",2004,IF(MID(D94,5,2)="03",2003,IF(MID(D94,5,2)="13",2013,IF(MID(D94,5,2)="14",2014,IF(MID(D94,5,2)="15",2015,IF(MID(D94,5,2)="16",2016,IF(MID(D94,5,2)="17",2017,IF(MID(D94,5,2)="18",2018,2019)))))))))))))))) -> 2006 | AM94: =COUNTIF([6]Daftar!$D$5:$D$851,D94) -> #VALUE! | AN94: =COUNTIF([7]daftar!$D$4:$D$885,D94) -> #VALUE! | AS94: =C94 -> Akbar Juliansyah | AT94: =D94 -> F1B006006 | AU94: =A94 -> 91
A95: =A94+1 -> 92 | B95: 40765 | C95: =VLOOKUP(D95,'[4]mhs elektro-kecil'!$B$5:$C$1847,2,0) -> Singgih Herjuno Jati | D95: F1B007074 | E95: Rancang Bangun Pembangkit Listrik dengan Sistem Mesin Kalor Menggunakan Delapan Piston | F95: Syafarudin Ch, S.T., M.T. | G95: Abdul Natsir, S.T., M.T. | H95: Paniran, S.T., M.T. | I95: Agung Budi Muljono, S.T., M.T. | J95: Rosmaliati, S.T., M.T. | K95: Sabtu | L95: 40768 | M95: 08.00-10.00 | N95: R. D2 | O95: Lulus | P95: 738 | Q95: 4 | R95: 14 | S95: 28 | T95: 13 | U95: 16 | W95: =TEXT(L95,"dd mmmm yyyy") -> 13 Agustus 2011 | X95: =IFERROR(VLOOKUP(D95,'[5]mhs elektro-kecil'!$B$5:$E$2151,3,0),"CEK") -> CEK | Y95: =IFERROR(VLOOKUP(D95,'[5]mhs elektro-kecil'!$B$5:$E$2151,4,0),"CEK") -> CEK | Z95: =L95 -> 40768 | AA95: =Z95+180 -> 40948 | AI95: =MID(D95,5,2) -> 07 | AL95: =IF(MID(D95,5,2)="06",2006,IF(MID(D95,5,2)="07",2007,IF(MID(D95,5,2)="08",2008,IF(MID(D95,5,2)="09",2009,IF(MID(D95,5,2)="10",2010,IF(MID(D95,5,2)="11",2011,IF(MID(D95,5,2)="12",2012,IF(MID(D95,5,2)="05",2005,IF(MID(D95,5,2)="04",2004,IF(MID(D95,5,2)="03",2003,IF(MID(D95,5,2)="13",2013,IF(MID(D95,5,2)="14",2014,IF(MID(D95,5,2)="15",2015,IF(MID(D95,5,2)="16",2016,IF(MID(D95,5,2)="17",2017,IF(MID(D95,5,2)="18",2018,2019)))))))))))))))) -> 2007 | AM95: =COUNTIF([6]Daftar!$D$5:$D$851,D95) -> #VALUE! | AN95: =COUNTIF([7]daftar!$D$4:$D$885,D95) -> #VALUE! | AS95: =C95 -> Singgih Herjuno Jati | AT95: =D95 -> F1B007074 | AU95: =A95 -> 92
A96: =A95+1 -> 93 | B96: 40777 | C96: =VLOOKUP(D96,'[4]mhs elektro-kecil'!$B$5:$C$1847,2,0) -> Reza Rachmadani Fajrin | D96: F1B007065 | E96: Pengalokasian Rugi Daya pada Sistem Distribusi Primer Lombok Menggunakan Metode Z-Bus | F96: Supriyatna, S.T., M.T. | G96: Ida Bagus Fery Citarsa, S.T., M.T. | H96: Sultan, S.T., M.T. | I96: I Made Ari Nrartha, S.T., M.T. | J96: Agung Budi Muljono, S.T., M.T. | K96: Selasa | L96: 40778 | M96: 15.00-17.00 | N96: R. D2 | O96: Lulus | P96: 769 | Q96: 2 | R96: 12 | S96: 5 | T96: 25 | U96: 13 | W96: =TEXT(L96,"dd mmmm yyyy") -> 23 Agustus 2011 | X96: =IFERROR(VLOOKUP(D96,'[5]mhs elektro-kecil'!$B$5:$E$2151,3,0),"CEK") -> CEK | Y96: =IFERROR(VLOOKUP(D96,'[5]mhs elektro-kecil'!$B$5:$E$2151,4,0),"CEK") -> CEK | Z96: =L96 -> 40778 | AA96: =Z96+180 -> 40958 | AI96: =MID(D96,5,2) -> 07 | AL96: =IF(MID(D96,5,2)="06",2006,IF(MID(D96,5,2)="07",2007,IF(MID(D96,5,2)="08",2008,IF(MID(D96,5,2)="09",2009,IF(MID(D96,5,2)="10",2010,IF(MID(D96,5,2)="11",2011,IF(MID(D96,5,2)="12",2012,IF(MID(D96,5,2)="05",2005,IF(MID(D96,5,2)="04",2004,IF(MID(D96,5,2)="03",2003,IF(MID(D96,5,2)="13",2013,IF(MID(D96,5,2)="14",2014,IF(MID(D96,5,2)="15",2015,IF(MID(D96,5,2)="16",2016,IF(MID(D96,5,2)="17",2017,IF(MID(D96,5,2)="18",2018,2019)))))))))))))))) -> 2007 | AM96: =COUNTIF([6]Daftar!$D$5:$D$851,D96) -> #VALUE! | AN96: =COUNTIF([7]daftar!$D$4:$D$885,D96) -> #VALUE! | AS96: =C96 -> Reza Rachmadani Fajrin | AT96: =D96 -> F1B007065 | AU96: =A96 -> 93
A97: =A96+1 -> 94 | B97: 40812 | C97: =VLOOKUP(D97,'[4]mhs elektro-kecil'!$B$5:$C$1847,2,0) -> Mizar Febrian | D97: F1B007052 | E97: Klasifikasi Dokumen Teks Menggunakan Learning Vector Quantization | F97: Dr. Misbahuddin, S.T., M.T. | G97: I B K Widiartha, S.T., M.T. | H97: Heri Wijayanto, S.T., M.T. | I97: Budi Irmawati, S. Kom., M.T. | J97: Giri Wahyu Wiriasto, S.T., M.T. | K97: Sabtu | L97: 40817 | M97: 08.00-10.00 | N97: R. D2 | P97: 834 | Q97: 7 | R97: 27 | S97: 32 | T97: 20 | U97: 41 | W97: =TEXT(L97,"dd mmmm yyyy") -> 01 Oktober 2011 | X97: =IFERROR(VLOOKUP(D97,'[5]mhs elektro-kecil'!$B$5:$E$2151,3,0),"CEK") -> CEK | Y97: =IFERROR(VLOOKUP(D97,'[5]mhs elektro-kecil'!$B$5:$E$2151,4,0),"CEK") -> CEK | Z97: =L97 -> 40817 | AA97: =Z97+180 -> 40997 | AD97: =IF(F97=H97,"bentrok",IF(F97=I97,"bentrok",IF(F97=J97,"bentrok","ok"))) -> ok | AE97: =IF(G97=I97,"bentrok",IF(G97=J97,"bentrok",IF(G97=H97,"bentrok","ok"))) -> ok | AF97: =IF(H97=I97,"bentrok",IF(H97=J97,"bentrok",IF(H97=F97,"bentrok",IF(H97=G97,"bentrok","ok")))) -> ok | AG97: =IF(I97=J97,"bentrok",IF(I97=F97,"bentrok",IF(I97=G97,"bentrok",IF(I97=H97,"bentrok","ok")))) -> ok | AH97: =IF(J97=F97,"bentrok",IF(J97=G97,"bentrok",IF(J97=H97,"bentrok",IF(J97=I97,"bentrok","ok")))) -> ok | AI97: =MID(D97,5,2) -> 07 | AL97: =IF(MID(D97,5,2)="06",2006,IF(MID(D97,5,2)="07",2007,IF(MID(D97,5,2)="08",2008,IF(MID(D97,5,2)="09",2009,IF(MID(D97,5,2)="10",2010,IF(MID(D97,5,2)="11",2011,IF(MID(D97,5,2)="12",2012,IF(MID(D97,5,2)="05",2005,IF(MID(D97,5,2)="04",2004,IF(MID(D97,5,2)="03",2003,IF(MID(D97,5,2)="13",2013,IF(MID(D97,5,2)="14",2014,IF(MID(D97,5,2)="15",2015,IF(MID(D97,5,2)="16",2016,IF(MID(D97,5,2)="17",2017,IF(MID(D97,5,2)="18",2018,2019)))))))))))))))) -> 2007 | AM97: =COUNTIF([6]Daftar!$D$5:$D$851,D97) -> #VALUE! | AN97: =COUNTIF([7]daftar!$D$4:$D$885,D97) -> #VALUE! | AS97: =C97 -> Mizar Febrian | AT97: =D97 -> F1B007052 | AU97: =A97 -> 94
A98: =A97+1 -> 95 | B98: 40812 | C98: =VLOOKUP(D98,'[4]mhs elektro-kecil'!$B$5:$C$1847,2,0) -> Akhiruddin | D98: F1B004006 | E98: Perancangan Antenna Helix 4 Lilitan Hubung Array 2,4 GHz pada Mode Axial untuk Aplikasi wireless LAN | F98: Abdullah Zainuddin, S.T., M.T. | G98: I Made Budi Suksmadana, S.T., M.T. | H98: Made Sutha Yadnya, S.T., M.T. | I98: Bulkis Kanata, S.T., M.T. | J98: Syafarudin Ch, S.T., M.T. | K98: Sabtu | L98: 40817 | M98: 08.00-10.00 | N98: R. Studio | O98: Lulus | P98: 833 | Q98: 15 | R98: 24 | S98: 19 | T98: 21 | U98: 4 | W98: =TEXT(L98,"dd mmmm yyyy") -> 01 Oktober 2011 | X98: =IFERROR(VLOOKUP(D98,'[5]mhs elektro-kecil'!$B$5:$E$2151,3,0),"CEK") -> CEK | Y98: =IFERROR(VLOOKUP(D98,'[5]mhs elektro-kecil'!$B$5:$E$2151,4,0),"CEK") -> CEK | Z98: =L98 -> 40817 | AA98: =Z98+180 -> 40997 | AD98: =IF(F98=H98,"bentrok",IF(F98=I98,"bentrok",IF(F98=J98,"bentrok","ok"))) -> ok | AE98: =IF(G98=I98,"bentrok",IF(G98=J98,"bentrok",IF(G98=H98,"bentrok","ok"))) -> ok | AF98: =IF(H98=I98,"bentrok",IF(H98=J98,"bentrok",IF(H98=F98,"bentrok",IF(H98=G98,"bentrok","ok")))) -> ok | AG98: =IF(I98=J98,"bentrok",IF(I98=F98,"bentrok",IF(I98=G98,"bentrok",IF(I98=H98,"bentrok","ok")))) -> ok | AH98: =IF(J98=F98,"bentrok",IF(J98=G98,"bentrok",IF(J98=H98,"bentrok",IF(J98=I98,"bentrok","ok")))) -> ok | AI98: =MID(D98,5,2) -> 04 | AL98: =IF(MID(D98,5,2)="06",2006,IF(MID(D98,5,2)="07",2007,IF(MID(D98,5,2)="08",2008,IF(MID(D98,5,2)="09",2009,IF(MID(D98,5,2)="10",2010,IF(MID(D98,5,2)="11",2011,IF(MID(D98,5,2)="12",2012,IF(MID(D98,5,2)="05",2005,IF(MID(D98,5,2)="04",2004,IF(MID(D98,5,2)="03",2003,IF(MID(D98,5,2)="13",2013,IF(MID(D98,5,2)="14",2014,IF(MID(D98,5,2)="15",2015,IF(MID(D98,5,2)="16",2016,IF(MID(D98,5,2)="17",2017,IF(MID(D98,5,2)="18",2018,2019)))))))))))))))) -> 2004 | AM98: =COUNTIF([6]Daftar!$D$5:$D$851,D98) -> #VALUE! | AN98: =COUNTIF([7]daftar!$D$4:$D$885,D98) -> #VALUE! | AS98: =C98 -> Akhiruddin | AT98: =D98 -> F1B004006 | AU98: =A98 -> 95
A99: =A98+1 -> 96 | B99: 40836 | C99: =VLOOKUP(D99,'[4]mhs elektro-kecil'!$B$5:$C$1847,2,0) -> Annas Rahma Fath | D99: F1B007009 | E99: Desain Konten Pelajaran Fisika SMU "Hukum Mekanika II : Momentum" dengan Menggunakan 3D Game Studio | F99: Dr. Rismon H. Sianipar, S.T., M.Eng. | G99: I Ketut Wiryajati, S.T., M.T. | H99: I B K Widiartha, S.T., M.T. | I99: Ir. Sri Endang Anjarwani, M.Kom. | J99: Dr.rer.nat. Teti Zubaidah, S.T., M.T. | K99: Selasa | L99: 40841 | M99: 08.00-10.00 | N99: Lab. Komputer | O99: Lulus | P99: 912 | Q99: 33 | R99: 3 | S99: 27 | T99: 38 | U99: 22 | W99: =TEXT(L99,"dd mmmm yyyy") -> 25 Oktober 2011 | X99: =IFERROR(VLOOKUP(D99,'[5]mhs elektro-kecil'!$B$5:$E$2151,3,0),"CEK") -> CEK | Y99: =IFERROR(VLOOKUP(D99,'[5]mhs elektro-kecil'!$B$5:$E$2151,4,0),"CEK") -> CEK | Z99: =L99 -> 40841 | AA99: =Z99+180 -> 41021 | AD99: =IF(F99=H99,"bentrok",IF(F99=I99,"bentrok",IF(F99=J99,"bentrok","ok"))) -> ok | AE99: =IF(G99=I99,"bentrok",IF(G99=J99,"bentrok",IF(G99=H99,"bentrok","ok"))) -> ok | AF99: =IF(H99=I99,"bentrok",IF(H99=J99,"bentrok",IF(H99=F99,"bentrok",IF(H99=G99,"bentrok","ok")))) -> ok | AG99: =IF(I99=J99,"bentrok",IF(I99=F99,"bentrok",IF(I99=G99,"bentrok",IF(I99=H99,"bentrok","ok")))) -> ok | AH99: =IF(J99=F99,"bentrok",IF(J99=G99,"bentrok",IF(J99=H99,"bentrok",IF(J99=I99,"bentrok","ok")))) -> ok | AI99: =MID(D99,5,2) -> 07 | AL99: =IF(MID(D99,5,2)="06",2006,IF(MID(D99,5,2)="07",2007,IF(MID(D99,5,2)="08",2008,IF(MID(D99,5,2)="09",2009,IF(MID(D99,5,2)="10",2010,IF(MID(D99,5,2)="11",2011,IF(MID(D99,5,2)="12",2012,IF(MID(D99,5,2)="05",2005,IF(MID(D99,5,2)="04",2004,IF(MID(D99,5,2)="03",2003,IF(MID(D99,5,2)="13",2013,IF(MID(D99,5,2)="14",2014,IF(MID(D99,5,2)="15",2015,IF(MID(D99,5,2)="16",2016,IF(MID(D99,5,2)="17",2017,IF(MID(D99,5,2)="18",2018,2019)))))))))))))))) -> 2007 | AM99: =COUNTIF([6]Daftar!$D$5:$D$851,D99) -> #VALUE! | AN99: =COUNTIF([7]daftar!$D$4:$D$885,D99) -> #VALUE! | AS99: =C99 -> Annas Rahma Fath | AT99: =D99 -> F1B007009 | AU99: =A99 -> 96
A100: =A99+1 -> 97 | B100: 40836 | C100: =VLOOKUP(D100,'[4]mhs elektro-kecil'!$B$5:$C$1847,2,0) -> Nawir One Taufik | D100: F1B007060 | E100: Desain Konten Pelajaran Fisika SMU "Hukum Mekanika I"dengan Menggunakan 3D Game Studio | F100: Dr. Rismon H. Sianipar, S.T., M.Eng. | G100: I Ketut Wiryajati, S.T., M.T. | H100: Budi Irmawati, S. Kom., M.T. | I100: I B K Widiartha, S.T., M.T. | J100: Made Sutha Yadnya, S.T., M.T. | K100: Rabu | L100: 40842 | M100: 08.00-10.00 | N100: Lab. Komputer | O100: Lulus | P100: 913 | Q100: 33 | R100: 3 | S100: 20 | T100: 27 | U100: 19 | W100: =TEXT(L100,"dd mmmm yyyy") -> 26 Oktober 2011 | X100: =IFERROR(VLOOKUP(D100,'[5]mhs elektro-kecil'!$B$5:$E$2151,3,0),"CEK") -> CEK | Y100: =IFERROR(VLOOKUP(D100,'[5]mhs elektro-kecil'!$B$5:$E$2151,4,0),"CEK") -> CEK | Z100: =L100 -> 40842 | AA100: =Z100+180 -> 41022 | AD100: =IF(F100=H100,"bentrok",IF(F100=I100,"bentrok",IF(F100=J100,"bentrok","ok"))) -> ok | AE100: =IF(G100=I100,"bentrok",IF(G100=J100,"bentrok",IF(G100=H100,"bentrok","ok"))) -> ok | AF100: =IF(H100=I100,"bentrok",IF(H100=J100,"bentrok",IF(H100=F100,"bentrok",IF(H100=G100,"bentrok","ok")))) -> ok | AG100: =IF(I100=J100,"bentrok",IF(I100=F100,"bentrok",IF(I100=G100,"bentrok",IF(I100=H100,"bentrok","ok")))) -> ok | AH100: =IF(J100=F100,"bentrok",IF(J100=G100,"bentrok",IF(J100=H100,"bentrok",IF(J100=I100,"bentrok","ok")))) -> ok | AI100: =MID(D100,5,2) -> 07 | AL100: =IF(MID(D100,5,2)="06",2006,IF(MID(D100,5,2)="07",2007,IF(MID(D100,5,2)="08",2008,IF(MID(D100,5,2)="09",2009,IF(MID(D100,5,2)="10",2010,IF(MID(D100,5,2)="11",2011,IF(MID(D100,5,2)="12",2012,IF(MID(D100,5,2)="05",2005,IF(MID(D100,5,2)="04",2004,IF(MID(D100,5,2)="03",2003,IF(MID(D100,5,2)="13",2013,IF(MID(D100,5,2)="14",2014,IF(MID(D100,5,2)="15",2015,IF(MID(D100,5,2)="16",2016,IF(MID(D100,5,2)="17",2017,IF(MID(D100,5,2)="18",2018,2019)))))))))))))))) -> 2007 | AM100: =COUNTIF([6]Daftar!$D$5:$D$851,D100) -> #VALUE! | AN100: =COUNTIF([7]daftar!$D$4:$D$885,D100) -> #VALUE! | AS100: =C100 -> Nawir One Taufik | AT100: =D100 -> F1B007060 | AU100: =A100 -> 97
A101: =A100+1 -> 98 | B101: 40847 | C101: =VLOOKUP(D101,'[4]mhs elektro-kecil'!$B$5:$C$1847,2,0) -> Dwi Pandu Santoso | D101: F1B007017 | E101: Penentun Karakteristik Panel Surya untuk Menghasilkan Daya Maksimum dengan Berbagai Hubungan Rangkaian di Laboratorium Energi Terbarukan Universitas Mataram | F101: Abdul Natsir, S.T., M.T. | G101: Paniran, S.T., M.T. | H101: Ida Bagus Fery Citarsa, S.T., M.T. | I101: Ni Made Seniari, S.T., M.T. | J101: Sultan, S.T., M.T. | K101: Kamis | L101: 40850 | M101: 08.00-10.00 | N101: Lab. LD | P101: 933 | Q101: 14 | R101: 28 | S101: 12 | T101: 1 | U101: 5 | W101: =TEXT(L101,"dd mmmm yyyy") -> 03 November 2011 | X101: =IFERROR(VLOOKUP(D101,'[5]mhs elektro-kecil'!$B$5:$E$2151,3,0),"CEK") -> CEK | Y101: =IFERROR(VLOOKUP(D101,'[5]mhs elektro-kecil'!$B$5:$E$2151,4,0),"CEK") -> CEK | Z101: =L101 -> 40850 | AA101: =Z101+180 -> 41030 | AD101: =IF(F101=H101,"bentrok",IF(F101=I101,"bentrok",IF(F101=J101,"bentrok","ok"))) -> ok | AE101: =IF(G101=I101,"bentrok",IF(G101=J101,"bentrok",IF(G101=H101,"bentrok","ok"))) -> ok | AF101: =IF(H101=I101,"bentrok",IF(H101=J101,"bentrok",IF(H101=F101,"bentrok",IF(H101=G101,"bentrok","ok")))) -> ok | AG101: =IF(I101=J101,"bentrok",IF(I101=F101,"bentrok",IF(I101=G101,"bentrok",IF(I101=H101,"bentrok","ok")))) -> ok | AH101: =IF(J101=F101,"bentrok",IF(J101=G101,"bentrok",IF(J101=H101,"bentrok",IF(J101=I101,"bentrok","ok")))) -> ok | AI101: =MID(D101,5,2) -> 07 | AL101: =IF(MID(D101,5,2)="06",2006,IF(MID(D101,5,2)="07",2007,IF(MID(D101,5,2)="08",2008,IF(MID(D101,5,2)="09",2009,IF(MID(D101,5,2)="10",2010,IF(MID(D101,5,2)="11",2011,IF(MID(D101,5,2)="12",2012,IF(MID(D101,5,2)="05",2005,IF(MID(D101,5,2)="04",2004,IF(MID(D101,5,2)="03",2003,IF(MID(D101,5,2)="13",2013,IF(MID(D101,5,2)="14",2014,IF(MID(D101,5,2)="15",2015,IF(MID(D101,5,2)="16",2016,IF(MID(D101,5,2)="17",2017,IF(MID(D101,5,2)="18",2018,2019)))))))))))))))) -> 2007 | AM101: =COUNTIF([6]Daftar!$D$5:$D$851,D101) -> #VALUE! | AN101: =COUNTIF([7]daftar!$D$4:$D$885,D101) -> #VALUE! | AS101: =C101 -> Dwi Pandu Santoso | AT101: =D101 -> F1B007017 | AU101: =A101 -> 98
...

Sheet u kon
A8: Nomor | B8: : | D8: /UN18.F6./TE/EP/2020 | J8: =VLOOKUP(N8,data,2,M80) -> 6 Juli 2020 | N8: 759
A9: Lamp. | B9: : | C9: 1 (satu) eksemplar
A10: H a l | B10: : | C10: Undangan Seminar Proposal Tugas Akhir
A13: Yth. Bapak/Ibu | D13: : | E13: ………………………………………………..
A14: Dosen Pembimbing & Penguji Seminar Proposal Tugas akhir
A15: Mataram
A18: Sesuai dengan permohonan mahasiswa atas nama :
A20: N a m a | D20: : | E20: =VLOOKUP($N$8,data,3,0) -> M. Rivaldi Harjian
A21: N I M | D21: : | E21: =VLOOKUP($N$8,data,4,0) -> F1B016055
A22: Judul Proposal TA | D22: : | E22: =VLOOKUP(N8,data,5,0) -> Analisis Keandalan Sistem Distribusi 20 KV Pada Gardu Induk Kuta PT. PLN Unit Layanan Pelanggan Praya Menggunakan Metode Section Technique Dan FMEA (Failure Model And Effect Analysis)
A25: Tentang permohonan Seminar Proposal Tugas Akhir, maka dengan ini ditugaskan sebagai Tim Penguji Seminar proposal Tugas Akhir sebagai berikut :
A28: 1 | C28: =VLOOKUP($N$8,data,6,0) -> Supriyatna, S.T., M.T. | I28: Pembimbing Utama
A29: 2 | C29: =VLOOKUP($N$8,data,7,0) -> Ir. Agung Budi Muljono, S.T., M.T., IPU. | I29: Pembimbing Pendamping
A30: 3 | C30: =VLOOKUP($N$8,data,8,0) -> Dr. rer. nat. Teti Zubaidah, S.T., M.T. | I30: Penguji 1
A31: 4 | C31: =VLOOKUP($N$8,data,9,0) -> Dr. Ir. I Made Ginarsa, S.T., M.T., IPU. | I31: Penguji 2
A32: 5 | C32: =VLOOKUP($N$8,data,10,0) -> Ir. I Made Ari Nrartha, S.T., M.T. | I32: Penguji 3
A34: Seminar Proposal Tugas Akhir akan dilaksanakan pada :
A36: Hari | B36: : | C36: =VLOOKUP($N$8,data,11,0) -> Rabu
A37: Tanggal | B37: : | C37: =VLOOKUP($N$8,data,12,0) -> 44020
A38: Waktu | B38: : | C38: =VLOOKUP($N$8,data,13,0) -> 13.30-15.00
A39: Tempat | B39: : | C39: =VLOOKUP($N$8,data,14,0) -> Secara online dengan aplikasi Zoom
A41: Demikian atas perhatian dan kerjasamanya disampaikan, terima kasih.
N43: Ketua,
H44: Sekretaris I,
R45: Sekretaris I,
N47: Sudi Mariyanto Al Sasongko, ST., MT.
H48: Dr. Misbahuddin, S.T., M.T. | N48: NIP. 19670526 199703 1 001
H49: NIP 196810051997031001 | N49: Sekretaris I, | R49: Syafaruddin Ch., ST., MT.
A50: Catatan : | R50: NIP. 19690612 199702 1 001
A51: - Jika bapak/ibu dosen Pembimbing dan Penguji berhalangan hadir, agar melapor ke Ketua/Sekretaris
A52: JTE paling lambat H-3 (baik lapor secara langsung atau melalui perwakilan/mahasiswa)
A53: - Jika Ketua Tim Penguji yang ditunjuk berhalangan/terlambat datang, maka Ketua Tim Penguji dapat | N53: Dr. Misbahuddin, S.T., M.T. | R53: Ketua,
A54: digantikan oleh penguji 2 dan 3, atau berdasarkan kesepakatan | N54: NIP 196810051997031001
R57: Muhamad Syamsu Iqbal, S.T., M.T., Ph.D.
R58: NIP 197202221999031002

Sheet u jadi
A7: Nomor | B7: : | C7: =VLOOKUP($N$7,data,16,0) -> 301 | D7: /UN18.F6./TE/EP/2025 | J7: =VLOOKUP(N7,data,2,0) -> 45849 | N7: 1348 | O7: 890
A8: Lamp. | B8: : | C8: 1 (satu) eksemplar | N8: 0
A9: H a l | B9: : | C9: Undangan Seminar Proposal Tugas Akhir
A12: Yth. Bapak/Ibu | D12: : | E12: ………………………………………………..
A13: Dosen Pembimbing & Penguji Seminar Proposal Tugas akhir
A14: Mataram
A17: Sesuai dengan permohonan mahasiswa atas nama :
A19: N a m a | D19: : | E19: =VLOOKUP($N$7,data,3,0) -> Maelani Fauziah
A20: N I M | D20: : | E20: =VLOOKUP($N$7,data,4,0) -> F1B021066
A21: Judul Proposal TA | D21: : | E21: =VLOOKUP(N7,data,5,0) -> Rancang Bangun Alat Pemilah Sampah Organik dan Anorganik Otomatis Berbasis ESP32
A24: Tentang permohonan Seminar Proposal Tugas Akhir, maka dengan ini ditugaskan sebagai Tim Penguji Seminar proposal Tugas Akhir sebagai berikut :
A27: 1 | C27: =VLOOKUP($N$7,data,6,0) -> Budi Darmawan, S.T., M.Eng. | I27: Pembimbing Utama
A28: 2 | C28: =VLOOKUP($N$7,data,7,0) -> Syafaruddin Ch, S.T., M.T. | I28: Pembimbing Pendamping
A29: 3 | C29: dr. Elly Rosila Wijaya., Sp.KJ,MM. | I29: Pembimbing Pendamping II
A30: 3 | C30: =VLOOKUP($N$7,data,8,0) -> I Made Budi Suksmadana, S.T., M.T. | I30: Penguji 1
A31: 4 | C31: =VLOOKUP($N$7,data,9,0) -> Paniran, S.T., M.T. | I31: Penguji 2
A32: 5 | C32: =VLOOKUP($N$7,data,10,0) -> Ir. I Made Ari Nrartha, S.T., M.T. | I32: Penguji 3
T33: Sekretaris I,
A34: Seminar Proposal Tugas Akhir akan dilaksanakan pada :
A36: Hari | B36: : | C36: =VLOOKUP($N$7,data,11,0) -> Rabu
A37: Tanggal | B37: : | C37: =VLOOKUP($N$7,data,12,0) -> 45854 | N37: Ketua, | T37: Syafaruddin Ch., ST., MT.
A38: Waktu | B38: : | C38: =VLOOKUP($N$7,data,13,0) -> 10.30-12.00 | T38: NIP. 19690612 199702 1 001
A39: Tempat | B39: : | C39: =VLOOKUP($N$7,data,14,0) -> Lab. Elka & Digital
A41: Demikian atas perhatian dan kerjasamanya disampaikan, terima kasih. | N41: Sudi Mariyanto Al Sasongko, ST., MT.
N42: NIP. 19670526 199703 1 001
H44: Ketua Jurusan,
H48: A. Sjamsjiar Rachman, S.T., M.T.
H49: NIP. 197111241999031004
A50: Catatan :
A51: - Jika bapak/ibu dosen Pembimbing dan Penguji berhalangan hadir, agar melapor ke Ketua/Sekretaris | S51: Ketua,
A52: JTE paling lambat H-3 (baik lapor secara langsung atau melalui perwakilan/mahasiswa)
A53: - Jika Ketua Tim Penguji yang ditunjuk berhalangan/terlambat datang, maka Ketua Tim Penguji dapat | O53: Sekretaris I,
A54: digantikan oleh penguji 2 dan 3, atau berdasarkan kesepakatan
A55: - Dimohon kepada dosen pembimbing untuk tidak menunjuk dosen penguji pengganti tanpa sepengetahuan | S55: Muhamad Syamsu Iqbal, S.T., M.T., Ph.D.
A56: Jurusan | S56: NIP 197202221999031002
O57: Dr. Misbahuddin, S.T., M.T.
O58: NIP 196810051997031001
O61: Ketua,
O65: Dr. Misbahuddin, S.T., M.T.
O66: NIP 196810051997031001

Sheet SURAT KET TA
A10: SURAT KETERANGAN
A11: Nomor : /UN18.F6/TE/EP/2019
A14: Ketua Jurusan Teknik Elektro Fakultas Teknik Universitas Mataram menerangkan dengan sebenarnya mahasiswa :
L15: NO. URUT | N15: DOSEN
A16: N a m a | D16: : | E16: =VLOOKUP(L16,data,3,0) -> HELMY AMALIA ARIESTA | L16: 812 | N16: =VLOOKUP(L16,data,17,0) -> 22
A17: N I M | D17: : | E17: =VLOOKUP(L16,data,4,0) -> F1B117017 | N17: =VLOOKUP(L16,data,18,0) -> 45
A18: Judul Tugas Akhir | D18: : | E18: =VLOOKUP(L16,data,5,0) -> Analisis Diferensiasi Big Data Geomagnetik Sebagai Prekursor Gempa Lombok Dengan GUI (Graphic User Interface) Matlab
A21: Pembimbing I | D21: : | E21: =VLOOKUP(N16,dosen,3,0) -> Dr. rer. nat. Teti Zubaidah, S.T., M.T.
A22: Pembimbing II | D22: : | E22: =VLOOKUP(N17,dosen,3,0) -> Dwi Ratnasari, S.Kom., MT.
A24: memang benar yang bersangkutan sedang dalam proses menyelesaikan Tugas Akhir (Skripsi) pada Jurusan Teknik Elektro Fakultas Teknik Universitas Mataram
A25: terhitung mulai tanggal | E25: =VLOOKUP(L16,data,24,0) -> Teknik Informatika & Komputer | H25: s/d | I25: =E25+180 -> #VALUE!
A27: Demikian keterangan ini dibuat agar yang berkepentingan maklum.
G31: Mataram, 10 April 2019
G32: Ketua,
G37: Muhamad Syamsu Iqbal, S.T., M.T., Ph.D.
G38: NIP 197202221999031002

Sheet SURAT KET TA Dekan
A10: SURAT KETERANGAN
A11: Nomor : /UN18.F6/EP/2021
A14: Dekan Fakultas Teknik Universitas Mataram menerangkan dengan sebenarnya bahwa mahasiswa :
L15: NO. URUT | N15: DOSEN
A16: N a m a | D16: : | E16: =VLOOKUP(L16,data,3,0) -> HELMY AMALIA ARIESTA | L16: 812 | N16: =VLOOKUP(L16,data,17,0) -> 22
A17: N I M | D17: : | E17: =VLOOKUP(L16,data,4,0) -> F1B117017 | N17: =VLOOKUP(L16,data,18,0) -> 45
A18: Judul Tugas Akhir | D18: : | E18: =VLOOKUP(L16,data,5,0) -> Analisis Diferensiasi Big Data Geomagnetik Sebagai Prekursor Gempa Lombok Dengan GUI (Graphic User Interface) Matlab
A21: Pembimbing I | D21: : | E21: =VLOOKUP(N16,dosen,3,0) -> Dr. rer. nat. Teti Zubaidah, S.T., M.T.
A22: Pembimbing II | D22: : | E22: =VLOOKUP(N17,dosen,3,0) -> Dwi Ratnasari, S.Kom., MT.
A24: memang benar yang bersangkutan sedang dalam proses penelitian guna penyelesaian Tugas Akhir (Skripsi)
A25: terhitung mulai tanggal | E25: =VLOOKUP(L16,data,24,0) -> Teknik Informatika & Komputer | H25: s/d | I25: =E25+180 -> #VALUE!
A27: Demikian surat keterangan ini dibuat agar yang berkepentingan maklum.
G31: Mataram, 8 Mei 2021
G32: Dekan,
G37: Akmaluddin, S.T., M.Sc.(Eng)., Ph.D.
G38: NIP 196812311994121001

Sheet u rev KON
A1: KEMENTERIAN RISET, TEKNOLOGI DAN PENDIDIKAN TINGGI
A2: FAKULTAS TEKNIK
A3: UNIVERSITAS MATARAM
A4: JURUSAN TEKNIK ELEKTRO
A5: Jalan Majapahit No. 62 Mataram 83125 Telepon (0370) 636126 Fax. (0370) 636523
A7: Nomor | B7: : | D7: /UN18.F6.2/JTE/EP/2017 | J7: =VLOOKUP(N7,data,2,0) -> 18 Januari 2019 | N7: 617
A8: Lamp. | B8: : | C8: 1 (satu) eksemplar
A9: H a l | B9: : | C9: REVISI Undangan Seminar Proposal Tugas Akhir
A12: Yth. Bapak/Ibu | D12: : | E12: ………………………………………………..
A13: Dosen Penguji Seminar Proposal Tugas akhir
A14: Mataram
A17: Sesuai dengan permohonan mahasiswa atas nama :
A19: N a m a | D19: : | E19: =VLOOKUP($N$7,data,3,0) -> Ahmad Marizki
A20: N I M | D20: : | E20: =VLOOKUP($N$7,data,4,0) -> F1B014003
A21: Judul Proposal TA | D21: : | E21: =VLOOKUP(N7,data,5,0) -> Rancang Bangun Aoutomatic Voltage Regulator Generator Sinkron 300 Watt Menggunakan Buck Converter
A24: Tentang permohonan Seminar Proposal Tugas Akhir, maka dengan ini ditugaskan sebagai Tim Penguji Seminar proposal Tugas Akhir sebagai berikut :
A27: 1 | C27: =VLOOKUP($N$7,data,6,0) -> I Made Ari Nrartha, S.T., M.T. | I27: Pembimbing Utama
A28: 2 | C28: =VLOOKUP($N$7,data,7,0) -> Dr. Warindi, S.T., M.Eng. | I28: Pembimbing Pendamping
A29: 3 | C29: =VLOOKUP($N$7,data,8,0) -> Abdul Natsir, S.T., M.T. | I29: Penguji 1
A30: 4 | C30: =VLOOKUP($N$7,data,9,0) -> Sabar Nababan, S.T., M.T. | I30: Penguji 2
A31: 5 | C31: =VLOOKUP($N$7,data,10,0) -> Supriyatna, S.T., M.T. | I31: Penguji 3
A33: Seminar Proposal Tugas Akhir akan dilaksanakan pada :
A35: Hari | B35: : | C35: =VLOOKUP($N$7,data,11,0) -> Kamis
A36: Tanggal | B36: : | C36: =VLOOKUP($N$7,data,12,0) -> 43489
A37: Waktu | B37: : | C37: =VLOOKUP($N$7,data,13,0) -> 08.00-09.40
A38: Tempat | B38: : | C38: =VLOOKUP($N$7,data,14,0) -> Lab. Sistem Tenaga
A40: Surat ini sekaligus merevisi undangan seminar Proposal tugas akhir nomor : 1293/UN18.F6.2/JTE/EP/2017 tertanggal 20 Desember 2017
A43: Demikian atas perhatian dan kerjasamanya disampaikan, terima kasih.
I46: Ketua,
I50: Dr. Misbahuddin, S.T., M.T.
I51: NIP 196810051997031001
A52: Catatan :
A53: - Jika bapak/ibu dosen Pembimbing dan Penguji berhalangan hadir, agar melapor ke Ketua/Sekretaris
A54: JTE paling lambat H-1 dan dilakukan pada jam kerja
A55: - Dimohon hadir tepat waktu.

Sheet u rev JADI
A7: Nomor | B7: : | C7: 81 | D7: /UN18.F6./TE/EP/2019 | J7: =VLOOKUP(N7,data,2,0) -> 15 Juli 2019 | N7: 653
A8: Lamp. | B8: : | C8: 1 (satu) eksemplar
A9: H a l | B9: : | C9: REVISI Undangan Seminar Proposal Tugas Akhir
A12: Yth. Bapak/Ibu | D12: : | E12: ………………………………………………..
A13: Dosen Penguji Seminar Proposal Tugas akhir
A14: Mataram
A17: Sesuai dengan permohonan mahasiswa atas nama :
A19: N a m a | D19: : | E19: =VLOOKUP($N$7,data,3,0) -> Pramono
A20: N I M | D20: : | E20: =VLOOKUP($N$7,data,4,0) -> F1B015074
A21: Judul Proposal TA | D21: : | E21: =VLOOKUP(N7,data,5,0) -> Penambahan Zat Adiktif Dapat Menurunkan Tahanan Pentahanan Menggunakan Metode Plat Di Kecamatan Bayan Lombok Utara
A24: Tentang permohonan Seminar Proposal Tugas Akhir, maka dengan ini ditugaskan sebagai Tim Penguji Seminar proposal Tugas Akhir sebagai berikut :
A27: 1 | C27: =VLOOKUP($N$7,data,6,0) -> Ni Made Seniari, S.T., M.T. | I27: Pembimbing Utama
A28: 2 | C28: =VLOOKUP($N$7,data,7,0) -> Dr. Ida Ayu Sri Adnyani, S.T., M.Erg. | I28: Pembimbing Pendamping
A29: 3 | C29: =VLOOKUP($N$7,data,8,0) -> Agung Budi Muljono, S.T., M.T. | I29: Penguji 1
A30: 4 | C30: =VLOOKUP($N$7,data,9,0) -> Sultan, S.T., M.T. | I30: Penguji 2
A31: 5 | C31: =VLOOKUP($N$7,data,10,0) -> Sabar Nababan, S.T., M.T. | I31: Penguji 3
A33: Seminar Proposal Tugas Akhir akan dilaksanakan pada :
A35: Hari | B35: : | C35: =VLOOKUP($N$7,data,11,0) -> Kamis
A36: Tanggal | B36: : | C36: =VLOOKUP($N$7,data,12,0) -> 43664
A37: Waktu | B37: : | C37: =VLOOKUP($N$7,data,13,0) -> 13.00-14.30
A38: Tempat | B38: : | C38: =VLOOKUP($N$7,data,14,0) -> Lab. Sistem Tenaga
A40: Surat ini sekaligus merevisi undangan seminar Proposal tugas akhir nomor : 69/UN18.F6.2/JTE/EP/2019 tertanggal 26 Januari 2019
A43: Demikian atas perhatian dan kerjasamanya disampaikan, terima kasih.
I46: Sekretaris I
I50: Dr. Misbahuddin, S.T., M.T.
I51: NIP 196810051997031001
A52: Catatan :
A53: - Jika bapak/ibu dosen Pembimbing dan Penguji berhalangan hadir, agar melapor ke Ketua/Sekretaris
A54: JTE paling lambat H-3 (baik lapor secara langsung atau melalui perwakilan/mahasiswa)
A55: - Jika Ketua Tim Penguji yang ditunjuk berhalangan/terlambat datang, maka Ketua Tim Penguji dapat
A56: digantikan oleh penguji 2 dan 3, atau berdasarkan kesepakatan
A57: - Dimohon kepada dosen pembimbing untuk tidak menunjuk dosen penguji pengganti tanpa sepengetahuan
A58: Jurusan

Sheet Alokasi Jadwal
A2: ALOKASI DOSEN PEMBIMBING DAN PENGUJI SEMINAR PROPOSAL MAHASISWA TAHUN 2025
A4: NO. | B4: TGL SURAT | C4: NAMA | D4: NIM | E4: JUDUL PROPOSAL TUGAS AKHIR | F4: PEMBIMBING 1 | G4: PEMBIMBING 2 | H4: PENGUJI 1 | I4: PENGUJI 2 | J4: PENGUJI 3 | K4: HARI | L4: TANGGAL | M4: WAKTU | N4: TEMPAT | P4: BIDANG KONSENTRASI | Q4: 1 | R4: 2 | S4: 3 | T4: 4 | U4: 5
A5: 1 | B5: 40282 | C5: =VLOOKUP(D5,'[11]mhs elektro-kecil'!$B$5:$C$993,2,0) -> Alpan Hadi | D5: F1B005005 | E5: Pengatur Posisi Ketinggian Tiang Mikrofof Otomatis Berbasis Mikrokontroler Seri AVR ATMega 8535 | F5: =VLOOKUP(Q5,dosen,3,0) -> Paniran, S.T., M.T. | G5: =VLOOKUP(R5,dosen,3,0) -> Syafaruddin Ch, S.T., M.T. | H5: =VLOOKUP(S5,dosen,3,0) -> Abdullah Zainuddin, S.T., M.T. | I5: =VLOOKUP(T5,dosen,3,0) -> Sudi M. Al Sasongko, S.T., M.T. | J5: =VLOOKUP(U5,dosen,3,0) -> Djul Fikry Budiman, S.T., M.T. | K5: Senin | L5: 40289 | M5: 10.00-12.00 | N5: D2 | Q5: 28 | R5: 4 | S5: 15 | T5: 6 | U5: 35
A6: =A5+1 -> 2 | B6: 40301 | C6: =VLOOKUP(D6,'[11]mhs elektro-kecil'!$B$5:$C$993,2,0) -> Thendriani Yastenti | D6: F1B006081 | E6: Mitigasi Gelombang Milimeter pada Kondisi Hujan Menggunakan Teknik Water Filling di Kota Mataram | F6: =VLOOKUP(Q6,dosen,3,0) -> Made Sutha Yadnya, S.T., M.T. | G6: =VLOOKUP(R6,dosen,3,0) -> Djul Fikry Budiman, S.T., M.T. | H6: =VLOOKUP(S6,dosen,3,0) -> Sudi M. Al Sasongko, S.T., M.T. | I6: =VLOOKUP(T6,dosen,3,0) -> Bulkis Kanata, S.T., M.T. | J6: =VLOOKUP(U6,dosen,3,0) -> Abdullah Zainuddin, S.T., M.T. | K6: Sabtu | L6: 40306 | M6: 08.00-10.00 | N6: R. D2 | Q6: 19 | R6: 35 | S6: 6 | T6: 21 | U6: 15
A7: =A6+1 -> 3 | B7: 40301 | C7: =VLOOKUP(D7,'[11]mhs elektro-kecil'!$B$5:$C$993,2,0) -> Muhammad Wahyudi | D7: F1B005053 | E7: Rancang Bangun Alat Pengendali Penerangan Ruangan Menggunakan Metode Fuzzy Logic Berbasis Mikrokontroler ATMEGA8535 | F7: =VLOOKUP(Q7,dosen,3,0) -> I Made Budi Suksmadana, S.T., M.T. | G7: =VLOOKUP(R7,dosen,3,0) -> Dr. Ir. Misbahuddin, S.T., M.T., IPU. | H7: =VLOOKUP(S7,dosen,3,0) -> Paniran, S.T., M.T. | I7: =VLOOKUP(T7,dosen,3,0) -> Sultan, S.T., M.T. | J7: =VLOOKUP(U7,dosen,3,0) -> Dr. Ir. I Ketut Wiryajati,ST.,MT.,IPU.,ASEAN.Eng. | K7: Sabtu | L7: 40306 | M7: 08.00-10.00 | N7: R. Studio | Q7: 24 | R7: 7 | S7: 28 | T7: 5 | U7: 3
A8: =A7+1 -> 4 | B8: 40305 | C8: =VLOOKUP(D8,'[11]mhs elektro-kecil'!$B$5:$C$993,2,0) -> Satriasyah Haris S. | D8: F1B003062 | E8: Analisa Kelayakan Implementasi Internet Protokol Television (IP-Tv) Berbasis Perangkat Lunak Open Source | F8: =VLOOKUP(Q8,dosen,3,0) -> Dr. Ir. Misbahuddin, S.T., M.T., IPU. | G8: =VLOOKUP(R8,dosen,3,0) -> Heri Wijayanto, S.T., M.T. | H8: =VLOOKUP(S8,dosen,3,0) -> Muhamad Syamsu Iqbal, S.T., M.T., Ph.D. | I8: =VLOOKUP(T8,dosen,3,0) -> I B K Widiartha, S.T., M.T. | J8: =VLOOKUP(U8,dosen,3,0) -> Muhamad Irwan, S.T., M.T. | K8: Sabtu | L8: 40306 | M8: 10.00-12.00 | N8: R. Studio | Q8: 7 | R8: 32 | S8: 18 | T8: 27 | U8: 39
A9: =A8+1 -> 5 | B9: 40308 | C9: =VLOOKUP(D9,'[11]mhs elektro-kecil'!$B$5:$C$993,2,0) -> Eddy Kurniawan | D9: F1B003014 | E9: Data Encryption Standard (DES) Cryptosystem Berfungsi sebagai Fungsi Hash untuk Menguji Integritas Sinyal Audio | F9: =VLOOKUP(Q9,dosen,3,0) -> Dr. Rismon H. Sianipar, S.T., M. Eng. | G9: =VLOOKUP(R9,dosen,3,0) -> Heri Wijayanto, S.T., M.T. | H9: =VLOOKUP(S9,dosen,3,0) -> I B K Widiartha, S.T., M.T. | I9: =VLOOKUP(T9,dosen,3,0) -> Muhamad Irwan, S.T., M.T. | J9: =VLOOKUP(U9,dosen,3,0) -> Budi Irmawati, S. Kom., M.T. | K9: Rabu | L9: 40310 | M9: 09.30-11.30 | N9: R. Lab. Komputer | O9: Tunda | Q9: 33 | R9: 32 | S9: 27 | T9: 39 | U9: 20
A10: =A9+1 -> 6 | B10: 40308 | C10: =VLOOKUP(D10,'[11]mhs elektro-kecil'!$B$5:$C$993,2,0) -> Salimyul Pathurrahman | D10: F1B006075 | E10: Penentuan Posisi Sensor Mitigasi Curah Hujan untuk Komunikasi LMDS dengan Metode SST (Synthetic Storm Technique) di Mataram | F10: =VLOOKUP(Q10,dosen,3,0) -> Made Sutha Yadnya, S.T., M.T. | G10: =VLOOKUP(R10,dosen,3,0) -> Djul Fikry Budiman, S.T., M.T. | H10: =VLOOKUP(S10,dosen,3,0) -> Sudi M. Al Sasongko, S.T., M.T. | I10: =VLOOKUP(T10,dosen,3,0) -> Muhamad Syamsu Iqbal, S.T., M.T., Ph.D. | J10: =VLOOKUP(U10,dosen,3,0) -> Bulkis Kanata, S.T., M.T. | K10: Sabtu | L10: 40313 | M10: 10.00-12.00 | N10: R. Lab. Elka & Digital | Q10: 19 | R10: 35 | S10: 6 | T10: 18 | U10: 21
A11: =A10+1 -> 7 | B11: 40329 | C11: =VLOOKUP(D11,'[11]mhs elektro-kecil'!$B$5:$C$993,2,0) -> Isnu Handibrata Eko Putra | D11: F1B006042 | E11: Analisis Stabilitas Transien pada Sistem Tenaga Listrik Pulau Lombok Menggunakan Kriteria Luas Sama dan Jaringan Syaraf Tiruan | F11: =VLOOKUP(Q11,dosen,3,0) -> Abdul Natsir, S.T., M.T. | G11: =VLOOKUP(R11,dosen,3,0) -> Ir. I Made Ari Nrartha, S.T., M.T. | H11: =VLOOKUP(S11,dosen,3,0) -> Dr. Ir. Rosmaliati, S.T., M.T. | I11: =VLOOKUP(T11,dosen,3,0) -> I Ketut Perdana Putra, S.T., M.T. | J11: =VLOOKUP(U11,dosen,3,0) -> Supriono, S.T., M.T. | K11: Sabtu | L11: 40334 | M11: 08.00-10.00 | N11: R. D2 | Q11: 14 | R11: 25 | S11: 16 | T11: 23 | U11: 29
A12: =A11+1 -> 8 | B12: 40329 | C12: =VLOOKUP(D12,'[11]mhs elektro-kecil'!$B$5:$C$993,2,0) -> Eddy Kurniawan | D12: F1B003014 | E12: Data Encryption Standard (DES) Cryptosystem Berfungsi sebagai Fungsi Hash untuk Menguji Integritas Sinyal Audio | F12: =VLOOKUP(Q12,dosen,3,0) -> Dr. Rismon H. Sianipar, S.T., M. Eng. | G12: =VLOOKUP(R12,dosen,3,0) -> Heri Wijayanto, S.T., M.T. | H12: =VLOOKUP(S12,dosen,3,0) -> I B K Widiartha, S.T., M.T. | I12: =VLOOKUP(T12,dosen,3,0) -> Muhamad Irwan, S.T., M.T. | J12: =VLOOKUP(U12,dosen,3,0) -> Budi Irmawati, S. Kom., M.T. | K12: Sabtu | L12: 40334 | M12: 08.00-10.00 | N12: R. Studio | Q12: 33 | R12: 32 | S12: 27 | T12: 39 | U12: 20
A13: =A12+1 -> 9 | B13: 40329 | C13: =VLOOKUP(D13,'[11]mhs elektro-kecil'!$B$5:$C$993,2,0) -> Agus Nugroho | D13: F1B002003 | E13: Rancang Bangun Pembangkit Listrik Tenaga Angin (PLTB) dengan Menggunakan Turbin Savonius | F13: =VLOOKUP(Q13,dosen,3,0) -> Sabar Nababan, S.T., M.T. | G13: =VLOOKUP(R13,dosen,3,0) -> Ir. Agung Budi Muljono, S.T., M.T., IPU. | H13: =VLOOKUP(S13,dosen,3,0) -> Ni Made Seniari, S.T., M.T. | I13: =VLOOKUP(T13,dosen,3,0) -> Supriyatna, S.T., M.T. | J13: =VLOOKUP(U13,dosen,3,0) -> I Ketut Perdana Putra, S.T., M.T. | K13: Sabtu | L13: 40334 | M13: 10.00-12.00 | N13: R. D2 | Q13: 31 | R13: 13 | S13: 1 | T13: 2 | U13: 23
A14: =A13+1 -> 10 | B14: 40329 | C14: =VLOOKUP(D14,'[11]mhs elektro-kecil'!$B$5:$C$993,2,0) -> Parlinawati | D14: F1B005059 | E14: Simulasi dan Analisis Perbandingan Kinerja Sistem OFCDM Berbasis Wavelet terhadap Sistem OFCDM Berbasis FFT | F14: =VLOOKUP(Q14,dosen,3,0) -> Sudi M. Al Sasongko, S.T., M.T. | G14: =VLOOKUP(R14,dosen,3,0) -> I Made Budi Suksmadana, S.T., M.T. | H14: =VLOOKUP(S14,dosen,3,0) -> Abdullah Zainuddin, S.T., M.T. | I14: =VLOOKUP(T14,dosen,3,0) -> Made Sutha Yadnya, S.T., M.T. | J14: =VLOOKUP(U14,dosen,3,0) -> Muhamad Syamsu Iqbal, S.T., M.T., Ph.D. | K14: Sabtu | L14: 40334 | M14: 10.00-12.00 | N14: R. Studio | Q14: 6 | R14: 24 | S14: 15 | T14: 19 | U14: 18
A15: =A14+1 -> 11 | B15: 40329 | C15: =VLOOKUP(D15,'[11]mhs elektro-kecil'!$B$5:$C$993,2,0) -> Eddy Kurniawan | D15: F1B003014 | E15: Data Encryption Standard (DES) Cryptosystem Berfungsi sebagai Fungsi Hash untuk Menguji Integritas Sinyal Audio | F15: =VLOOKUP(Q15,dosen,3,0) -> Dr. Rismon H. Sianipar, S.T., M. Eng. | G15: =VLOOKUP(R15,dosen,3,0) -> Heri Wijayanto, S.T., M.T. | H15: =VLOOKUP(S15,dosen,3,0) -> I B K Widiartha, S.T., M.T. | I15: =VLOOKUP(T15,dosen,3,0) -> Muhamad Irwan, S.T., M.T. | J15: =VLOOKUP(U15,dosen,3,0) -> Budi Irmawati, S. Kom., M.T. | K15: Rabu | L15: 40338 | M15: 10.00-12.00 | N15: R. WLTI | Q15: 33 | R15: 32 | S15: 27 | T15: 39 | U15: 20
A16: 1 | B16: 40338 | C16: =VLOOKUP(D16,'[11]mhs elektro-kecil'!$B$5:$C$993,2,0) -> I Gusti Ayu Ita Kusmira | D16: F1B006034 | E16: Economi Dispatch Menggunakan Algoritma Genetika (Studi Kasus : Sistem Kelistrikan Lombok) | F16: =VLOOKUP(Q16,dosen,3,0) -> Ir. Agung Budi Muljono, S.T., M.T., IPU. | G16: =VLOOKUP(R16,dosen,3,0) -> Ir. I Made Ari Nrartha, S.T., M.T. | H16: =VLOOKUP(S16,dosen,3,0) -> Dr. rer. nat. Teti Zubaidah, S.T., M.T. | I16: =VLOOKUP(T16,dosen,3,0) -> Ida Bagus Fery Citarsa, S.T., M.T. | J16: =VLOOKUP(U16,dosen,3,0) -> Supriyatna, S.T., M.T. | K16: Sabtu | L16: 40341 | M16: 08.00-10.00 | N16: R. D2 | Q16: 13 | R16: 25 | S16: 22 | T16: 12 | U16: 2
A17: =A16+1 -> 2 | B17: 40338 | C17: =VLOOKUP(D17,'[11]mhs elektro-kecil'!$B$5:$C$993,2,0) -> Dedek Hudayana | D17: F1B005011 | E17: Alat Pengontrol dan Pemonitor Lingkungan Rumah Kaca pada Tanaman Kamboja Jepang di Dinas Pertanian Narmada Berbasiskan Mikrokontroler ATMEGA8535 | F17: =VLOOKUP(Q17,dosen,3,0) -> Paniran, S.T., M.T. | G17: =VLOOKUP(R17,dosen,3,0) -> Supriono, S.T., M.T. | H17: =VLOOKUP(S17,dosen,3,0) -> Dr. Ir. I Ketut Wiryajati,ST.,MT.,IPU.,ASEAN.Eng. | I17: =VLOOKUP(T17,dosen,3,0) -> #N/A | J17: =VLOOKUP(U17,dosen,3,0) -> Lalu A. Syamsul Irfan A., S.T., M.Eng. | K17: Sabtu | L17: 40341 | M17: 08.00-10.00 | N17: R. Studio | Q17: 28 | R17: 29 | S17: 3 | T17: 11 | U17: 40
A18: 1 | B18: 40357 | C18: =VLOOKUP(D18,'[11]mhs elektro-kecil'!$B$5:$C$993,2,0) -> Kamarudin | D18: F1B005033 | E18: Perancangan Sistem Pengaman Sepeda Motor Menggunakan Telepon Seluler (Handphone) Berbasis Mikrokontroller ATMEGA 8535 | F18: =VLOOKUP(Q18,dosen,3,0) -> Supriono, S.T., M.T. | G18: =VLOOKUP(R18,dosen,3,0) -> I Made Budi Suksmadana, S.T., M.T. | H18: =VLOOKUP(S18,dosen,3,0) -> Syafaruddin Ch, S.T., M.T. | I18: =VLOOKUP(T18,dosen,3,0) -> Sabar Nababan, S.T., M.T. | J18: =VLOOKUP(U18,dosen,3,0) -> Lalu A. Syamsul Irfan A., S.T., M.Eng. | K18: Kamis | L18: 40360 | M18: 08.00-10.00 | N18: R. Studio | Q18: 29 | R18: 24 | S18: 4 | T18: 31 | U18: 40
A19: 1 | B19: 40403 | C19: =VLOOKUP(D19,'[11]mhs elektro-kecil'!$B$5:$C$993,2,0) -> I Gde Aditya P S | D19: F1B004032 | E19: Sistem Proteksi Keamanan Ruangan dan Pengendali Lampu Berbasis SMS | F19: =VLOOKUP(Q19,dosen,3,0) -> Supriono, S.T., M.T. | G19: =VLOOKUP(R19,dosen,3,0) -> I Made Budi Suksmadana, S.T., M.T. | H19: =VLOOKUP(S19,dosen,3,0) -> Dr. Ir. I Ketut Wiryajati,ST.,MT.,IPU.,ASEAN.Eng. | I19: =VLOOKUP(T19,dosen,3,0) -> Syafaruddin Ch, S.T., M.T. | J19: =VLOOKUP(U19,dosen,3,0) -> Lalu A. Syamsul Irfan A., S.T., M.Eng. | K19: Rabu | L19: 40408 | M19: 10.00-12.00 | N19: R. Studio | Q19: 29 | R19: 24 | S19: 3 | T19: 4 | U19: 40
A20: =A19+1 -> 2 | B20: 40403 | C20: =VLOOKUP(D20,'[11]mhs elektro-kecil'!$B$5:$C$993,2,0) -> Edi Waskita Putra | D20: F1B003015 | E20: Rancang Bangun Sistem Absensi Mengajar Dosen dengan SMS Gateway | F20: =VLOOKUP(Q20,dosen,3,0) -> Dr. Ir. Misbahuddin, S.T., M.T., IPU. | G20: =VLOOKUP(R20,dosen,3,0) -> Heri Wijayanto, S.T., M.T. | H20: =VLOOKUP(S20,dosen,3,0) -> Budi Irmawati, S. Kom., M.T. | I20: =VLOOKUP(T20,dosen,3,0) -> I B K Widiartha, S.T., M.T. | J20: =VLOOKUP(U20,dosen,3,0) -> Ir. Sri Endang Anjarwani, M. Kom. | K20: Rabu | L20: 40408 | M20: 08.00-10.00 | N20: R. D2 | Q20: 7 | R20: 32 | S20: 20 | T20: 27 | U20: 38
A21: =A20+1 -> 3 | B21: 40410 | C21: =VLOOKUP(D21,'[11]mhs elektro-kecil'!$B$5:$C$993,2,0) -> Donny Adithia | D21: F1B005013 | E21: Rancang Bangun prototipe Pembangkit Listrik Gelombang Laut dengan Sistem Rakit | F21: =VLOOKUP(Q21,dosen,3,0) -> Syafaruddin Ch, S.T., M.T. | G21: =VLOOKUP(R21,dosen,3,0) -> Abdul Natsir, S.T., M.T. | H21: =VLOOKUP(S21,dosen,3,0) -> Ni Made Seniari, S.T., M.T. | I21: =VLOOKUP(T21,dosen,3,0) -> Ida Bagus Fery Citarsa, S.T., M.T. | J21: =VLOOKUP(U21,dosen,3,0) -> Dr. Ir. Rosmaliati, S.T., M.T. | K21: Selasa | L21: 40414 | M21: 08.00-10.00 | N21: R. Studio | Q21: 4 | R21: 14 | S21: 1 | T21: 12 | U21: 16
A22: =A21+1 -> 4 | B22: 40450 | C22: =VLOOKUP(D22,'[11]mhs elektro-kecil'!$B$5:$C$993,2,0) -> Supandi | D22: F1B005071 | E22: Economic Dispatch Menggunakan Algoritma Partikel Swarm Optimization | F22: =VLOOKUP(Q22,dosen,3,0) -> Ir. I Made Ari Nrartha, S.T., M.T. | G22: =VLOOKUP(R22,dosen,3,0) -> Sultan, S.T., M.T. | H22: =VLOOKUP(S22,dosen,3,0) -> Supriyatna, S.T., M.T. | I22: =VLOOKUP(T22,dosen,3,0) -> Ir. Agung Budi Muljono, S.T., M.T., IPU. | J22: =VLOOKUP(U22,dosen,3,0) -> Sabar Nababan, S.T., M.T. | K22: Sabtu | L22: 40453 | M22: 08.00-10.00 | N22: R. Studio | Q22: 25 | R22: 5 | S22: 2 | T22: 13 | U22: 31
A23: 1 | B23: 40454 | C23: =VLOOKUP(D23,'[11]mhs elektro-kecil'!$B$5:$C$993,2,0) -> Prasetyadiguna | D23: F1B004063 | E23: Design Realisasi Power Splitter Mikrostrip pada Pemancar TV Kampus dengan Model Eksponensial Menggunakan HFSS | F23: =VLOOKUP(Q23,dosen,3,0) -> Sudi M. Al Sasongko, S.T., M.T. | G23: =VLOOKUP(R23,dosen,3,0) -> Abdullah Zainuddin, S.T., M.T. | H23: =VLOOKUP(S23,dosen,3,0) -> Djul Fikry Budiman, S.T., M.T. | I23: =VLOOKUP(T23,dosen,3,0) -> Muhamad Syamsu Iqbal, S.T., M.T., Ph.D. | J23: =VLOOKUP(U23,dosen,3,0) -> Bulkis Kanata, S.T., M.T. | K23: Rabu | L23: 40457 | M23: 09.30-11.30 | N23: Lab. Telkom | Q23: 6 | R23: 15 | S23: 35 | T23: 18 | U23: 21
A24: 1 | B24: 40454 | C24: =VLOOKUP(D24,'[11]mhs elektro-kecil'!$B$5:$C$993,2,0) -> Amir Hasanudin Fauzi | D24: F1B006008 | E24: Pattern Matching Method Based On Aho-Corasick Algorithm to Detect Malicious Code | F24: =VLOOKUP(Q24,dosen,3,0) -> Dr. Rismon H. Sianipar, S.T., M. Eng. | G24: =VLOOKUP(R24,dosen,3,0) -> Heri Wijayanto, S.T., M.T. | H24: =VLOOKUP(S24,dosen,3,0) -> Budi Irmawati, S. Kom., M.T. | I24: =VLOOKUP(T24,dosen,3,0) -> I B K Widiartha, S.T., M.T. | J24: =VLOOKUP(U24,dosen,3,0) -> Muhamad Irwan, S.T., M.T. | K24: Rabu | L24: 40457 | M24: 07.30-09.30 | N24: Lab. Komputer | Q24: 33 | R24: 32 | S24: 20 | T24: 27 | U24: 39
A25: =A24+1 -> 2 | B25: 40483 | C25: =VLOOKUP(D25,'[11]mhs elektro-kecil'!$B$5:$C$993,2,0) -> Siswadi | D25: F1B005067 | E25: Prototype Pengendalian System Buka Tutup Gerbang dan Berpengunci Otomatis Menggunakan Mikrokontroller ATMEGA 8535 | F25: =VLOOKUP(Q25,dosen,3,0) -> Paniran, S.T., M.T. | G25: =VLOOKUP(R25,dosen,3,0) -> Supriono, S.T., M.T. | H25: =VLOOKUP(S25,dosen,3,0) -> Syafaruddin Ch, S.T., M.T. | I25: =VLOOKUP(T25,dosen,3,0) -> I Made Budi Suksmadana, S.T., M.T. | J25: =VLOOKUP(U25,dosen,3,0) -> Ida Bagus Fery Citarsa, S.T., M.T. | K25: Kamis | L25: 40486 | M25: 08.00-10.00 | N25: R. D2 | Q25: 28 | R25: 29 | S25: 4 | T25: 24 | U25: 12
A26: =A25+1 -> 3 | B26: 40483 | C26: =VLOOKUP(D26,'[11]mhs elektro-kecil'!$B$5:$C$993,2,0) -> Fetty Nursofy Ristianty | D26: F1B006024 | E26: Simulasi Analisa Unjuk Kerja Transmisi Paket Data pada Jaringan GSM (Global System For Mobile) Menggunakan Network Simulator - 2 (NS2) | F26: =VLOOKUP(Q26,dosen,3,0) -> Muhamad Syamsu Iqbal, S.T., M.T., Ph.D. | G26: =VLOOKUP(R26,dosen,3,0) -> Heri Wijayanto, S.T., M.T. | H26: =VLOOKUP(S26,dosen,3,0) -> Sudi M. Al Sasongko, S.T., M.T. | I26: =VLOOKUP(T26,dosen,3,0) -> Made Sutha Yadnya, S.T., M.T. | J26: =VLOOKUP(U26,dosen,3,0) -> Dr. Ir. Misbahuddin, S.T., M.T., IPU. | K26: Kamis | L26: 40486 | M26: 10.00-12.00 | N26: R. D2 | Q26: 18 | R26: 32 | S26: 6 | T26: 19 | U26: 7
A27: 1 | B27: 40498 | C27: =VLOOKUP(D27,'[11]mhs elektro-kecil'!$B$5:$C$993,2,0) -> En Mahsyar | D27: F1B006021 | E27: Perencanaan Instalasi Listrik yang Optimal dalam Menekan Pengaruh Interferensi Gelombang Elektromagnetik di Observatorium Geomagnetik Lombok (OGL) | F27: =VLOOKUP(Q27,dosen,3,0) -> Dr. rer. nat. Teti Zubaidah, S.T., M.T. | G27: =VLOOKUP(R27,dosen,3,0) -> Sultan, S.T., M.T. | H27: =VLOOKUP(S27,dosen,3,0) -> Abdul Natsir, S.T., M.T. | I27: =VLOOKUP(T27,dosen,3,0) -> Dr. Ir. Rosmaliati, S.T., M.T. | J27: =VLOOKUP(U27,dosen,3,0) -> Ir. I Made Ari Nrartha, S.T., M.T. | K27: Sabtu | L27: 40502 | M27: 08.00-10.00 | N27: R. D2 | Q27: 22 | R27: 5 | S27: 14 | T27: 16 | U27: 25
A28: =A27+1 -> 2 | B28: 40498 | C28: =VLOOKUP(D28,'[11]mhs elektro-kecil'!$B$5:$C$993,2,0) -> Ni Nyoman Novita S | D28: F1B005058 | E28: Kajian Tarif Biaya Hak Penggunaan (BHP) Frekuensi Sistem Seluler | F28: =VLOOKUP(Q28,dosen,3,0) -> Muhamad Syamsu Iqbal, S.T., M.T., Ph.D. | G28: =VLOOKUP(R28,dosen,3,0) -> Sudi M. Al Sasongko, S.T., M.T. | H28: =VLOOKUP(S28,dosen,3,0) -> Made Sutha Yadnya, S.T., M.T. | I28: =VLOOKUP(T28,dosen,3,0) -> Abdullah Zainuddin, S.T., M.T. | J28: =VLOOKUP(U28,dosen,3,0) -> Bulkis Kanata, S.T., M.T. | K28: Sabtu | L28: 40502 | M28: 08.00-10.00 | N28: R. Studio | Q28: 18 | R28: 6 | S28: 19 | T28: 15 | U28: 21
A29: =A28+1 -> 3 | B29: 40498 | C29: =VLOOKUP(D29,'[11]mhs elektro-kecil'!$B$5:$C$993,2,0) -> Akbar Satryantho | D29: F1B005004 | E29: Sistem Kontrol dan Monitoring Meteo Payload Roket sebagai Aplikasi Pemantau Suhu dan Kelembaban diudara Menggunakan Teknologi Wireless YS-1020 | F29: =VLOOKUP(Q29,dosen,3,0) -> I Made Budi Suksmadana, S.T., M.T. | G29: =VLOOKUP(R29,dosen,3,0) -> Paniran, S.T., M.T. | H29: =VLOOKUP(S29,dosen,3,0) -> Supriono, S.T., M.T. | I29: =VLOOKUP(T29,dosen,3,0) -> Syafaruddin Ch, S.T., M.T. | J29: =VLOOKUP(U29,dosen,3,0) -> Muhamad Irwan, S.T., M.T. | K29: Sabtu | L29: 40502 | M29: 10.00-12.00 | N29: R. D2 | Q29: 24 | R29: 28 | S29: 29 | T29: 4 | U29: 39
A30: =A29+1 -> 4 | B30: 40498 | C30: =VLOOKUP(D30,'[11]mhs elektro-kecil'!$B$5:$C$993,2,0) -> Rosiawan | D30: F1B006073 | E30: Pengukuran dan Analisa Pengaruh Interferensi terhadap Quality of Service (QOS) pada Standar Jaringan 802.11B | F30: =VLOOKUP(Q30,dosen,3,0) -> Abdullah Zainuddin, S.T., M.T. | G30: =VLOOKUP(R30,dosen,3,0) -> Sudi M. Al Sasongko, S.T., M.T. | H30: =VLOOKUP(S30,dosen,3,0) -> Muhamad Syamsu Iqbal, S.T., M.T., Ph.D. | I30: =VLOOKUP(T30,dosen,3,0) -> Bulkis Kanata, S.T., M.T. | J30: =VLOOKUP(U30,dosen,3,0) -> Djul Fikry Budiman, S.T., M.T. | K30: Sabtu | L30: 40502 | M30: 10.00-12.00 | N30: R. Studio | Q30: 15 | R30: 6 | S30: 18 | T30: 21 | U30: 35
A31: 2 | B31: 40505 | C31: =VLOOKUP(D31,'[11]mhs elektro-kecil'!$B$5:$C$993,2,0) -> M. Septiadi Rangga Permana | D31: F1B006054 | E31: Pembangkit Kode Batang Unik Menggunakan Fungsi Hash SHA-512 | F31: =VLOOKUP(Q31,dosen,3,0) -> Heri Wijayanto, S.T., M.T. | G31: =VLOOKUP(R31,dosen,3,0) -> Dr. Rismon H. Sianipar, S.T., M. Eng. | H31: =VLOOKUP(S31,dosen,3,0) -> Budi Irmawati, S. Kom., M.T. | I31: =VLOOKUP(T31,dosen,3,0) -> I B K Widiartha, S.T., M.T. | J31: =VLOOKUP(U31,dosen,3,0) -> Ir. Sri Endang Anjarwani, M. Kom. | K31: Sabtu | L31: 40509 | M31: 08.00-10.00 | N31: R. Studio | Q31: 32 | R31: 33 | S31: 20 | T31: 27 | U31: 38
A32: 3 | B32: 40505 | C32: =VLOOKUP(D32,'[11]mhs elektro-kecil'!$B$5:$C$993,2,0) -> Taufan Timur | D32: F1B005074 | E32: Implementasi Algoritma LZ77 dengan Metode Kompresi Bit Menggunakan Adaptive Huffman untuk Kompresi File Teks | F32: =VLOOKUP(Q32,dosen,3,0) -> Dr. Rismon H. Sianipar, S.T., M. Eng. | G32: =VLOOKUP(R32,dosen,3,0) -> Heri Wijayanto, S.T., M.T. | H32: =VLOOKUP(S32,dosen,3,0) -> I B K Widiartha, S.T., M.T. | I32: =VLOOKUP(T32,dosen,3,0) -> Lalu A. Syamsul Irfan A., S.T., M.Eng. | J32: =VLOOKUP(U32,dosen,3,0) -> Ir. Sri Endang Anjarwani, M. Kom. | K32: Sabtu | L32: 40509 | M32: 10.00-12.00 | N32: R. Studio | Q32: 33 | R32: 32 | S32: 27 | T32: 40 | U32: 38
A33: 1 | B33: 40518 | C33: =VLOOKUP(D33,'[11]mhs elektro-kecil'!$B$5:$C$993,2,0) -> Rosihan Musa | D33: F1B005063 | E33: Optimalisasi Perencanaan Sistem Penerangan yang Hemat Energi pada Gedung Observatorium Geomagnet Lombok | F33: =VLOOKUP(Q33,dosen,3,0) -> Dr. rer. nat. Teti Zubaidah, S.T., M.T. | G33: =VLOOKUP(R33,dosen,3,0) -> Sultan, S.T., M.T. | H33: =VLOOKUP(S33,dosen,3,0) -> Ni Made Seniari, S.T., M.T. | I33: =VLOOKUP(T33,dosen,3,0) -> Supriyatna, S.T., M.T. | J33: =VLOOKUP(U33,dosen,3,0) -> Ir. Agung Budi Muljono, S.T., M.T., IPU. | K33: Sabtu | L33: 40523 | M33: 10.00-12.00 | N33: R. D2 | Q33: 22 | R33: 5 | S33: 1 | T33: 2 | U33: 13
A34: =A33+1 -> 2 | B34: 40505 | C34: =VLOOKUP(D34,'[11]mhs elektro-kecil'!$B$5:$C$993,2,0) -> Dwi Agussusanti F. | D34: F1B006020 | E34: Simulasi dan Analisa BAS (Building Automation System) Berbasis Jaringan Sensor Nirkabel untuk Manajemen Energi Menggunakan Network Simulator 2 | F34: =VLOOKUP(Q34,dosen,3,0) -> Muhamad Syamsu Iqbal, S.T., M.T., Ph.D. | G34: =VLOOKUP(R34,dosen,3,0) -> I Made Budi Suksmadana, S.T., M.T. | H34: =VLOOKUP(S34,dosen,3,0) -> Bulkis Kanata, S.T., M.T. | I34: =VLOOKUP(T34,dosen,3,0) -> Djul Fikry Budiman, S.T., M.T. | J34: =VLOOKUP(U34,dosen,3,0) -> Made Sutha Yadnya, S.T., M.T. | K34: Sabtu | L34: 40509 | M34: 10.00-12.00 | N34: R. D2 | Q34: 18 | R34: 24 | S34: 21 | T34: 35 | U34: 19
A35: =#REF!+1 -> #REF! | B35: 40518 | C35: =VLOOKUP(D35,'[11]mhs elektro-kecil'!$B$5:$C$993,2,0) -> Rosihan Musa | D35: F1B005063 | E35: Optimalisasi Perencanaan Sistem Penerangan yang Hemat Energi pada Gedung Observatorium Geomagnet Lombok | F35: =VLOOKUP(Q35,dosen,3,0) -> Dr. rer. nat. Teti Zubaidah, S.T., M.T. | G35: =VLOOKUP(R35,dosen,3,0) -> Sultan, S.T., M.T. | H35: =VLOOKUP(S35,dosen,3,0) -> Ni Made Seniari, S.T., M.T. | I35: =VLOOKUP(T35,dosen,3,0) -> Supriyatna, S.T., M.T. | J35: =VLOOKUP(U35,dosen,3,0) -> Ir. Agung Budi Muljono, S.T., M.T., IPU. | K35: Sabtu | L35: 40523 | M35: 10.00-12.00 | N35: R. D2 | Q35: 22 | R35: 5 | S35: 1 | T35: 2 | U35: 13
A36: 1 | B36: 40527 | C36: =VLOOKUP(D36,'[11]mhs elektro-kecil'!$B$5:$C$993,2,0) -> Ni Nym. Komala Pradini | D36: F1B006064 | E36: Analisis Pengurangan Harmonisa Transformator Distribusi dengan Menggunakan Filter Pasif (STF dan HDF) | F36: =VLOOKUP(Q36,dosen,3,0) -> Ni Made Seniari, S.T., M.T. | G36: =VLOOKUP(R36,dosen,3,0) -> Sabar Nababan, S.T., M.T. | H36: =VLOOKUP(S36,dosen,3,0) -> Dr. Ir. I Ketut Wiryajati,ST.,MT.,IPU.,ASEAN.Eng. | I36: =VLOOKUP(T36,dosen,3,0) -> Ir. I Made Ari Nrartha, S.T., M.T. | J36: =VLOOKUP(U36,dosen,3,0) -> Supriono, S.T., M.T. | K36: Senin | L36: 40532 | M36: 08.00-10.00 | N36: Lab. LD | Q36: 1 | R36: 31 | S36: 3 | T36: 25 | U36: 29
A37: =A36+1 -> 2 | B37: 40539 | C37: =VLOOKUP(D37,'[11]mhs elektro-kecil'!$B$5:$C$993,2,0) -> Linda Rahmawati S. | D37: F1B006049 | E37: Aplikasi Penerjemah Bahasa Sasak Ke Bahasa Indonesia dengan Menggunakan Metode Parsing Brute Force | F37: =VLOOKUP(Q37,dosen,3,0) -> Heri Wijayanto, S.T., M.T. | G37: =VLOOKUP(R37,dosen,3,0) -> Budi Irmawati, S. Kom., M.T. | H37: =VLOOKUP(S37,dosen,3,0) -> Dr. Ir. Misbahuddin, S.T., M.T., IPU. | I37: =VLOOKUP(T37,dosen,3,0) -> Lalu A. Syamsul Irfan A., S.T., M.Eng. | J37: =VLOOKUP(U37,dosen,3,0) -> Ir. Sri Endang Anjarwani, M. Kom. | K37: Rabu | L37: 40541 | M37: 08.00-10.00 | N37: R. D2 | Q37: 32 | R37: 20 | S37: 7 | T37: 40 | U37: 38
A38: =A37+1 -> 3 | B38: 40543 | C38: =VLOOKUP(D38,'[11]mhs elektro-kecil'!$B$5:$C$993,2,0) -> Rita Dewi Sukmawati S. | D38: F1B006072 | E38: Analisa Kelayakan Implementasi Layanan VoIP (Voice Over Internet Protocol) Menggunakan Jaringan WLAN (Wireless Local Area Network) di Fakultas Teknik Unram | F38: =VLOOKUP(Q38,dosen,3,0) -> Heri Wijayanto, S.T., M.T. | G38: =VLOOKUP(R38,dosen,3,0) -> Muhamad Syamsu Iqbal, S.T., M.T., Ph.D. | H38: =VLOOKUP(S38,dosen,3,0) -> Sudi M. Al Sasongko, S.T., M.T. | I38: =VLOOKUP(T38,dosen,3,0) -> I B K Widiartha, S.T., M.T. | J38: =VLOOKUP(U38,dosen,3,0) -> Dr. Ir. Misbahuddin, S.T., M.T., IPU. | K38: Senin | L38: 40181 | M38: 08.00-10.00 | N38: R. D2 | Q38: 32 | R38: 18 | S38: 6 | T38: 27 | U38: 7
A39: 1 | B39: 40554 | C39: =VLOOKUP(D39,'[11]mhs elektro-kecil'!$B$5:$C$993,2,0) -> Thendriani Yastenti | D39: F1B006081 | E39: Peta Interaktif untuk Pencarian Rute terpendek Jaringan Jalan Kota Mataram Berbasis Algoritma DJIKSTRA Shortest Path Menggunakan Adobe Flash 7 | F39: =VLOOKUP(Q39,dosen,3,0) -> Heri Wijayanto, S.T., M.T. | G39: =VLOOKUP(R39,dosen,3,0) -> I B K Widiartha, S.T., M.T. | H39: =VLOOKUP(S39,dosen,3,0) -> Dr. Ir. Misbahuddin, S.T., M.T., IPU. | I39: =VLOOKUP(T39,dosen,3,0) -> Muhamad Irwan, S.T., M.T. | J39: =VLOOKUP(U39,dosen,3,0) -> Lalu A. Syamsul Irfan A., S.T., M.Eng. | K39: Sabtu | L39: 40558 | M39: 08.00-10.00 | N39: R. Studio | Q39: 32 | R39: 27 | S39: 7 | T39: 39 | U39: 40
A40: =A39+1 -> 2 | B40: 40554 | C40: =VLOOKUP(D40,'[11]mhs elektro-kecil'!$B$5:$C$993,2,0) -> Das Rizal | D40: F1B006015 | E40: Perbaikan Kinerja PLTS dengan Simulasi Minimalisasi Harmonisa pada PLTS Dusun Selak, Lombok Tengah | F40: =VLOOKUP(Q40,dosen,3,0) -> Sabar Nababan, S.T., M.T. | G40: =VLOOKUP(R40,dosen,3,0) -> Supriono, S.T., M.T. | H40: =VLOOKUP(S40,dosen,3,0) -> Ida Bagus Fery Citarsa, S.T., M.T. | I40: =VLOOKUP(T40,dosen,3,0) -> Abdul Natsir, S.T., M.T. | J40: =VLOOKUP(U40,dosen,3,0) -> Dr. Ir. Rosmaliati, S.T., M.T. | K40: Sabtu | L40: 40558 | M40: 08.00-10.00 | N40: R. D2 | Q40: 31 | R40: 29 | S40: 12 | T40: 14 | U40: 16
A41: =A40+1 -> 3 | B41: 40554 | C41: =VLOOKUP(D41,'[11]mhs elektro-kecil'!$B$5:$C$993,2,0) -> Eva Rosdiana Dewi | D41: F1B006022 | E41: Pengukuran dan Analisa Pengaruh Interferensi terhadap Kuat Sinyal yang diterima Propagasi Kanal Radio dalam Ruang pada Frekuensi 2,4 GHz | F41: =VLOOKUP(Q41,dosen,3,0) -> Abdullah Zainuddin, S.T., M.T. | G41: =VLOOKUP(R41,dosen,3,0) -> Sudi M. Al Sasongko, S.T., M.T. | H41: =VLOOKUP(S41,dosen,3,0) -> Djul Fikry Budiman, S.T., M.T. | I41: =VLOOKUP(T41,dosen,3,0) -> Syafaruddin Ch, S.T., M.T. | J41: =VLOOKUP(U41,dosen,3,0) -> Made Sutha Yadnya, S.T., M.T. | K41: Sabtu | L41: 40558 | M41: 10.00-12.00 | N41: R. Studio | Q41: 15 | R41: 6 | S41: 35 | T41: 4 | U41: 19
A42: 5 | B42: 40554 | C42: =VLOOKUP(D42,'[11]mhs elektro-kecil'!$B$5:$C$993,2,0) -> Abdul Ra'uf Alfansani | D42: F1B006002 | E42: Teknik Penyandian dan Penyembunyian Data Berbasis Algoritma Kriptosistem El Gamal dan Algoritma SVD (Singular Value Decomposition) | F42: =VLOOKUP(Q42,dosen,3,0) -> Dr. Rismon H. Sianipar, S.T., M. Eng. | G42: =VLOOKUP(R42,dosen,3,0) -> Muhamad Irwan, S.T., M.T. | H42: =VLOOKUP(S42,dosen,3,0) -> Heri Wijayanto, S.T., M.T. | I42: =VLOOKUP(T42,dosen,3,0) -> I B K Widiartha, S.T., M.T. | J42: =VLOOKUP(U42,dosen,3,0) -> Lalu A. Syamsul Irfan A., S.T., M.Eng. | K42: Sabtu | L42: 40558 | M42: 10.00-12.00 | N42: R. D2 | Q42: 33 | R42: 39 | S42: 32 | T42: 27 | U42: 40
A43: 4 | B43: 40556 | C43: =VLOOKUP(D43,'[11]mhs elektro-kecil'!$B$5:$C$993,2,0) -> Agung Surya Wiguna | D43: F1B006004 | E43: Merekonstruksi Virus Melissa dan Pengembangan Fiturnya untuk Menghapus File-file Kritis dan Menghapus Semua File pada Drive D dan Cara Mengatasinya | F43: =VLOOKUP(Q43,dosen,3,0) -> Dr. Rismon H. Sianipar, S.T., M. Eng. | G43: =VLOOKUP(R43,dosen,3,0) -> Heri Wijayanto, S.T., M.T. | H43: =VLOOKUP(S43,dosen,3,0) -> I B K Widiartha, S.T., M.T. | I43: =VLOOKUP(T43,dosen,3,0) -> Ir. Sri Endang Anjarwani, M. Kom. | J43: =VLOOKUP(U43,dosen,3,0) -> I Made Budi Suksmadana, S.T., M.T. | K43: Senin | L43: 40560 | M43: 08.00-10.00 | N43: R. D2 | Q43: 33 | R43: 32 | S43: 27 | T43: 38 | U43: 24
A44: 6 | B44: 40571 | C44: =VLOOKUP(D44,'[11]mhs elektro-kecil'!$B$5:$C$993,2,0) -> I Nyoman Gede Aryarta | D44: F1B006035 | E44: Identifikasi Karakteristik Suara Mesin Asinkron 3 Fasa terhadap Kerusakan Akibat Pembebanan Lebih dengan Metode FFT (Fast Fourier Transform) | F44: =VLOOKUP(Q44,dosen,3,0) -> Dr. Ir. I Ketut Wiryajati,ST.,MT.,IPU.,ASEAN.Eng. | G44: =VLOOKUP(R44,dosen,3,0) -> Dr. Rismon H. Sianipar, S.T., M. Eng. | H44: =VLOOKUP(S44,dosen,3,0) -> Ida Bagus Fery Citarsa, S.T., M.T. | I44: =VLOOKUP(T44,dosen,3,0) -> Ir. Agung Budi Muljono, S.T., M.T., IPU. | J44: =VLOOKUP(U44,dosen,3,0) -> Bulkis Kanata, S.T., M.T. | K44: Senin | L44: 40574 | M44: 08.00-10.00 | N44: R. D2 | Q44: 3 | R44: 33 | S44: 12 | T44: 13 | U44: 21
A45: 7 | B45: 40571 | C45: =VLOOKUP(D45,'[11]mhs elektro-kecil'!$B$5:$C$993,2,0) -> Ibnu Shina | D45: F1B006037 | E45: Identifikasi Karakteristik Suara Mesin DC Eksitasi Diri terhadap Kerusakan Akibat Pembebanan Lebih dengan Metode Wavelet | F45: =VLOOKUP(Q45,dosen,3,0) -> Dr. Ir. I Ketut Wiryajati,ST.,MT.,IPU.,ASEAN.Eng. | G45: =VLOOKUP(R45,dosen,3,0) -> Dr. Rismon H. Sianipar, S.T., M. Eng. | H45: =VLOOKUP(S45,dosen,3,0) -> Ir. I Made Ari Nrartha, S.T., M.T. | I45: =VLOOKUP(T45,dosen,3,0) -> Dr. rer. nat. Teti Zubaidah, S.T., M.T. | J45: =VLOOKUP(U45,dosen,3,0) -> Paniran, S.T., M.T. | K45: Senin | L45: 40574 | M45: 10.00-12.00 | N45: R. Studio | Q45: 3 | R45: 33 | S45: 25 | T45: 22 | U45: 28
A46: 8 | B46: 40571 | C46: =VLOOKUP(D46,'[11]mhs elektro-kecil'!$B$5:$C$993,2,0) -> Indra Darmawan | D46: F1B006041 | E46: Identifikasi Karakteristik Suara Mesin Asinkron 3 Fasa terhadap Kerusakan Akibat Pembebanan Lebih dengan Metode DCT (Discrete Cosine Transform) | F46: =VLOOKUP(Q46,dosen,3,0) -> Dr. Ir. I Ketut Wiryajati,ST.,MT.,IPU.,ASEAN.Eng. | G46: =VLOOKUP(R46,dosen,3,0) -> Dr. Rismon H. Sianipar, S.T., M. Eng. | H46: =VLOOKUP(S46,dosen,3,0) -> Abdul Natsir, S.T., M.T. | I46: =VLOOKUP(T46,dosen,3,0) -> Dr. Ir. Rosmaliati, S.T., M.T. | J46: =VLOOKUP(U46,dosen,3,0) -> Supriono, S.T., M.T. | K46: Selasa | L46: 40575 | M46: 08.00-10.00 | N46: R. Studio | Q46: 3 | R46: 33 | S46: 14 | T46: 16 | U46: 29
A47: 1 | B47: 40590 | C47: =VLOOKUP(D47,'[11]mhs elektro-kecil'!$B$5:$C$993,2,0) -> Salimyul Pathurrahman | D47: F1B006075 | E47: Pengolahan Sinyal Fluktuasi Geomagnetik untuk Analisa Aktifitas Seismik Regional Menggunakan Prosedur Diferensiasi (Moving Average) dan Metode Analisis Polarisasi Magnetik | F47: =VLOOKUP(Q47,dosen,3,0) -> Bulkis Kanata, S.T., M.T. | G47: =VLOOKUP(R47,dosen,3,0) -> Dr. rer. nat. Teti Zubaidah, S.T., M.T. | H47: =VLOOKUP(S47,dosen,3,0) -> Abdullah Zainuddin, S.T., M.T. | I47: =VLOOKUP(T47,dosen,3,0) -> I Made Budi Suksmadana, S.T., M.T. | J47: =VLOOKUP(U47,dosen,3,0) -> Ni Made Seniari, S.T., M.T. | K47: Jum'at | L47: 40592 | M47: 08.00-10.00 | N47: R. Studio | Q47: 21 | R47: 22 | S47: 15 | T47: 24 | U47: 1
A48: =A47+1 -> 2 | B48: 40590 | C48: =VLOOKUP(D48,'[11]mhs elektro-kecil'!$B$5:$C$993,2,0) -> Suhaidi | D48: F1B004072 | E48: Pengukuran Kandungan Sedimen Suspensi dengan Metode Intensitas Cahaya Berbasis Mikrokontroller AVR ATMEGA 8535 | F48: =VLOOKUP(Q48,dosen,3,0) -> Supriono, S.T., M.T. | G48: =VLOOKUP(R48,dosen,3,0) -> Bulkis Kanata, S.T., M.T. | H48: =VLOOKUP(S48,dosen,3,0) -> Sudi M. Al Sasongko, S.T., M.T. | I48: =VLOOKUP(T48,dosen,3,0) -> Made Sutha Yadnya, S.T., M.T. | J48: =VLOOKUP(U48,dosen,3,0) -> Paniran, S.T., M.T. | K48: Sabtu | L48: 40593 | M48: 08.00-10.00 | N48: R. Studio | Q48: 29 | R48: 21 | S48: 6 | T48: 19 | U48: 28
A49: =A48+1 -> 3 | B49: 40590 | C49: =VLOOKUP(D49,'[11]mhs elektro-kecil'!$B$5:$C$993,2,0) -> Shinta Primasari | D49: F1B006076 | E49: Simulasi Propagasi Pentransmisian LMDS untuk Redaman Hujan pada Daerah Mataram - Sesaot | F49: =VLOOKUP(Q49,dosen,3,0) -> Made Sutha Yadnya, S.T., M.T. | G49: =VLOOKUP(R49,dosen,3,0) -> Bulkis Kanata, S.T., M.T. | H49: =VLOOKUP(S49,dosen,3,0) -> Muhamad Syamsu Iqbal, S.T., M.T., Ph.D. | I49: =VLOOKUP(T49,dosen,3,0) -> Abdullah Zainuddin, S.T., M.T. | J49: =VLOOKUP(U49,dosen,3,0) -> Djul Fikry Budiman, S.T., M.T. | K49: Sabtu | L49: 40593 | M49: 10.00-12.00 | N49: R. Studio | Q49: 19 | R49: 21 | S49: 18 | T49: 15 | U49: 35
A50: =A49+1 -> 4 | B50: 40590 | C50: =VLOOKUP(D50,'[11]mhs elektro-kecil'!$B$5:$C$993,2,0) -> Kenyya Venaringan De Side | D50: F1B006044 | E50: Perancangan Pengatur Catu Daya Hybrid Otomatis pada Observatorium Geomagnetik Lombok (OGL) | F50: =VLOOKUP(Q50,dosen,3,0) -> Dr. rer. nat. Teti Zubaidah, S.T., M.T. | G50: =VLOOKUP(R50,dosen,3,0) -> Paniran, S.T., M.T. | H50: =VLOOKUP(S50,dosen,3,0) -> Ir. I Made Ari Nrartha, S.T., M.T. | I50: =VLOOKUP(T50,dosen,3,0) -> Supriyatna, S.T., M.T. | J50: =VLOOKUP(U50,dosen,3,0) -> Ida Bagus Fery Citarsa, S.T., M.T. | K50: Sabtu | L50: 40593 | M50: 08.00-10.00 | N50: R. D2 | Q50: 22 | R50: 28 | S50: 25 | T50: 2 | U50: 12
A51: =A50+1 -> 5 | B51: 40590 | C51: =VLOOKUP(D51,'[11]mhs elektro-kecil'!$B$5:$C$993,2,0) -> R. R. Dwie Rosmiyati | D51: F1B006074 | E51: Sistem Pendukung Keputusan Seleksi Penentuan Jabatan pada PT. PLN (Persero) dengan Metode Profile Matching | F51: =VLOOKUP(Q51,dosen,3,0) -> Heri Wijayanto, S.T., M.T. | G51: =VLOOKUP(R51,dosen,3,0) -> Dr. Ir. Misbahuddin, S.T., M.T., IPU. | H51: =VLOOKUP(S51,dosen,3,0) -> Budi Irmawati, S. Kom., M.T. | I51: =VLOOKUP(T51,dosen,3,0) -> Dr. Rismon H. Sianipar, S.T., M. Eng. | J51: =VLOOKUP(U51,dosen,3,0) -> Dr. Ir. Rosmaliati, S.T., M.T. | K51: Sabtu | L51: 40593 | M51: 10.00-12.00 | N51: R. D2 | Q51: 32 | R51: 7 | S51: 20 | T51: 33 | U51: 16
A52: 1 | B52: 40602 | C52: =VLOOKUP(D52,'[11]mhs elektro-kecil'!$B$5:$C$993,2,0) -> Mardiyah Hidayati | D52: F1B006056 | E52: Implementasi Algoritma Best First Search (BFS) untuk Permainan CIWA (congklak sasak) Menggunakan Java Server Pages (JSP) | F52: =VLOOKUP(Q52,dosen,3,0) -> Heri Wijayanto, S.T., M.T. | G52: =VLOOKUP(R52,dosen,3,0) -> Budi Irmawati, S. Kom., M.T. | H52: =VLOOKUP(S52,dosen,3,0) -> I B K Widiartha, S.T., M.T. | I52: =VLOOKUP(T52,dosen,3,0) -> Dr. Rismon H. Sianipar, S.T., M. Eng. | J52: =VLOOKUP(U52,dosen,3,0) -> Dr. Ir. Misbahuddin, S.T., M.T., IPU. | K52: Kamis | L52: 40605 | M52: 14.00-16.00 | N52: R. D2 | Q52: 32 | R52: 20 | S52: 27 | T52: 33 | U52: 7 | X52: =L52 -> 40605 | Y52: =X52+180 -> 40785
A53: =A52+1 -> 2 | B53: 40602 | C53: =VLOOKUP(D53,'[11]mhs elektro-kecil'!$B$5:$C$993,2,0) -> Suwandi Jaya Pratama | D53: F1B006078 | E53: Perancangan Sistem Telemetri Suhu Berbasis Layanan SMS (short message servive) Jaringan GSM untuk Pemantauan Aktifitas Serta Peringatan Dini Bencana Gunung Merapi | F53: =VLOOKUP(Q53,dosen,3,0) -> Abdullah Zainuddin, S.T., M.T. | G53: =VLOOKUP(R53,dosen,3,0) -> #N/A | H53: =VLOOKUP(S53,dosen,3,0) -> Bulkis Kanata, S.T., M.T. | I53: =VLOOKUP(T53,dosen,3,0) -> Djul Fikry Budiman, S.T., M.T. | J53: =VLOOKUP(U53,dosen,3,0) -> Muhamad Syamsu Iqbal, S.T., M.T., Ph.D. | K53: Kamis | L53: 40605 | M53: 14.00-16.00 | N53: R. Studio | Q53: 15 | S53: 21 | T53: 35 | U53: 18 | X53: =L53 -> 40605 | Y53: =X53+180 -> 40785
A54: =A53+1 -> 3 | B54: 40602 | C54: =VLOOKUP(D54,'[11]mhs elektro-kecil'!$B$5:$C$993,2,0) -> M. Riza Rizky | D54: F1B006058 | E54: Optimasi Ekonomi Dispacth Pembangkit Termal Sistem Kelistrikan Lombok dengan Menggunakan Metode MIPSO | F54: =VLOOKUP(Q54,dosen,3,0) -> Supriyatna, S.T., M.T. | G54: =VLOOKUP(R54,dosen,3,0) -> Dr. Ir. Misbahuddin, S.T., M.T., IPU. | H54: =VLOOKUP(S54,dosen,3,0) -> Abdul Natsir, S.T., M.T. | I54: =VLOOKUP(T54,dosen,3,0) -> Ir. Agung Budi Muljono, S.T., M.T., IPU. | J54: =VLOOKUP(U54,dosen,3,0) -> Sultan, S.T., M.T. | K54: Jum'at | L54: 40606 | M54: 09.30-11.30 | N54: Lab. Tenaga | Q54: 2 | R54: 7 | S54: 14 | T54: 13 | U54: 5 | X54: =L54 -> 40606 | Y54: =X54+180 -> 40786
A55: 1 | B55: 40623 | C55: =VLOOKUP(D55,'[11]mhs elektro-kecil'!$B$5:$C$993,2,0) -> Azhari Hasbi | D55: F1B005008 | E55: Desain dan Implementasi Jaringan Hotspot Fakultas Teknik Universitas Mataram Menggunakan Chillispot Autentifikasi System dan Radius Server | F55: =VLOOKUP(Q55,dosen,3,0) -> I B K Widiartha, S.T., M.T. | G55: =VLOOKUP(R55,dosen,3,0) -> Dr. Ir. Misbahuddin, S.T., M.T., IPU. | H55: =VLOOKUP(S55,dosen,3,0) -> Budi Irmawati, S. Kom., M.T. | I55: =VLOOKUP(T55,dosen,3,0) -> Ir. Sri Endang Anjarwani, M. Kom. | J55: =VLOOKUP(U55,dosen,3,0) -> Lalu A. Syamsul Irfan A., S.T., M.Eng. | K55: Kamis | L55: 40626 | M55: 14.00-16.00 | N55: R. D2 | O55: 40617 | Q55: 27 | R55: 7 | S55: 20 | T55: 38 | U55: 40 | W55: 40616 | X55: =L55 -> 40626 | Y55: =X55+180 -> 40806
A56: 1 | B56: 40625 | C56: =VLOOKUP(D56,'[11]mhs elektro-kecil'!$B$5:$C$993,2,0) -> Arya Bambang Sastra G. | D56: F1B006012 | E56: Pemanfaatan Algoritma Ant Colony System (ACS) untuk Penyelesaian Masalah Penjadwalan Praktikum pada Jurusan Teknik Elektro Universitas Mataram | F56: =VLOOKUP(Q56,dosen,3,0) -> Heri Wijayanto, S.T., M.T. | G56: =VLOOKUP(R56,dosen,3,0) -> Dr. Ir. Misbahuddin, S.T., M.T., IPU. | H56: =VLOOKUP(S56,dosen,3,0) -> Ir. Sri Endang Anjarwani, M. Kom. | I56: =VLOOKUP(T56,dosen,3,0) -> Budi Irmawati, S. Kom., M.T. | J56: =VLOOKUP(U56,dosen,3,0) -> Supriyatna, S.T., M.T. | K56: Sabtu | L56: 40628 | M56: 10.00-12.00 | N56: R. Studio | O56: 40621 | Q56: 32 | R56: 7 | S56: 38 | T56: 20 | U56: 2 | W56: 40616 | X56: =L56 -> 40628 | Y56: =X56+180 -> 40808
A57: 1 | B57: 40630 | C57: =VLOOKUP(D57,'[11]mhs elektro-kecil'!$B$5:$C$993,2,0) -> Supriadi | D57: F1B004073 | E57: Perancangan dan Pembuatan Alat Ukur Kadar Alkohol dengan Osilator Berbasis Mikrontroller ATMEGA 8535 | F57: =VLOOKUP(Q57,dosen,3,0) -> Supriono, S.T., M.T. | G57: =VLOOKUP(R57,dosen,3,0) -> I Made Budi Suksmadana, S.T., M.T. | H57: =VLOOKUP(S57,dosen,3,0) -> Syafaruddin Ch, S.T., M.T. | I57: =VLOOKUP(T57,dosen,3,0) -> Dr. Ir. I Ketut Wiryajati,ST.,MT.,IPU.,ASEAN.Eng. | J57: =VLOOKUP(U57,dosen,3,0) -> Muhamad Irwan, S.T., M.T. | K57: Kamis | L57: 40633 | M57: 09.30-11.30 | N57: Lab. Kendali | Q57: 29 | R57: 24 | S57: 4 | T57: 3 | U57: 39 | W57: 40616 | X57: =L57 -> 40633 | Y57: =X57+180 -> 40813
A58: 9 | C58: =VLOOKUP(D58,'[11]mhs elektro-kecil'!$B$5:$C$993,2,0) -> Gst. Bgs. Surya Dharma Wibawa | D58: F1B006027 | E58: Mencari Pola Desain Kain Songket Sasak Menggunakan Fraktal Julia Set | F58: =VLOOKUP(Q58,dosen,3,0) -> Dr. Rismon H. Sianipar, S.T., M. Eng. | G58: =VLOOKUP(R58,dosen,3,0) -> Muhamad Irwan, S.T., M.T. | Q58: 33 | R58: 39
A59: 10 | C59: =VLOOKUP(D59,'[11]mhs elektro-kecil'!$B$5:$C$993,2,0) -> I Wyn Eka Rudytha Harimbawa | D59: F1B006036 | E59: Analisa Tingkat Keacakan dan Kemiripan Nilai Hash Haval dan Tiger Menggunakan Variabel Uji Probabilitas Bersyarat dan Korelasi Silang | F59: =VLOOKUP(Q59,dosen,3,0) -> Dr. Rismon H. Sianipar, S.T., M. Eng. | G59: =VLOOKUP(R59,dosen,3,0) -> Muhamad Irwan, S.T., M.T. | Q59: 33 | R59: 39
A60: 11 | C60: =VLOOKUP(D60,'[11]mhs elektro-kecil'!$B$5:$C$993,2,0) -> Ariyan Nurrahman | D60: F1B006011 | E60: Mencari Pola Desain Kain Batik Yogakarta Menggunakan Fraktal Mandelbrot Set | F60: =VLOOKUP(Q60,dosen,3,0) -> Dr. Rismon H. Sianipar, S.T., M. Eng. | G60: =VLOOKUP(R60,dosen,3,0) -> Muhamad Irwan, S.T., M.T. | Q60: 33 | R60: 39
A61: =A60+1 -> 12 | B61: 40644 | C61: =VLOOKUP(D61,'[12]mhs elektro-kecil'!$B$5:$C$996,2,0) -> Gst. Bgs. Surya Dharma Wibawa | D61: F1B006027 | E61: Mencari Pola Desain Kain Songket Sasak Menggunakan Fraktal Julia Set | F61: =VLOOKUP(Q61,dosen,3,0) -> Dr. Rismon H. Sianipar, S.T., M. Eng. | H61: =VLOOKUP(S61,dosen,3,0) -> Ir. Sri Endang Anjarwani, M. Kom. | I61: =VLOOKUP(T61,dosen,3,0) -> I Made Budi Suksmadana, S.T., M.T. | J61: =VLOOKUP(U61,dosen,3,0) -> Muhamad Irwan, S.T., M.T. | K61: Jum'at | L61: 40648 | M61: 07.30-09.30 | N61: Lab. Komputer | Q61: 33 | S61: 38 | T61: 24 | U61: 39 | X61: =L61 -> 40648 | Y61: =X61+180 -> 40828
